Workbook

Sheet Main_Data
A1: Sector | B1: Year | C1: Month | D1: Cereals and products | E1: Meat and fish | F1: Egg | G1: Milk and products | H1: Oils and fats | I1: Fruits | J1: Vegetables | K1: Pulses and products | L1: Sugar and Confectionery | M1: Spices | N1: Non-alcoholic beverages | O1: Prepared meals, snacks, sweets etc. | P1: Food and beverages | Q1: Pan, tobacco and intoxicants | R1: Clothing | S1: Footwear | T1: Clothing and footwear | U1: Housing | V1: Fuel and light | W1: Household goods and services | X1: Health | Y1: Transport and communication | Z1: Recreation and amusement | AA1: Education | AB1: Personal care and effects | AC1: Miscellaneous | AD1: General index
A2: Rural | B2: 2013 | C2: January | D2: 107.5 | E2: 106.3 | F2: 108.1 | G2: 104.9 | H2: 106.1 | I2: 103.9 | J2: 101.9 | K2: 106.1 | L2: 106.8 | M2: 103.1 | N2: 104.8 | O2: 106.7 | P2: 105.5 | Q2: 105.1 | R2: 106.5 | S2: 105.8 | T2: 106.4 | U2: NA | V2: 105.5 | W2: 104.8 | X2: 104 | Y2: 103.3 | Z2: 103.4 | AA2: 103.8 | AB2: 104.7 | AC2: 104 | AD2: 105.1
A3: Urban | B3: 2013 | C3: January | D3: 110.5 | E3: 109.1 | F3: 113 | G3: 103.6 | H3: 103.4 | I3: 102.3 | J3: 102.9 | K3: 105.8 | L3: 105.1 | M3: 101.8 | N3: 105.1 | O3: 107.9 | P3: 105.9 | Q3: 105.2 | R3: 105.9 | S3: 105 | T3: 105.8 | U3: 100.3 | V3: 105.4 | W3: 104.8 | X3: 104.1 | Y3: 103.2 | Z3: 102.9 | AA3: 103.5 | AB3: 104.3 | AC3: 103.7 | AD3: 104
A4: Rural+Urban | B4: 2013 | C4: January | D4: 108.4 | E4: 107.3 | F4: 110 | G4: 104.4 | H4: 105.1 | I4: 103.2 | J4: 102.2 | K4: 106 | L4: 106.2 | M4: 102.7 | N4: 104.9 | O4: 107.3 | P4: 105.6 | Q4: 105.1 | R4: 106.3 | S4: 105.5 | T4: 106.2 | U4: 100.3 | V4: 105.5 | W4: 104.8 | X4: 104 | Y4: 103.2 | Z4: 103.1 | AA4: 103.6 | AB4: 104.5 | AC4: 103.9 | AD4: 104.6
A5: Rural | B5: 2013 | C5: February | D5: 109.2 | E5: 108.7 | F5: 110.2 | G5: 105.4 | H5: 106.7 | I5: 104 | J5: 102.4 | K5: 105.9 | L5: 105.7 | M5: 103.1 | N5: 105.1 | O5: 107.7 | P5: 106.3 | Q5: 105.6 | R5: 107.1 | S5: 106.3 | T5: 107 | U5: NA | V5: 106.2 | W5: 105.2 | X5: 104.4 | Y5: 103.9 | Z5: 104 | AA5: 104.1 | AB5: 104.6 | AC5: 104.4 | AD5: 105.8
A6: Urban | B6: 2013 | C6: February | D6: 112.9 | E6: 112.9 | F6: 116.9 | G6: 104 | H6: 103.5 | I6: 103.1 | J6: 104.9 | K6: 104.1 | L6: 103.8 | M6: 102.3 | N6: 106 | O6: 109 | P6: 107.2 | Q6: 106 | R6: 106.6 | S6: 105.5 | T6: 106.4 | U6: 100.4 | V6: 105.7 | W6: 105.2 | X6: 104.7 | Y6: 104.4 | Z6: 103.3 | AA6: 103.7 | AB6: 104.3 | AC6: 104.3 | AD6: 104.7
A7: Rural+Urban | B7: 2013 | C7: February | D7: 110.4 | E7: 110.2 | F7: 112.8 | G7: 104.9 | H7: 105.5 | I7: 103.6 | J7: 103.2 | K7: 105.3 | L7: 105.1 | M7: 102.8 | N7: 105.5 | O7: 108.3 | P7: 106.6 | Q7: 105.7 | R7: 106.9 | S7: 106 | T7: 106.8 | U7: 100.4 | V7: 106 | W7: 105.2 | X7: 104.5 | Y7: 104.2 | Z7: 103.6 | AA7: 103.9 | AB7: 104.5 | AC7: 104.4 | AD7: 105.3
A8: Rural | B8: 2013 | C8: March | D8: 110.2 | E8: 108.8 | F8: 109.9 | G8: 105.6 | H8: 106.2 | I8: 105.7 | J8: 101.4 | K8: 105.7 | L8: 105 | M8: 103.3 | N8: 105.6 | O8: 108.2 | P8: 106.6 | Q8: 106.5 | R8: 107.6 | S8: 106.8 | T8: 107.5 | U8: NA | V8: 106.1 | W8: 105.6 | X8: 104.7 | Y8: 104.6 | Z8: 104 | AA8: 104.3 | AB8: 104.3 | AC8: 104.6 | AD8: 106
A9: Urban | B9: 2013 | C9: March | D9: 113.9 | E9: 111.4 | F9: 113.2 | G9: 104.3 | H9: 102.7 | I9: 104.9 | J9: 103.8 | K9: 103.5 | L9: 102.6 | M9: 102.4 | N9: 107 | O9: 109.8 | P9: 107.3 | Q9: 106.8 | R9: 107.2 | S9: 106 | T9: 107 | U9: 100.4 | V9: 106 | W9: 105.7 | X9: 105.2 | Y9: 105.5 | Z9: 103.5 | AA9: 103.8 | AB9: 104.2 | AC9: 104.9 | AD9: 105
A10: Rural+Urban | B10: 2013 | C10: March | D10: 111.4 | E10: 109.7 | F10: 111.2 | G10: 105.1 | H10: 104.9 | I10: 105.3 | J10: 102.2 | K10: 105 | L10: 104.2 | M10: 103 | N10: 106.2 | O10: 108.9 | P10: 106.9 | Q10: 106.6 | R10: 107.4 | S10: 106.5 | T10: 107.3 | U10: 100.4 | V10: 106.1 | W10: 105.6 | X10: 104.9 | Y10: 105.1 | Z10: 103.7 | AA10: 104 | AB10: 104.3 | AC10: 104.7 | AD10: 105.5
A11: Rural | B11: 2013 | C11: April | D11: 110.2 | E11: 109.5 | F11: 106.9 | G11: 106.3 | H11: 105.7 | I11: 108.3 | J11: 103.4 | K11: 105.7 | L11: 104.2 | M11: 103.2 | N11: 106.5 | O11: 108.8 | P11: 107.1 | Q11: 107.1 | R11: 108.1 | S11: 107.4 | T11: 108 | U11: NA | V11: 106.5 | W11: 106.1 | X11: 105.1 | Y11: 104.4 | Z11: 104.5 | AA11: 104.8 | AB11: 102.7 | AC11: 104.6 | AD11: 106.4
A12: Urban | B12: 2013 | C12: April | D12: 114.6 | E12: 113.4 | F12: 106 | G12: 104.7 | H12: 102.1 | I12: 109.5 | J12: 109.7 | K12: 104.6 | L12: 102 | M12: 103.5 | N12: 108.2 | O12: 110.6 | P12: 108.8 | Q12: 108.5 | R12: 107.9 | S12: 106.4 | T12: 107.7 | U12: 100.5 | V12: 106.4 | W12: 106.5 | X12: 105.7 | Y12: 105 | Z12: 104 | AA12: 105.2 | AB12: 103.2 | AC12: 105.1 | AD12: 105.7
A13: Rural+Urban | B13: 2013 | C13: April | D13: 111.6 | E13: 110.9 | F13: 106.6 | G13: 105.7 | H13: 104.4 | I13: 108.9 | J13: 105.5 | K13: 105.3 | L13: 103.5 | M13: 103.3 | N13: 107.2 | O13: 109.6 | P13: 107.7 | Q13: 107.5 | R13: 108 | S13: 107 | T13: 107.9 | U13: 100.5 | V13: 106.5 | W13: 106.3 | X13: 105.3 | Y13: 104.7 | Z13: 104.2 | AA13: 105 | AB13: 102.9 | AC13: 104.8 | AD13: 106.1
A14: Rural | B14: 2013 | C14: May | D14: 110.9 | E14: 109.8 | F14: 105.9 | G14: 107.5 | H14: 105.3 | I14: 108.1 | J14: 107.3 | K14: 106.1 | L14: 103.7 | M14: 104 | N14: 107.4 | O14: 109.9 | P14: 108.1 | Q14: 108.1 | R14: 108.8 | S14: 107.9 | T14: 108.6 | U14: NA | V14: 107.5 | W14: 106.8 | X14: 105.7 | Y14: 104.1 | Z14: 105 | AA14: 105.5 | AB14: 102.1 | AC14: 104.8 | AD14: 107.2
A15: Urban | B15: 2013 | C15: May | D15: 115.4 | E15: 114.2 | F15: 102.7 | G15: 105.5 | H15: 101.5 | I15: 110.6 | J15: 123.7 | K15: 105.2 | L15: 101.9 | M15: 105 | N15: 109.1 | O15: 111.3 | P15: 111.1 | Q15: 109.8 | R15: 108.5 | S15: 106.7 | T15: 108.3 | U15: 100.5 | V15: 107.2 | W15: 107.1 | X15: 106.2 | Y15: 103.9 | Z15: 104.6 | AA15: 105.7 | AB15: 102.6 | AC15: 104.9 | AD15: 106.6
A16: Rural+Urban | B16: 2013 | C16: May | D16: 112.3 | E16: 111.3 | F16: 104.7 | G16: 106.8 | H16: 103.9 | I16: 109.3 | J16: 112.9 | K16: 105.8 | L16: 103.1 | M16: 104.3 | N16: 108.1 | O16: 110.5 | P16: 109.2 | Q16: 108.6 | R16: 108.7 | S16: 107.4 | T16: 108.5 | U16: 100.5 | V16: 107.4 | W16: 106.9 | X16: 105.9 | Y16: 104 | Z16: 104.8 | AA16: 105.6 | AB16: 102.3 | AC16: 104.8 | AD16: 106.9
A17: Rural | B17: 2013 | C17: June | D17: 112.3 | E17: 112.1 | F17: 108.1 | G17: 108.3 | H17: 105.9 | I17: 109.2 | J17: 118 | K17: 106.8 | L17: 104.1 | M17: 105.4 | N17: 108.2 | O17: 111 | P17: 110.6 | Q17: 109 | R17: 109.7 | S17: 108.8 | T17: 109.5 | U17: NA | V17: 108.5 | W17: 107.5 | X17: 106.3 | Y17: 105 | Z17: 105.6 | AA17: 106.5 | AB17: 102.5 | AC17: 105.5 | AD17: 108.9
A18: Urban | B18: 2013 | C18: June | D18: 117 | E18: 120.1 | F18: 112.5 | G18: 107.3 | H18: 101.3 | I18: 112.4 | J18: 143.6 | K18: 105.4 | L18: 101.4 | M18: 106.4 | N18: 110 | O18: 112.2 | P18: 115 | Q18: 110.9 | R18: 109.2 | S18: 107.2 | T18: 108.9 | U18: 106.6 | V18: 108 | W18: 107.7 | X18: 106.5 | Y18: 105.2 | Z18: 105.2 | AA18: 108.1 | AB18: 103.3 | AC18: 106.1 | AD18: 109.7
A19: Rural+Urban | B19: 2013 | C19: June | D19: 113.8 | E19: 114.9 | F19: 109.8 | G19: 107.9 | H19: 104.2 | I19: 110.7 | J19: 126.7 | K19: 106.3 | L19: 103.2 | M19: 105.7 | N19: 109 | O19: 111.6 | P19: 112.2 | Q19: 109.5 | R19: 109.5 | S19: 108.1 | T19: 109.3 | U19: 106.6 | V19: 108.3 | W19: 107.6 | X19: 106.4 | Y19: 105.1 | Z19: 105.4 | AA19: 107.4 | AB19: 102.8 | AC19: 105.8 | AD19: 109.3
A20: Rural | B20: 2013 | C20: July | D20: 113.4 | E20: 114.9 | F20: 110.5 | G20: 109.3 | H20: 106.2 | I20: 110.3 | J20: 129.2 | K20: 107.1 | L20: 104.3 | M20: 106.4 | N20: 109.1 | O20: 112.1 | P20: 113.1 | Q20: 109.8 | R20: 110.5 | S20: 109.5 | T20: 110.3 | U20: NA | V20: 109.5 | W20: 108.3 | X20: 106.9 | Y20: 106.8 | Z20: 106.4 | AA20: 107.8 | AB20: 102.5 | AC20: 106.5 | AD20: 110.7
A21: Urban | B21: 2013 | C21: July | D21: 117.8 | E21: 119.2 | F21: 114 | G21: 108.3 | H21: 101.1 | I21: 113.2 | J21: 160.9 | K21: 105.1 | L21: 101.3 | M21: 107.5 | N21: 110.4 | O21: 113.1 | P21: 117.5 | Q21: 111.7 | R21: 109.8 | S21: 107.8 | T21: 109.5 | U21: 107.7 | V21: 108.6 | W21: 108.1 | X21: 107.1 | Y21: 107.3 | Z21: 105.9 | AA21: 110.1 | AB21: 103.2 | AC21: 107.3 | AD21: 111.4
A22: Rural+Urban | B22: 2013 | C22: July | D22: 114.8 | E22: 116.4 | F22: 111.9 | G22: 108.9 | H22: 104.3 | I22: 111.7 | J22: 140 | K22: 106.4 | L22: 103.3 | M22: 106.8 | N22: 109.6 | O22: 112.6 | P22: 114.7 | Q22: 110.3 | R22: 110.2 | S22: 108.8 | T22: 110 | U22: 107.7 | V22: 109.2 | W22: 108.2 | X22: 107 | Y22: 107.1 | Z22: 106.1 | AA22: 109.1 | AB22: 102.8 | AC22: 106.9 | AD22: 111
A23: Rural | B23: 2013 | C23: August | D23: 114.3 | E23: 115.4 | F23: 111.1 | G23: 110 | H23: 106.4 | I23: 110.8 | J23: 138.9 | K23: 107.4 | L23: 104.1 | M23: 106.9 | N23: 109.7 | O23: 112.6 | P23: 114.9 | Q23: 110.7 | R23: 111.3 | S23: 110.2 | T23: 111.1 | U23: NA | V23: 109.9 | W23: 108.7 | X23: 107.5 | Y23: 107.8 | Z23: 106.8 | AA23: 108.7 | AB23: 105 | AC23: 107.5 | AD23: 112.1
A24: Urban | B24: 2013 | C24: August | D24: 118.3 | E24: 120.4 | F24: 112.7 | G24: 108.9 | H24: 101.1 | I24: 108.7 | J24: 177 | K24: 104.7 | L24: 101 | M24: 108.5 | N24: 110.9 | O24: 114.3 | P24: 119.6 | Q24: 112.4 | R24: 110.6 | S24: 108.3 | T24: 110.2 | U24: 108.9 | V24: 109.3 | W24: 108.7 | X24: 107.6 | Y24: 108.1 | Z24: 106.5 | AA24: 110.8 | AB24: 106 | AC24: 108.3 | AD24: 112.7
A25: Rural+Urban | B25: 2013 | C25: August | D25: 115.6 | E25: 117.2 | F25: 111.7 | G25: 109.6 | H25: 104.5 | I25: 109.8 | J25: 151.8 | K25: 106.5 | L25: 103.1 | M25: 107.4 | N25: 110.2 | O25: 113.4 | P25: 116.6 | Q25: 111.2 | R25: 111 | S25: 109.4 | T25: 110.7 | U25: 108.9 | V25: 109.7 | W25: 108.7 | X25: 107.5 | Y25: 108 | Z25: 106.6 | AA25: 109.9 | AB25: 105.4 | AC25: 107.9 | AD25: 112.4
A26: Rural | B26: 2013 | C26: September | D26: 115.4 | E26: 115.7 | F26: 111.7 | G26: 111 | H26: 107.4 | I26: 110.9 | J26: 154 | K26: 108.1 | L26: 104.2 | M26: 107.9 | N26: 110.4 | O26: 114 | P26: 117.8 | Q26: 111.7 | R26: 112.7 | S26: 111.4 | T26: 112.5 | U26: NA | V26: 111.1 | W26: 109.6 | X26: 108.3 | Y26: 109.3 | Z26: 107.7 | AA26: 109.8 | AB26: 106.7 | AC26: 108.7 | AD26: 114.2
A27: Urban | B27: 2013 | C27: September | D27: 118.6 | E27: 119.1 | F27: 113.2 | G27: 109.6 | H27: 101.7 | I27: 103.2 | J27: 174.3 | K27: 105.1 | L27: 100.8 | M27: 109.1 | N27: 111.1 | O27: 115.4 | P27: 119.2 | Q27: 112.9 | R27: 111.4 | S27: 109 | T27: 111.1 | U27: 109.7 | V27: 109.5 | W27: 109.6 | X27: 107.9 | Y27: 110.4 | Z27: 107.4 | AA27: 111.2 | AB27: 106.9 | AC27: 109.4 | AD27: 113.2
A28: Rural+Urban | B28: 2013 | C28: September | D28: 116.4 | E28: 116.9 | F28: 112.3 | G28: 110.5 | H28: 105.3 | I28: 107.3 | J28: 160.9 | K28: 107.1 | L28: 103.1 | M28: 108.3 | N28: 110.7 | O28: 114.6 | P28: 118.3 | Q28: 112 | R28: 112.2 | S28: 110.4 | T28: 111.9 | U28: 109.7 | V28: 110.5 | W28: 109.6 | X28: 108.1 | Y28: 109.9 | Z28: 107.5 | AA28: 110.6 | AB28: 106.8 | AC28: 109 | AD28: 113.7
A29: Rural | B29: 2013 | C29: October | D29: 116.3 | E29: 115.4 | F29: 112.6 | G29: 111.7 | H29: 107.7 | I29: 113.2 | J29: 164.9 | K29: 108.3 | L29: 103.9 | M29: 108.2 | N29: 111.1 | O29: 114.9 | P29: 119.8 | Q29: 112.2 | R29: 113.6 | S29: 112.3 | T29: 113.4 | U29: NA | V29: 111.6 | W29: 110.4 | X29: 108.9 | Y29: 109.3 | Z29: 108.3 | AA29: 110.2 | AB29: 107.5 | AC29: 109.1 | AD29: 115.5
A30: Urban | B30: 2013 | C30: October | D30: 118.9 | E30: 118.1 | F30: 114.5 | G30: 110.4 | H30: 102.3 | I30: 106.2 | J30: 183.5 | K30: 105.3 | L30: 100.2 | M30: 109.6 | N30: 111.4 | O30: 116 | P30: 120.8 | Q30: 113.5 | R30: 112.5 | S30: 109.7 | T30: 112 | U30: 110.5 | V30: 109.7 | W30: 110.2 | X30: 108.2 | Y30: 109.7 | Z30: 108 | AA30: 111.3 | AB30: 107.3 | AC30: 109.4 | AD30: 114
A31: Rural+Urban | B31: 2013 | C31: October | D31: 117.1 | E31: 116.3 | F31: 113.3 | G31: 111.2 | H31: 105.7 | I31: 109.9 | J31: 171.2 | K31: 107.3 | L31: 102.7 | M31: 108.7 | N31: 111.2 | O31: 115.4 | P31: 120.2 | Q31: 112.5 | R31: 113.2 | S31: 111.2 | T31: 112.8 | U31: 110.5 | V31: 110.9 | W31: 110.3 | X31: 108.6 | Y31: 109.5 | Z31: 108.1 | AA31: 110.8 | AB31: 107.4 | AC31: 109.2 | AD31: 114.8
A32: Rural | B32: 2013 | C32: November | D32: 117.3 | E32: 114.9 | F32: 116.2 | G32: 112.8 | H32: 108.9 | I32: 116.6 | J32: 178.1 | K32: 109.1 | L32: 103.6 | M32: 109 | N32: 111.8 | O32: 116 | P32: 122.5 | Q32: 112.8 | R32: 114.6 | S32: 113.1 | T32: 114.4 | U32: NA | V32: 112.6 | W32: 111.3 | X32: 109.7 | Y32: 109.6 | Z32: 108.7 | AA32: 111 | AB32: 108.2 | AC32: 109.8 | AD32: 117.4
A33: Urban | B33: 2013 | C33: November | D33: 119.8 | E33: 116.3 | F33: 122.6 | G33: 112 | H33: 103.2 | I33: 110 | J33: 192.8 | K33: 106.3 | L33: 99.5 | M33: 110.3 | N33: 111.8 | O33: 117.1 | P33: 122.9 | Q33: 114.1 | R33: 113.5 | S33: 110.3 | T33: 113 | U33: 111.1 | V33: 110 | W33: 110.9 | X33: 108.6 | Y33: 109.5 | Z33: 108.5 | AA33: 111.3 | AB33: 107.9 | AC33: 109.6 | AD33: 115
A34: Rural+Urban | B34: 2013 | C34: November | D34: 118.1 | E34: 115.4 | F34: 118.7 | G34: 112.5 | H34: 106.8 | I34: 113.5 | J34: 183.1 | K34: 108.2 | L34: 102.2 | M34: 109.4 | N34: 111.8 | O34: 116.5 | P34: 122.6 | Q34: 113.1 | R34: 114.2 | S34: 111.9 | T34: 113.8 | U34: 111.1 | V34: 111.6 | W34: 111.1 | X34: 109.3 | Y34: 109.5 | Z34: 108.6 | AA34: 111.2 | AB34: 108.1 | AC34: 109.7 | AD34: 116.3
A35: Rural | B35: 2013 | C35: December | D35: 118.4 | E35: 115.9 | F35: 120.4 | G35: 113.8 | H35: 109.5 | I35: 115.5 | J35: 145.7 | K35: 109.5 | L35: 102.9 | M35: 109.8 | N35: 112.1 | O35: 116.8 | P35: 118.7 | Q35: 113.6 | R35: 115.8 | S35: 114 | T35: 115.5 | U35: NA | V35: 112.8 | W35: 112.1 | X35: 110.1 | Y35: 109.9 | Z35: 109.2 | AA35: 111.6 | AB35: 108.1 | AC35: 110.1 | AD35: 115.5
A36: Urban | B36: 2013 | C36: December | D36: 120.5 | E36: 118.1 | F36: 128.5 | G36: 112.8 | H36: 103.4 | I36: 110.7 | J36: 144.8 | K36: 107.1 | L36: 98.6 | M36: 111.9 | N36: 112.1 | O36: 118.1 | P36: 117.8 | Q36: 115 | R36: 114.2 | S36: 110.9 | T36: 113.7 | U36: 110.7 | V36: 110.4 | W36: 111.3 | X36: 109 | Y36: 109.7 | Z36: 108.9 | AA36: 111.4 | AB36: 107.7 | AC36: 109.8 | AD36: 113.3
A37: Rural+Urban | B37: 2013 | C37: December | D37: 119.1 | E37: 116.7 | F37: 123.5 | G37: 113.4 | H37: 107.3 | I37: 113.3 | J37: 145.4 | K37: 108.7 | L37: 101.5 | M37: 110.5 | N37: 112.1 | O37: 117.4 | P37: 118.4 | Q37: 114 | R37: 115.2 | S37: 112.7 | T37: 114.8 | U37: 110.7 | V37: 111.9 | W37: 111.7 | X37: 109.7 | Y37: 109.8 | Z37: 109 | AA37: 111.5 | AB37: 107.9 | AC37: 110 | AD37: 114.5
A38: Rural | B38: 2014 | C38: January | D38: 118.9 | E38: 117.1 | F38: 120.5 | G38: 114.4 | H38: 109 | I38: 115.5 | J38: 123.9 | K38: 109.6 | L38: 101.8 | M38: 110.2 | N38: 112.4 | O38: 117.3 | P38: 116 | Q38: 114 | R38: 116.5 | S38: 114.5 | T38: 116.2 | U38: NA | V38: 113 | W38: 112.6 | X38: 110.6 | Y38: 110.5 | Z38: 109.6 | AA38: 111.8 | AB38: 108.3 | AC38: 110.6 | AD38: 114.2
A39: Urban | B39: 2014 | C39: January | D39: 121.2 | E39: 122 | F39: 129.9 | G39: 113.6 | H39: 102.9 | I39: 112.1 | J39: 118.9 | K39: 107.5 | L39: 96.9 | M39: 112.7 | N39: 112.1 | O39: 119 | P39: 115.5 | Q39: 115.7 | R39: 114.8 | S39: 111.3 | T39: 114.3 | U39: 111.6 | V39: 111 | W39: 111.9 | X39: 109.7 | Y39: 110.8 | Z39: 109.8 | AA39: 111.5 | AB39: 108 | AC39: 110.5 | AD39: 112.9
A40: Rural+Urban | B40: 2014 | C40: January | D40: 119.6 | E40: 118.8 | F40: 124.1 | G40: 114.1 | H40: 106.8 | I40: 113.9 | J40: 122.2 | K40: 108.9 | L40: 100.2 | M40: 111 | N40: 112.3 | O40: 118.1 | P40: 115.8 | Q40: 114.5 | R40: 115.8 | S40: 113.2 | T40: 115.4 | U40: 111.6 | V40: 112.2 | W40: 112.3 | X40: 110.3 | Y40: 110.7 | Z40: 109.7 | AA40: 111.6 | AB40: 108.2 | AC40: 110.6 | AD40: 113.6
A41: Rural | B41: 2014 | C41: February | D41: 119.4 | E41: 117.7 | F41: 121.2 | G41: 115 | H41: 109 | I41: 116.6 | J41: 116 | K41: 109.8 | L41: 101.1 | M41: 110.4 | N41: 112.9 | O41: 117.8 | P41: 115.3 | Q41: 114.2 | R41: 117.1 | S41: 114.5 | T41: 116.7 | U41: NA | V41: 113.2 | W41: 112.9 | X41: 110.9 | Y41: 110.8 | Z41: 109.9 | AA41: 112 | AB41: 108.7 | AC41: 110.9 | AD41: 114
A42: Urban | B42: 2014 | C42: February | D42: 121.9 | E42: 122 | F42: 124.5 | G42: 115.2 | H42: 102.5 | I42: 114.1 | J42: 111.5 | K42: 108.2 | L42: 95.4 | M42: 113.5 | N42: 112.1 | O42: 119.9 | P42: 115.2 | Q42: 116.2 | R42: 115.3 | S42: 111.7 | T42: 114.7 | U42: 112.5 | V42: 111.1 | W42: 112.6 | X42: 110.4 | Y42: 111.3 | Z42: 110.3 | AA42: 111.6 | AB42: 108.7 | AC42: 111 | AD42: 113.1
A43: Rural+Urban | B43: 2014 | C43: February | D43: 120.2 | E43: 119.2 | F43: 122.5 | G43: 115.1 | H43: 106.6 | I43: 115.4 | J43: 114.5 | K43: 109.3 | L43: 99.2 | M43: 111.4 | N43: 112.6 | O43: 118.8 | P43: 115.3 | Q43: 114.7 | R43: 116.4 | S43: 113.3 | T43: 115.9 | U43: 112.5 | V43: 112.4 | W43: 112.8 | X43: 110.7 | Y43: 111.1 | Z43: 110.1 | AA43: 111.8 | AB43: 108.7 | AC43: 110.9 | AD43: 113.6
A44: Rural | B44: 2014 | C44: March | D44: 120.1 | E44: 118.1 | F44: 120.7 | G44: 116.1 | H44: 109.3 | I44: 119.6 | J44: 117.9 | K44: 110.2 | L44: 101.2 | M44: 110.7 | N44: 113 | O44: 118.3 | P44: 116.2 | Q44: 114.6 | R44: 117.5 | S44: 114.9 | T44: 117.2 | U44: NA | V44: 113.4 | W44: 113.4 | X44: 111.4 | Y44: 111.2 | Z44: 110.2 | AA44: 112.4 | AB44: 108.9 | AC44: 111.3 | AD44: 114.6
A45: Urban | B45: 2014 | C45: March | D45: 122.1 | E45: 121.4 | F45: 121.5 | G45: 116.2 | H45: 102.8 | I45: 117.7 | J45: 113.3 | K45: 108.9 | L45: 96.3 | M45: 114.1 | N45: 112.2 | O45: 120.5 | P45: 116 | Q45: 116.7 | R45: 115.8 | S45: 112.1 | T45: 115.2 | U45: 113.2 | V45: 110.9 | W45: 113 | X45: 110.8 | Y45: 111.6 | Z45: 110.9 | AA45: 111.8 | AB45: 109.2 | AC45: 111.4 | AD45: 113.7
A46: Rural+Urban | B46: 2014 | C46: Marcrh | D46: 120.7 | E46: 119.3 | F46: 121 | G46: 116.1 | H46: 106.9 | I46: 118.7 | J46: 116.3 | K46: 109.8 | L46: 99.6 | M46: 111.8 | N46: 112.7 | O46: 119.3 | P46: 116.1 | Q46: 115.2 | R46: 116.8 | S46: 113.7 | T46: 116.4 | U46: 113.2 | V46: 112.5 | W46: 113.2 | X46: 111.2 | Y46: 111.4 | Z46: 110.6 | AA46: 112 | AB46: 109 | AC46: 111.3 | AD46: 114.2
A47: Rural | B47: 2014 | C47: April | D47: 120.2 | E47: 118.9 | F47: 118.1 | G47: 117 | H47: 109.7 | I47: 125.5 | J47: 120.5 | K47: 111 | L47: 102.6 | M47: 111.2 | N47: 113.5 | O47: 118.7 | P47: 117.2 | Q47: 115.4 | R47: 118.1 | S47: 116.1 | T47: 117.8 | U47: NA | V47: 113.4 | W47: 113.7 | X47: 111.8 | Y47: 111.2 | Z47: 110.5 | AA47: 113 | AB47: 108.9 | AC47: 111.5 | AD47: 115.4
A48: Urban | B48: 2014 | C48: April | D48: 122.5 | E48: 121.7 | F48: 113.3 | G48: 117 | H48: 103.1 | I48: 126.7 | J48: 121.2 | K48: 111 | L48: 100.3 | M48: 115.3 | N48: 112.7 | O48: 121 | P48: 118.2 | Q48: 117.6 | R48: 116.3 | S48: 112.5 | T48: 115.7 | U48: 113.9 | V48: 110.9 | W48: 113.4 | X48: 111 | Y48: 111.2 | Z48: 111.2 | AA48: 112.5 | AB48: 109.1 | AC48: 111.4 | AD48: 114.7
A49: Rural+Urban | B49: 2014 | C49: April | D49: 120.9 | E49: 119.9 | F49: 116.2 | G49: 117 | H49: 107.3 | I49: 126.1 | J49: 120.7 | K49: 111 | L49: 101.8 | M49: 112.6 | N49: 113.2 | O49: 119.8 | P49: 117.6 | Q49: 116 | R49: 117.4 | S49: 114.6 | T49: 117 | U49: 113.9 | V49: 112.5 | W49: 113.6 | X49: 111.5 | Y49: 111.2 | Z49: 110.9 | AA49: 112.7 | AB49: 109 | AC49: 111.5 | AD49: 115.1
A50: Rural | B50: 2014 | C50: May | D50: 120.3 | E50: 120.2 | F50: 116.9 | G50: 118 | H50: 110.1 | I50: 126.3 | J50: 123.9 | K50: 111.5 | L50: 103.5 | M50: 111.6 | N50: 114.2 | O50: 119.2 | P50: 118.2 | Q50: 116.3 | R50: 118.7 | S50: 116.8 | T50: 118.5 | U50: NA | V50: 113.4 | W50: 114.1 | X50: 112.1 | Y50: 111.4 | Z50: 110.9 | AA50: 113.1 | AB50: 108.9 | AC50: 111.8 | AD50: 116
A51: Urban | B51: 2014 | C51: May | D51: 122.7 | E51: 124.1 | F51: 114.2 | G51: 119.1 | H51: 103.5 | I51: 129.2 | J51: 127 | K51: 112.6 | L51: 101.3 | M51: 117 | N51: 112.9 | O51: 121.7 | P51: 120 | Q51: 118.3 | R51: 116.8 | S51: 112.9 | T51: 116.2 | U51: 114.3 | V51: 111.1 | W51: 114.1 | X51: 111.2 | Y51: 111.3 | Z51: 111.5 | AA51: 112.9 | AB51: 109.3 | AC51: 111.7 | AD51: 115.6
A52: Rural+Urban | B52: 2014 | C52: May | D52: 121.1 | E52: 121.6 | F52: 115.9 | G52: 118.4 | H52: 107.7 | I52: 127.7 | J52: 125 | K52: 111.9 | L52: 102.8 | M52: 113.4 | N52: 113.7 | O52: 120.4 | P52: 118.9 | Q52: 116.8 | R52: 118 | S52: 115.2 | T52: 117.6 | U52: 114.3 | V52: 112.5 | W52: 114.1 | X52: 111.8 | Y52: 111.3 | Z52: 111.2 | AA52: 113 | AB52: 109.1 | AC52: 111.8 | AD52: 115.8
A53: Rural | B53: 2014 | C53: June | D53: 120.7 | E53: 121.6 | F53: 116.1 | G53: 119.3 | H53: 110.3 | I53: 125.8 | J53: 129.3 | K53: 112.2 | L53: 103.6 | M53: 112.3 | N53: 114.9 | O53: 120.1 | P53: 119.5 | Q53: 117.3 | R53: 119.7 | S53: 117.3 | T53: 119.3 | U53: NA | V53: 114.4 | W53: 114.9 | X53: 112.8 | Y53: 112.2 | Z53: 111.4 | AA53: 114.3 | AB53: 108 | AC53: 112.3 | AD53: 117
A54: Urban | B54: 2014 | C54: June | D54: 123.1 | E54: 125.9 | F54: 115.4 | G54: 120.4 | H54: 103.4 | I54: 131.2 | J54: 137.5 | K54: 112.8 | L54: 101.4 | M54: 118.3 | N54: 113.2 | O54: 122.4 | P54: 122 | Q54: 119 | R54: 117.4 | S54: 113.2 | T54: 116.7 | U54: 113.9 | V54: 111.2 | W54: 114.3 | X54: 111.4 | Y54: 111.5 | Z54: 111.8 | AA54: 115.1 | AB54: 108.7 | AC54: 112.2 | AD54: 116.4
A55: Rural+Urban | B55: 2014 | C55: June | D55: 121.5 | E55: 123.1 | F55: 115.8 | G55: 119.7 | H55: 107.8 | I55: 128.3 | J55: 132.1 | K55: 112.4 | L55: 102.9 | M55: 114.3 | N55: 114.2 | O55: 121.2 | P55: 120.4 | Q55: 117.8 | R55: 118.8 | S55: 115.6 | T55: 118.3 | U55: 113.9 | V55: 113.2 | W55: 114.6 | X55: 112.3 | Y55: 111.8 | Z55: 111.6 | AA55: 114.8 | AB55: 108.3 | AC55: 112.3 | AD55: 116.7
A56: Rural | B56: 2014 | C56: July | D56: 121.7 | E56: 122.5 | F56: 117.7 | G56: 120.6 | H56: 110.4 | I56: 129.1 | J56: 150.1 | K56: 113.2 | L56: 104.8 | M56: 113.3 | N56: 115.6 | O56: 120.9 | P56: 123.3 | Q56: 118 | R56: 120.7 | S56: 118.3 | T56: 120.3 | U56: NA | V56: 115.3 | W56: 115.4 | X56: 113.4 | Y56: 113.2 | Z56: 111.8 | AA56: 115.5 | AB56: 108.8 | AC56: 113.1 | AD56: 119.5
A57: Urban | B57: 2014 | C57: July | D57: 123.8 | E57: 126.4 | F57: 118 | G57: 121.6 | H57: 103.5 | I57: 133.7 | J57: 172.4 | K57: 113.1 | L57: 102.7 | M57: 120 | N57: 113.8 | O57: 123.4 | P57: 127.1 | Q57: 121 | R57: 118 | S57: 113.6 | T57: 117.4 | U57: 114.8 | V57: 111.6 | W57: 114.9 | X57: 111.5 | Y57: 113 | Z57: 112.4 | AA57: 117.8 | AB57: 109.7 | AC57: 113.5 | AD57: 118.9
A58: Rural+Urban | B58: 2014 | C58: July | D58: 122.4 | E58: 123.9 | F58: 117.8 | G58: 121 | H58: 107.9 | I58: 131.2 | J58: 157.7 | K58: 113.2 | L58: 104.1 | M58: 115.5 | N58: 114.8 | O58: 122.1 | P58: 124.7 | Q58: 118.8 | R58: 119.6 | S58: 116.3 | T58: 119.1 | U58: 114.8 | V58: 113.9 | W58: 115.2 | X58: 112.7 | Y58: 113.1 | Z58: 112.1 | AA58: 116.8 | AB58: 109.2 | AC58: 113.3 | AD58: 119.2
A59: Rural | B59: 2014 | C59: August | D59: 121.8 | E59: 122.8 | F59: 117.8 | G59: 121.9 | H59: 110.6 | I59: 129.7 | J59: 161.1 | K59: 114.1 | L59: 105.1 | M59: 114.6 | N59: 115.8 | O59: 121.7 | P59: 125.3 | Q59: 118.8 | R59: 120.9 | S59: 118.8 | T59: 120.7 | U59: NA | V59: 115.4 | W59: 115.9 | X59: 114 | Y59: 113.2 | Z59: 112.2 | AA59: 116.2 | AB59: 109.4 | AC59: 113.5 | AD59: 120.7
A60: Urban | B60: 2014 | C60: August | D60: 124.8 | E60: 127.3 | F60: 116.5 | G60: 122.2 | H60: 103.6 | I60: 132.7 | J60: 181.9 | K60: 115.2 | L60: 102.7 | M60: 122.1 | N60: 114.4 | O60: 124.7 | P60: 128.9 | Q60: 123 | R60: 118.6 | S60: 114.1 | T60: 117.9 | U60: 115.5 | V60: 111.8 | W60: 115.3 | X60: 112.2 | Y60: 112.5 | Z60: 112.9 | AA60: 119.2 | AB60: 110.5 | AC60: 113.9 | AD60: 119.9
A61: Rural+Urban | B61: 2014 | C61: August | D61: 122.7 | E61: 124.4 | F61: 117.3 | G61: 122 | H61: 108 | I61: 131.1 | J61: 168.2 | K61: 114.5 | L61: 104.3 | M61: 117.1 | N61: 115.2 | O61: 123.1 | P61: 126.6 | Q61: 119.9 | R61: 120 | S61: 116.8 | T61: 119.6 | U61: 115.5 | V61: 114 | W61: 115.6 | X61: 113.3 | Y61: 112.8 | Z61: 112.6 | AA61: 118 | AB61: 109.9 | AC61: 113.7 | AD61: 120.3
A62: Rural | B62: 2014 | C62: September | D62: 122.3 | E62: 122.4 | F62: 117.8 | G62: 122.7 | H62: 110.4 | I62: 129.8 | J62: 158.8 | K62: 115 | L62: 104.7 | M62: 114.9 | N62: 116.5 | O62: 122.6 | P62: 125.3 | Q62: 119.5 | R62: 121.7 | S62: 119.2 | T62: 121.3 | U62: NA | V62: 115.8 | W62: 116.7 | X62: 114.5 | Y62: 112.8 | Z62: 112.6 | AA62: 116.6 | AB62: 109.1 | AC62: 113.7 | AD62: 120.9
A63: Urban | B63: 2014 | C63: September | D63: 124.2 | E63: 125.4 | F63: 116.4 | G63: 122.7 | H63: 103.5 | I63: 124.5 | J63: 168.6 | K63: 116.9 | L63: 101.9 | M63: 122.9 | N63: 114.8 | O63: 125.2 | P63: 126.7 | Q63: 124.3 | R63: 119.2 | S63: 114.5 | T63: 118.4 | U63: 116.1 | V63: 111.8 | W63: 115.5 | X63: 112.3 | Y63: 111.2 | Z63: 113.4 | AA63: 120 | AB63: 110 | AC63: 113.6 | AD63: 119.2
A64: Rural+Urban | B64: 2014 | C64: September | D64: 122.9 | E64: 123.5 | F64: 117.3 | G64: 122.7 | H64: 107.9 | I64: 127.3 | J64: 162.1 | K64: 115.6 | L64: 103.8 | M64: 117.6 | N64: 115.8 | O64: 123.8 | P64: 125.8 | Q64: 120.8 | R64: 120.7 | S64: 117.2 | T64: 120.1 | U64: 116.1 | V64: 114.3 | W64: 116.1 | X64: 113.7 | Y64: 112 | Z64: 113.1 | AA64: 118.6 | AB64: 109.5 | AC64: 113.7 | AD64: 120.1
A65: Rural | B65: 2014 | C65: October | D65: 122.6 | E65: 122.5 | F65: 118.3 | G65: 123.2 | H65: 110.5 | I65: 128.9 | J65: 155.3 | K65: 115.5 | L65: 104 | M65: 115.3 | N65: 116.8 | O65: 123.2 | P65: 125.1 | Q65: 120 | R65: 122.7 | S65: 120.3 | T65: 122.3 | U65: NA | V65: 116.4 | W65: 117.5 | X65: 115.3 | Y65: 112.6 | Z65: 113 | AA65: 116.9 | AB65: 109.3 | AC65: 114 | AD65: 121
A66: Urban | B66: 2014 | C66: October | D66: 124.6 | E66: 126.1 | F66: 117.8 | G66: 123.1 | H66: 103.5 | I66: 123.5 | J66: 159.6 | K66: 117.4 | L66: 101.2 | M66: 123.8 | N66: 115.2 | O66: 125.9 | P66: 125.8 | Q66: 124.3 | R66: 119.6 | S66: 114.9 | T66: 118.9 | U66: 116.7 | V66: 112 | W66: 115.8 | X66: 112.6 | Y66: 111 | Z66: 113.6 | AA66: 120.2 | AB66: 110.1 | AC66: 113.7 | AD66: 119.1
A67: Rural+Urban | B67: 2014 | C67: October | D67: 123.2 | E67: 123.8 | F67: 118.1 | G67: 123.2 | H67: 107.9 | I67: 126.4 | J67: 156.8 | K67: 116.1 | L67: 103.1 | M67: 118.1 | N67: 116.1 | O67: 124.5 | P67: 125.4 | Q67: 121.1 | R67: 121.5 | S67: 118.1 | T67: 121 | U67: 116.7 | V67: 114.7 | W67: 116.7 | X67: 114.3 | Y67: 111.8 | Z67: 113.3 | AA67: 118.8 | AB67: 109.6 | AC67: 113.9 | AD67: 120.1
A68: Rural | B68: 2014 | C68: November | D68: 122.7 | E68: 122.6 | F68: 119.9 | G68: 124 | H68: 110.5 | I68: 128.8 | J68: 152 | K68: 116.2 | L68: 103.3 | M68: 115.8 | N68: 116.8 | O68: 124.5 | P68: 124.9 | Q68: 120.8 | R68: 123.3 | S68: 120.5 | T68: 122.9 | U68: NA | V68: 117.3 | W68: 118.1 | X68: 115.9 | Y68: 112 | Z68: 113.3 | AA68: 117.2 | AB68: 108.8 | AC68: 114.1 | AD68: 121.1
A69: Urban | B69: 2014 | C69: November | D69: 124.5 | E69: 125.6 | F69: 122.7 | G69: 124.6 | H69: 103.2 | I69: 122.2 | J69: 153.2 | K69: 119.3 | L69: 99.8 | M69: 124.6 | N69: 115.8 | O69: 126.9 | P69: 125.4 | Q69: 125.8 | R69: 120.3 | S69: 115.4 | T69: 119.5 | U69: 117.1 | V69: 112.6 | W69: 116.4 | X69: 113 | Y69: 109.7 | Z69: 114 | AA69: 120.3 | AB69: 109.6 | AC69: 113.4 | AD69: 119
A70: Rural+Urban | B70: 2014 | C70: November | D70: 123.3 | E70: 123.7 | F70: 121 | G70: 124.2 | H70: 107.8 | I70: 125.7 | J70: 152.4 | K70: 117.2 | L70: 102.1 | M70: 118.7 | N70: 116.4 | O70: 125.6 | P70: 125.1 | Q70: 122.1 | R70: 122.1 | S70: 118.4 | T70: 121.6 | U70: 117.1 | V70: 115.5 | W70: 117.3 | X70: 114.8 | Y70: 110.8 | Z70: 113.7 | AA70: 119 | AB70: 109.1 | AC70: 113.8 | AD70: 120.1
A71: Rural | B71: 2014 | C71: December | D71: 122.4 | E71: 122.4 | F71: 121.8 | G71: 124.2 | H71: 110.2 | I71: 128.6 | J71: 140.3 | K71: 116.3 | L71: 102 | M71: 116 | N71: 117.3 | O71: 124.8 | P71: 123.3 | Q71: 121.7 | R71: 123.8 | S71: 120.6 | T71: 123.3 | U71: NA | V71: 117.4 | W71: 118.2 | X71: 116.2 | Y71: 111.5 | Z71: 113.3 | AA71: 117.7 | AB71: 109.4 | AC71: 114.2 | AD71: 120.3
A72: Urban | B72: 2014 | C72: December | D72: 124 | E72: 124.7 | F72: 126.3 | G72: 124.9 | H72: 103 | I72: 122.3 | J72: 141 | K72: 120.1 | L72: 97.8 | M72: 125.4 | N72: 116.1 | O72: 127.6 | P72: 124 | Q72: 126.4 | R72: 120.7 | S72: 115.8 | T72: 120 | U72: 116.5 | V72: 113 | W72: 116.8 | X72: 113.2 | Y72: 108.8 | Z72: 114.3 | AA72: 120.7 | AB72: 110.4 | AC72: 113.4 | AD72: 118.4
A73: Rural+Urban | B73: 2014 | C73: December | D73: 122.9 | E73: 123.2 | F73: 123.5 | G73: 124.5 | H73: 107.6 | I73: 125.7 | J73: 140.5 | K73: 117.6 | L73: 100.6 | M73: 119.1 | N73: 116.8 | O73: 126.1 | P73: 123.6 | Q73: 123 | R73: 122.6 | S73: 118.6 | T73: 122 | U73: 116.5 | V73: 115.7 | W73: 117.5 | X73: 115.1 | Y73: 110.1 | Z73: 113.9 | AA73: 119.5 | AB73: 109.8 | AC73: 113.8 | AD73: 119.4
A74: Rural | B74: 2015 | C74: January | D74: 123.1 | E74: 123.1 | F74: 122.1 | G74: 124.9 | H74: 111 | I74: 130.4 | J74: 132.3 | K74: 117.2 | L74: 100.5 | M74: 117.2 | N74: 117.9 | O74: 125.6 | P74: 122.8 | Q74: 122.7 | R74: 124.4 | S74: 121.6 | T74: 124 | U74: NA | V74: 118.4 | W74: 118.9 | X74: 116.6 | Y74: 111 | Z74: 114 | AA74: 118.2 | AB74: 110.2 | AC74: 114.5 | AD74: 120.3
A75: Urban | B75: 2015 | C75: January | D75: 124 | E75: 125.5 | F75: 126.6 | G75: 125.2 | H75: 104.3 | I75: 121.3 | J75: 134.4 | K75: 122.9 | L75: 96.1 | M75: 126.6 | N75: 116.5 | O75: 128 | P75: 123.5 | Q75: 127.4 | R75: 121 | S75: 116.1 | T75: 120.2 | U75: 117.3 | V75: 113.4 | W75: 117.2 | X75: 113.7 | Y75: 107.9 | Z75: 114.6 | AA75: 120.8 | AB75: 111.4 | AC75: 113.4 | AD75: 118.5
A76: Rural+Urban | B76: 2015 | C76: January | D76: 123.4 | E76: 123.9 | F76: 123.8 | G76: 125 | H76: 108.5 | I76: 126.2 | J76: 133 | K76: 119.1 | L76: 99 | M76: 120.3 | N76: 117.3 | O76: 126.7 | P76: 123.1 | Q76: 124 | R76: 123.1 | S76: 119.3 | T76: 122.5 | U76: 117.3 | V76: 116.5 | W76: 118.1 | X76: 115.5 | Y76: 109.4 | Z76: 114.3 | AA76: 119.7 | AB76: 110.7 | AC76: 114 | AD76: 119.5
A77: Rural | B77: 2015 | C77: February | D77: 123.4 | E77: 124.4 | F77: 122.1 | G77: 125.8 | H77: 111.5 | I77: 129.4 | J77: 128.2 | K77: 118.8 | L77: 100 | M77: 118.6 | N77: 118.8 | O77: 126.8 | P77: 122.8 | Q77: 124.2 | R77: 125.4 | S77: 122.7 | T77: 125 | U77: NA | V77: 120 | W77: 119.6 | X77: 117.7 | Y77: 110.9 | Z77: 114.8 | AA77: 118.7 | AB77: 110.8 | AC77: 115 | AD77: 120.6
A78: Urban | B78: 2015 | C78: February | D78: 124.3 | E78: 126.5 | F78: 119.5 | G78: 125.6 | H78: 104.9 | I78: 121.6 | J78: 131.8 | K78: 125.1 | L78: 95 | M78: 127.7 | N78: 116.8 | O78: 128.6 | P78: 123.7 | Q78: 128.1 | R78: 121.3 | S78: 116.5 | T78: 120.6 | U78: 118.1 | V78: 114 | W78: 117.7 | X78: 114.1 | Y78: 106.8 | Z78: 114.9 | AA78: 120.4 | AB78: 111.7 | AC78: 113.2 | AD78: 118.7
A79: Rural+Urban | B79: 2015 | C79: February | D79: 123.7 | E79: 125.1 | F79: 121.1 | G79: 125.7 | H79: 109.1 | I79: 125.8 | J79: 129.4 | K79: 120.9 | L79: 98.3 | M79: 121.6 | N79: 118 | O79: 127.6 | P79: 123.1 | Q79: 125.2 | R79: 123.8 | S79: 120.1 | T79: 123.3 | U79: 118.1 | V79: 117.7 | W79: 118.7 | X79: 116.3 | Y79: 108.7 | Z79: 114.9 | AA79: 119.7 | AB79: 111.2 | AC79: 114.1 | AD79: 119.7
A80: Rural | B80: 2015 | C80: March | D80: 123.3 | E80: 124.7 | F80: 118.9 | G80: 126 | H80: 111.8 | I80: 130.9 | J80: 128 | K80: 119.9 | L80: 98.9 | M80: 119.4 | N80: 118.9 | O80: 127.7 | P80: 123.1 | Q80: 124.7 | R80: 126 | S80: 122.9 | T80: 125.5 | U80: NA | V80: 120.6 | W80: 120.2 | X80: 118.2 | Y80: 111.6 | Z80: 115.5 | AA80: 119.4 | AB80: 110.8 | AC80: 115.5 | AD80: 121.1
A81: Urban | B81: 2015 | C81: March | D81: 124 | E81: 126.7 | F81: 113.5 | G81: 125.9 | H81: 104.8 | I81: 123.8 | J81: 131.4 | K81: 127.2 | L81: 93.2 | M81: 127.4 | N81: 117 | O81: 129.2 | P81: 123.9 | Q81: 128.8 | R81: 121.7 | S81: 116.9 | T81: 120.9 | U81: 118.6 | V81: 114.4 | W81: 118 | X81: 114.3 | Y81: 108.4 | Z81: 115.4 | AA81: 120.6 | AB81: 111.3 | AC81: 113.8 | AD81: 119.1
A82: Rural+Urban | B82: 2015 | C82: March | D82: 123.5 | E82: 125.4 | F82: 116.8 | G82: 126 | H82: 109.2 | I82: 127.6 | J82: 129.2 | K82: 122.4 | L82: 97 | M82: 122.1 | N82: 118.1 | O82: 128.4 | P82: 123.4 | Q82: 125.8 | R82: 124.3 | S82: 120.4 | T82: 123.7 | U82: 118.6 | V82: 118.3 | W82: 119.2 | X82: 116.7 | Y82: 109.9 | Z82: 115.4 | AA82: 120.1 | AB82: 111 | AC82: 114.7 | AD82: 120.2
A83: Rural | B83: 2015 | C83: April | D83: 123.3 | E83: 125.5 | F83: 117.2 | G83: 126.8 | H83: 111.9 | I83: 134.2 | J83: 127.5 | K83: 121.5 | L83: 97.8 | M83: 119.8 | N83: 119.4 | O83: 128.7 | P83: 123.6 | Q83: 125.7 | R83: 126.4 | S83: 123.3 | T83: 126 | U83: NA | V83: 121.2 | W83: 120.9 | X83: 118.6 | Y83: 111.9 | Z83: 116.2 | AA83: 119.9 | AB83: 111.6 | AC83: 116 | AD83: 121.5
A84: Urban | B84: 2015 | C84: April | D84: 123.8 | E84: 128.2 | F84: 110 | G84: 126.3 | H84: 104.5 | I84: 130.6 | J84: 130.8 | K84: 131.3 | L84: 91.6 | M84: 127.7 | N84: 117.2 | O84: 129.5 | P84: 124.6 | Q84: 130.1 | R84: 122.1 | S84: 117.2 | T84: 121.3 | U84: 119.2 | V84: 114.7 | W84: 118.4 | X84: 114.6 | Y84: 108.4 | Z84: 115.6 | AA84: 121.7 | AB84: 111.8 | AC84: 114.2 | AD84: 119.7
A85: Rural+Urban | B85: 2015 | C85: April | D85: 123.5 | E85: 126.4 | F85: 114.4 | G85: 126.6 | H85: 109.2 | I85: 132.5 | J85: 128.6 | K85: 124.8 | L85: 95.7 | M85: 122.4 | N85: 118.5 | O85: 129.1 | P85: 124 | Q85: 126.9 | R85: 124.7 | S85: 120.8 | T85: 124.1 | U85: 119.2 | V85: 118.7 | W85: 119.7 | X85: 117.1 | Y85: 110.1 | Z85: 115.9 | AA85: 121 | AB85: 111.7 | AC85: 115.1 | AD85: 120.7
A86: Rural | B86: 2015 | C86: May | D86: 123.5 | E86: 127.1 | F86: 117.3 | G86: 127.7 | H86: 112.5 | I86: 134.1 | J86: 128.5 | K86: 124.3 | L86: 97.6 | M86: 120.7 | N86: 120.2 | O86: 129.8 | P86: 124.4 | Q86: 126.7 | R86: 127.3 | S86: 124.1 | T86: 126.8 | U86: NA | V86: 121.9 | W86: 121.5 | X86: 119.4 | Y86: 113.3 | Z86: 116.7 | AA86: 120.5 | AB86: 112.3 | AC86: 116.9 | AD86: 122.4
A87: Urban | B87: 2015 | C87: May | D87: 123.8 | E87: 129.7 | F87: 111.3 | G87: 126.6 | H87: 105.2 | I87: 130.8 | J87: 135.6 | K87: 142.6 | L87: 90.8 | M87: 128.8 | N87: 117.7 | O87: 129.9 | P87: 126.1 | Q87: 131.3 | R87: 122.4 | S87: 117.4 | T87: 121.6 | U87: 119.6 | V87: 114.9 | W87: 118.7 | X87: 114.9 | Y87: 110.8 | Z87: 116 | AA87: 122 | AB87: 112.4 | AC87: 115.2 | AD87: 120.7
A88: Rural+Urban | B88: 2015 | C88: May | D88: 123.6 | E88: 128 | F88: 115 | G88: 127.3 | H88: 109.8 | I88: 132.6 | J88: 130.9 | K88: 130.5 | L88: 95.3 | M88: 123.4 | N88: 119.2 | O88: 129.8 | P88: 125 | Q88: 127.9 | R88: 125.4 | S88: 121.3 | T88: 124.7 | U88: 119.6 | V88: 119.2 | W88: 120.2 | X88: 117.7 | Y88: 112 | Z88: 116.3 | AA88: 121.4 | AB88: 112.3 | AC88: 116.1 | AD88: 121.6
A89: Rural | B89: 2015 | C89: June | D89: 124.1 | E89: 130.4 | F89: 122.1 | G89: 128.7 | H89: 114.1 | I89: 133.2 | J89: 135.2 | K89: 131.9 | L89: 96.3 | M89: 123 | N89: 121.1 | O89: 131.2 | P89: 126.6 | Q89: 128.2 | R89: 128.4 | S89: 125.1 | T89: 128 | U89: NA | V89: 122.6 | W89: 122.8 | X89: 120.4 | Y89: 114.2 | Z89: 117.9 | AA89: 122 | AB89: 113 | AC89: 117.9 | AD89: 124.1
A90: Urban | B90: 2015 | C90: June | D90: 123.6 | E90: 134.4 | F90: 120.9 | G90: 127.3 | H90: 106 | I90: 132.3 | J90: 146.7 | K90: 148.1 | L90: 89.8 | M90: 130.5 | N90: 118 | O90: 130.5 | P90: 128.5 | Q90: 132.1 | R90: 123.2 | S90: 117.6 | T90: 122.3 | U90: 119 | V90: 115.1 | W90: 119.2 | X90: 115.4 | Y90: 111.7 | Z90: 116.2 | AA90: 123.8 | AB90: 112.5 | AC90: 116 | AD90: 121.7
A91: Rural+Urban | B91: 2015 | C91: June | D91: 123.9 | E91: 131.8 | F91: 121.6 | G91: 128.2 | H91: 111.1 | I91: 132.8 | J91: 139.1 | K91: 137.4 | L91: 94.1 | M91: 125.5 | N91: 119.8 | O91: 130.9 | P91: 127.3 | Q91: 129.2 | R91: 126.4 | S91: 122 | T91: 125.7 | U91: 119 | V91: 119.8 | W91: 121.1 | X91: 118.5 | Y91: 112.9 | Z91: 116.9 | AA91: 123.1 | AB91: 112.8 | AC91: 117 | AD91: 123
A92: Rural | B92: 2015 | C92: July | D92: 124 | E92: 131.5 | F92: 122 | G92: 128.7 | H92: 113.5 | I92: 133.3 | J92: 140.8 | K92: 133.8 | L92: 94.1 | M92: 123.4 | N92: 121 | O92: 131.7 | P92: 127.5 | Q92: 129.4 | R92: 128.8 | S92: 125.5 | T92: 128.3 | U92: NA | V92: 123 | W92: 123 | X92: 120.8 | Y92: 114.1 | Z92: 118 | AA92: 122.9 | AB92: 112.7 | AC92: 118.1 | AD92: 124.7
A93: Urban | B93: 2015 | C93: July | D93: 123.2 | E93: 134.3 | F93: 119.5 | G93: 127.7 | H93: 106.3 | I93: 132.8 | J93: 153.5 | K93: 149.5 | L93: 85.7 | M93: 131.5 | N93: 118.3 | O93: 131.1 | P93: 129.5 | Q93: 133.1 | R93: 123.5 | S93: 117.9 | T93: 122.7 | U93: 119.9 | V93: 115.3 | W93: 119.5 | X93: 116 | Y93: 111.5 | Z93: 116.6 | AA93: 125.4 | AB93: 111.7 | AC93: 116.3 | AD93: 122.4
A94: Rural+Urban | B94: 2015 | C94: July | D94: 123.7 | E94: 132.5 | F94: 121 | G94: 128.3 | H94: 110.9 | I94: 133.1 | J94: 145.1 | K94: 139.1 | L94: 91.3 | M94: 126.1 | N94: 119.9 | O94: 131.4 | P94: 128.2 | Q94: 130.4 | R94: 126.7 | S94: 122.3 | T94: 126.1 | U94: 119.9 | V94: 120.1 | W94: 121.3 | X94: 119 | Y94: 112.7 | Z94: 117.2 | AA94: 124.4 | AB94: 112.3 | AC94: 117.2 | AD94: 123.6
A95: Rural | B95: 2015 | C95: August | D95: 124.7 | E95: 131.3 | F95: 121.3 | G95: 128.8 | H95: 114 | I95: 134.2 | J95: 153.6 | K95: 137.9 | L95: 93.1 | M95: 123.9 | N95: 121.5 | O95: 132.5 | P95: 129.8 | Q95: 130.1 | R95: 129.5 | S95: 126.3 | T95: 129 | U95: NA | V95: 123.8 | W95: 123.7 | X95: 121.1 | Y95: 113.6 | Z95: 118.5 | AA95: 123.6 | AB95: 112.5 | AC95: 118.2 | AD95: 126.1
A96: Urban | B96: 2015 | C96: August | D96: 123.1 | E96: 131.7 | F96: 118.1 | G96: 128 | H96: 106.8 | I96: 130.1 | J96: 165.5 | K96: 156 | L96: 85.3 | M96: 132.7 | N96: 118.8 | O96: 131.7 | P96: 131.1 | Q96: 134.2 | R96: 123.7 | S96: 118.2 | T96: 122.9 | U96: 120.9 | V96: 115.3 | W96: 120 | X96: 116.6 | Y96: 109.9 | Z96: 117.2 | AA96: 126.2 | AB96: 112 | AC96: 116.2 | AD96: 123.2
A97: Rural+Urban | B97: 2015 | C97: August | D97: 124.2 | E97: 131.4 | F97: 120.1 | G97: 128.5 | H97: 111.4 | I97: 132.3 | J97: 157.6 | K97: 144 | L97: 90.5 | M97: 126.8 | N97: 120.4 | O97: 132.1 | P97: 130.3 | Q97: 131.2 | R97: 127.2 | S97: 122.9 | T97: 126.6 | U97: 120.9 | V97: 120.6 | W97: 122 | X97: 119.4 | Y97: 111.7 | Z97: 117.8 | AA97: 125.1 | AB97: 112.3 | AC97: 117.2 | AD97: 124.8
A98: Rural | B98: 2015 | C98: September | D98: 125.1 | E98: 131.1 | F98: 120.7 | G98: 129.2 | H98: 114.7 | I98: 132.3 | J98: 158.9 | K98: 142.1 | L98: 92.5 | M98: 125.4 | N98: 121.9 | O98: 132.7 | P98: 131 | Q98: 131 | R98: 130.4 | S98: 126.8 | T98: 129.9 | U98: NA | V98: 123.7 | W98: 124.5 | X98: 121.4 | Y98: 113.8 | Z98: 119.6 | AA98: 124.5 | AB98: 113.7 | AC98: 118.8 | AD98: 127
A99: Urban | B99: 2015 | C99: September | D99: 123.4 | E99: 129 | F99: 115.6 | G99: 128.3 | H99: 107 | I99: 124 | J99: 168.5 | K99: 165.4 | L99: 86.3 | M99: 134.4 | N99: 119.1 | O99: 132.3 | P99: 131.5 | Q99: 134.7 | R99: 124 | S99: 118.6 | T99: 123.2 | U99: 121.6 | V99: 115.1 | W99: 120.4 | X99: 117.1 | Y99: 109.1 | Z99: 117.3 | AA99: 126.5 | AB99: 112.9 | AC99: 116.2 | AD99: 123.5
A100: Rural+Urban | B100: 2015 | C100: September | D100: 124.6 | E100: 130.4 | F100: 118.7 | G100: 128.9 | H100: 111.9 | I100: 128.4 | J100: 162.2 | K100: 150 | L100: 90.4 | M100: 128.4 | N100: 120.7 | O100: 132.5 | P100: 131.2 | Q100: 132 | R100: 127.9 | S100: 123.4 | T100: 127.2 | U100: 121.6 | V100: 120.4 | W100: 122.6 | X100: 119.8 | Y100: 111.3 | Z100: 118.3 | AA100: 125.7 | AB100: 113.4 | AC100: 117.5 | AD100: 125.4
...

Sheet Sheet3
A1: Sector | B1: Broader Buckets | C1: Rural | D1: Urban | E1: Rural+Urban | F1: Rural | G1: Urban | H1: Rural+Urban | I1: Rural | J1: Urban | K1: Rural+Urban | L1: Rural | M1: Urban | N1: Rural+Urban | O1: Rural | P1: Urban | Q1: Rural+Urban | R1: Rural | S1: Urban | T1: Rural+Urban | U1: Rural | V1: Urban | W1: Rural+Urban | X1: Rural | Y1: Urban | Z1: Rural+Urban | AA1: Rural | AB1: Urban | AC1: Rural+Urban | AD1: Rural | AE1: Urban | AF1: Rural+Urban | AG1: Rural | AH1: Urban | AI1: Rural+Urban | AJ1: Rural | AK1: Urban | AL1: Rural+Urban | AM1: Rural | AN1: Urban | AO1: Rural+Urban | AP1: Rural | AQ1: Urban | AR1: Rural+Urban | AS1: Rural | AT1: Urban | AU1: Rural+Urban | AV1: Rural | AW1: Urban | AX1: Rural+Urban | AY1: Rural | AZ1: Urban | BA1: Rural+Urban | BB1: Rural | BC1: Urban | BD1: Rural+Urban | BE1: Rural | BF1: Urban | BG1: Rural+Urban | BH1: Rural | BI1: Urban | BJ1: Rural+Urban | BK1: Rural | BL1: Urban | BM1: Rural+Urban | BN1: Rural | BO1: Urban | BP1: Rural+Urban | BQ1: Rural | BR1: Urban | BS1: Rural+Urban | BT1: Rural | BU1: Urban | BV1: Rural+Urban | BW1: Rural | BX1: Urban | BY1: Rural+Urban | BZ1: Rural | CA1: Urban | CB1: Rural+Urban | CC1: Rural | CD1: Urban | CE1: Rural+Urban | CF1: Rural | CG1: Urban | CH1: Rural+Urban | CI1: Rural | CJ1: Urban | CK1: Rural+Urban | CL1: Rural | CM1: Urban | CN1: Rural+Urban | CO1: Rural | CP1: Urban | CQ1: Rural+Urban | CR1: Rural | CS1: Urban | CT1: Rural+Urban | CU1: Rural | CV1: Urban | CW1: Rural+Urban | CX1: Rural | CY1: Urban | CZ1: Rural+Urban | DA1: Rural | DB1: Urban | DC1: Rural+Urban | DD1: Rural | DE1: Urban | DF1: Rural+Urban | DG1: Rural | DH1: Urban | DI1: Rural+Urban | DJ1: Rural | DK1: Urban | DL1: Rural+Urban | DM1: Rural | DN1: Urban | DO1: Rural+Urban | DP1: Rural | DQ1: Urban | DR1: Rural+Urban | DS1: Rural | DT1: Urban | DU1: Rural+Urban | DV1: Rural | DW1: Urban | DX1: Rural+Urban | DY1: Rural | DZ1: Urban | EA1: Rural+Urban | EB1: Rural | EC1: Urban | ED1: Rural+Urban | EE1: Rural | EF1: Urban | EG1: Rural+Urban | EH1: Rural | EI1: Urban | EJ1: Rural+Urban | EK1: Rural | EL1: Urban | EM1: Rural+Urban | EN1: Rural | EO1: Urban | EP1: Rural+Urban | EQ1: Rural | ER1: Urban | ES1: Rural+Urban | ET1: Rural | EU1: Urban | EV1: Rural+Urban | EW1: Rural | EX1: Urban | EY1: Rural+Urban | EZ1: Rural | FA1: Urban | FB1: Rural+Urban | FC1: Rural | FD1: Urban | FE1: Rural+Urban | FF1: Rural | FG1: Urban | FH1: Rural+Urban | FI1: Rural | FJ1: Urban | FK1: Rural+Urban | FL1: Rural | FM1: Urban | FN1: Rural+Urban | FO1: Rural | FP1: Urban | FQ1: Rural+Urban | FR1: Rural | FS1: Urban | FT1: Rural+Urban | FU1: Rural | FV1: Urban | FW1: Rural+Urban | FX1: Rural | FY1: Urban | FZ1: Rural+Urban | GA1: Rural | GB1: Urban | GC1: Rural+Urban | GD1: Rural | GE1: Urban | GF1: Rural+Urban | GG1: Rural | GH1: Urban | GI1: Rural+Urban | GJ1: Rural | GK1: Urban | GL1: Rural+Urban | GM1: Rural | GN1: Urban | GO1: Rural+Urban | GP1: Rural | GQ1: Urban | GR1: Rural+Urban | GS1: Rural | GT1: Urban | GU1: Rural+Urban | GV1: Rural | GW1: Urban | GX1: Rural+Urban | GY1: Rural | GZ1: Urban | HA1: Rural+Urban | HB1: Rural | HC1: Urban | HD1: Rural+Urban | HE1: Rural | HF1: Urban | HG1: Rural+Urban | HH1: Rural | HI1: Urban | HJ1: Rural+Urban | HK1: Rural | HL1: Urban | HM1: Rural+Urban | HN1: Rural | HO1: Urban | HP1: Rural+Urban | HQ1: Rural | HR1: Urban | HS1: Rural+Urban | HT1: Rural | HU1: Urban | HV1: Rural+Urban | HW1: Rural | HX1: Urban | HY1: Rural+Urban | HZ1: Rural | IA1: Urban | IB1: Rural+Urban | IC1: Rural | ID1: Urban | IE1: Rural+Urban | IF1: Rural | IG1: Urban | IH1: Rural+Urban | II1: Rural | IJ1: Urban | IK1: Rural+Urban | IL1: Rural | IM1: Urban | IN1: Rural+Urban | IO1: Rural | IP1: Urban | IQ1: Rural+Urban | IR1: Rural | IS1: Urban | IT1: Rural+Urban | IU1: Rural | IV1: Urban | IW1: Rural+Urban | IX1: Rural | IY1: Urban | IZ1: Rural+Urban | JA1: Rural | JB1: Urban | JC1: Rural+Urban | JD1: Rural | JE1: Urban | JF1: Rural+Urban | JG1: Rural | JH1: Urban | JI1: Rural+Urban | JJ1: Rural | JK1: Urban | JL1: Rural+Urban | JM1: Rural | JN1: Urban | JO1: Rural+Urban | JP1: Rural | JQ1: Urban | JR1: Rural+Urban | JS1: Rural | JT1: Urban | JU1: Rural+Urban | JV1: Rural | JW1: Urban | JX1: Rural+Urban | JY1: Rural | JZ1: Urban | KA1: Rural+Urban | KB1: Rural | KC1: Urban | KD1: Rural+Urban | KE1: Rural | KF1: Urban | KG1: Rural+Urban | KH1: Rural | KI1: Urban | KJ1: Rural+Urban | KK1: Rural | KL1: Urban | KM1: Rural+Urban | KN1: Rural | KO1: Urban | KP1: Rural+Urban | KQ1: Rural | KR1: Urban | KS1: Rural+Urban | KT1: Rural | KU1: Urban | KV1: Rural+Urban | KW1: Rural | KX1: Urban | KY1: Rural+Urban | KZ1: Rural | LA1: Urban | LB1: Rural+Urban | LC1: Rural | LD1: Urban | LE1: Rural+Urban | LF1: Rural | LG1: Urban | LH1: Rural+Urban | LI1: Rural | LJ1: Urban | LK1: Rural+Urban | LL1: Rural | LM1: Urban | LN1: Rural+Urban | LO1: Rural | LP1: Urban | LQ1: Rural+Urban | LR1: Rural | LS1: Urban | LT1: Rural+Urban | LU1: Rural | LV1: Urban | LW1: Rural+Urban | LX1: Rural | LY1: Urban | LZ1: Rural+Urban | MA1: Rural | MB1: Urban | MC1: Rural+Urban | MD1: Rural | ME1: Urban | MF1: Rural+Urban | MG1: Rural | MH1: Urban | MI1: Rural+Urban | MJ1: Rural | MK1: Urban | ML1: Rural+Urban | MM1: Rural | MN1: Urban | MO1: Rural+Urban | MP1: Rural | MQ1: Urban | MR1: Rural+Urban | MS1: Rural | MT1: Urban | MU1: Rural+Urban | MV1: Rural | MW1: Urban | MX1: Rural+Urban | MY1: Rural | MZ1: Urban | NA1: Rural+Urban | NB1: Rural | NC1: Urban | ND1: Rural+Urban | NE1: Rural | NF1: Urban | NG1: Rural+Urban | NH1: Rural | NI1: Urban | NJ1: Rural+Urban
A2: Year | C2: 2013 | D2: 2013 | E2: 2013 | F2: 2013 | G2: 2013 | H2: 2013 | I2: 2013 | J2: 2013 | K2: 2013 | L2: 2013 | M2: 2013 | N2: 2013 | O2: 2013 | P2: 2013 | Q2: 2013 | R2: 2013 | S2: 2013 | T2: 2013 | U2: 2013 | V2: 2013 | W2: 2013 | X2: 2013 | Y2: 2013 | Z2: 2013 | AA2: 2013 | AB2: 2013 | AC2: 2013 | AD2: 2013 | AE2: 2013 | AF2: 2013 | AG2: 2013 | AH2: 2013 | AI2: 2013 | AJ2: 2013 | AK2: 2013 | AL2: 2013 | AM2: 2014 | AN2: 2014 | AO2: 2014 | AP2: 2014 | AQ2: 2014 | AR2: 2014 | AS2: 2014 | AT2: 2014 | AU2: 2014 | AV2: 2014 | AW2: 2014 | AX2: 2014 | AY2: 2014 | AZ2: 2014 | BA2: 2014 | BB2: 2014 | BC2: 2014 | BD2: 2014 | BE2: 2014 | BF2: 2014 | BG2: 2014 | BH2: 2014 | BI2: 2014 | BJ2: 2014 | BK2: 2014 | BL2: 2014 | BM2: 2014 | BN2: 2014 | BO2: 2014 | BP2: 2014 | BQ2: 2014 | BR2: 2014 | BS2: 2014 | BT2: 2014 | BU2: 2014 | BV2: 2014 | BW2: 2015 | BX2: 2015 | BY2: 2015 | BZ2: 2015 | CA2: 2015 | CB2: 2015 | CC2: 2015 | CD2: 2015 | CE2: 2015 | CF2: 2015 | CG2: 2015 | CH2: 2015 | CI2: 2015 | CJ2: 2015 | CK2: 2015 | CL2: 2015 | CM2: 2015 | CN2: 2015 | CO2: 2015 | CP2: 2015 | CQ2: 2015 | CR2: 2015 | CS2: 2015 | CT2: 2015 | CU2: 2015 | CV2: 2015 | CW2: 2015 | CX2: 2015 | CY2: 2015 | CZ2: 2015 | DA2: 2015 | DB2: 2015 | DC2: 2015 | DD2: 2015 | DE2: 2015 | DF2: 2015 | DG2: 2016 | DH2: 2016 | DI2: 2016 | DJ2: 2016 | DK2: 2016 | DL2: 2016 | DM2: 2016 | DN2: 2016 | DO2: 2016 | DP2: 2016 | DQ2: 2016 | DR2: 2016 | DS2: 2016 | DT2: 2016 | DU2: 2016 | DV2: 2016 | DW2: 2016 | DX2: 2016 | DY2: 2016 | DZ2: 2016 | EA2: 2016 | EB2: 2016 | EC2: 2016 | ED2: 2016 | EE2: 2016 | EF2: 2016 | EG2: 2016 | EH2: 2016 | EI2: 2016 | EJ2: 2016 | EK2: 2016 | EL2: 2016 | EM2: 2016 | EN2: 2016 | EO2: 2016 | EP2: 2016 | EQ2: 2017 | ER2: 2017 | ES2: 2017 | ET2: 2017 | EU2: 2017 | EV2: 2017 | EW2: 2017 | EX2: 2017 | EY2: 2017 | EZ2: 2017 | FA2: 2017 | FB2: 2017 | FC2: 2017 | FD2: 2017 | FE2: 2017 | FF2: 2017 | FG2: 2017 | FH2: 2017 | FI2: 2017 | FJ2: 2017 | FK2: 2017 | FL2: 2017 | FM2: 2017 | FN2: 2017 | FO2: 2017 | FP2: 2017 | FQ2: 2017 | FR2: 2017 | FS2: 2017 | FT2: 2017 | FU2: 2017 | FV2: 2017 | FW2: 2017 | FX2: 2017 | FY2: 2017 | FZ2: 2017 | GA2: 2018 | GB2: 2018 | GC2: 2018 | GD2: 2018 | GE2: 2018 | GF2: 2018 | GG2: 2018 | GH2: 2018 | GI2: 2018 | GJ2: 2018 | GK2: 2018 | GL2: 2018 | GM2: 2018 | GN2: 2018 | GO2: 2018 | GP2: 2018 | GQ2: 2018 | GR2: 2018 | GS2: 2018 | GT2: 2018 | GU2: 2018 | GV2: 2018 | GW2: 2018 | GX2: 2018 | GY2: 2018 | GZ2: 2018 | HA2: 2018 | HB2: 2018 | HC2: 2018 | HD2: 2018 | HE2: 2018 | HF2: 2018 | HG2: 2018 | HH2: 2018 | HI2: 2018 | HJ2: 2018 | HK2: 2019 | HL2: 2019 | HM2: 2019 | HN2: 2019 | HO2: 2019 | HP2: 2019 | HQ2: 2019 | HR2: 2019 | HS2: 2019 | HT2: 2019 | HU2: 2019 | HV2: 2019 | HW2: 2019 | HX2: 2019 | HY2: 2019 | HZ2: 2019 | IA2: 2019 | IB2: 2019 | IC2: 2019 | ID2: 2019 | IE2: 2019 | IF2: 2019 | IG2: 2019 | IH2: 2019 | II2: 2019 | IJ2: 2019 | IK2: 2019 | IL2: 2019 | IM2: 2019 | IN2: 2019 | IO2: 2019 | IP2: 2019 | IQ2: 2019 | IR2: 2020 | IS2: 2020 | IT2: 2020 | IU2: 2020 | IV2: 2020 | IW2: 2020 | IX2: 2020 | IY2: 2020 | IZ2: 2020 | JA2: 2020 | JB2: 2020 | JC2: 2020 | JD2: 2020 | JE2: 2020 | JF2: 2020 | JG2: 2020 | JH2: 2020 | JI2: 2020 | JJ2: 2020 | JK2: 2020 | JL2: 2020 | JM2: 2020 | JN2: 2020 | JO2: 2020 | JP2: 2020 | JQ2: 2020 | JR2: 2020 | JS2: 2020 | JT2: 2020 | JU2: 2020 | JV2: 2020 | JW2: 2020 | JX2: 2020 | JY2: 2020 | JZ2: 2020 | KA2: 2020 | KB2: 2021 | KC2: 2021 | KD2: 2021 | KE2: 2021 | KF2: 2021 | KG2: 2021 | KH2: 2021 | KI2: 2021 | KJ2: 2021 | KK2: 2021 | KL2: 2021 | KM2: 2021 | KN2: 2021 | KO2: 2021 | KP2: 2021 | KQ2: 2021 | KR2: 2021 | KS2: 2021 | KT2: 2021 | KU2: 2021 | KV2: 2021 | KW2: 2021 | KX2: 2021 | KY2: 2021 | KZ2: 2021 | LA2: 2021 | LB2: 2021 | LC2: 2021 | LD2: 2021 | LE2: 2021 | LF2: 2021 | LG2: 2021 | LH2: 2021 | LI2: 2021 | LJ2: 2021 | LK2: 2021 | LL2: 2022 | LM2: 2022 | LN2: 2022 | LO2: 2022 | LP2: 2022 | LQ2: 2022 | LR2: 2022 | LS2: 2022 | LT2: 2022 | LU2: 2022 | LV2: 2022 | LW2: 2022 | LX2: 2022 | LY2: 2022 | LZ2: 2022 | MA2: 2022 | MB2: 2022 | MC2: 2022 | MD2: 2022 | ME2: 2022 | MF2: 2022 | MG2: 2022 | MH2: 2022 | MI2: 2022 | MJ2: 2022 | MK2: 2022 | ML2: 2022 | MM2: 2022 | MN2: 2022 | MO2: 2022 | MP2: 2022 | MQ2: 2022 | MR2: 2022 | MS2: 2022 | MT2: 2022 | MU2: 2022 | MV2: 2023 | MW2: 2023 | MX2: 2023 | MY2: 2023 | MZ2: 2023 | NA2: 2023 | NB2: 2023 | NC2: 2023 | ND2: 2023 | NE2: 2023 | NF2: 2023 | NG2: 2023 | NH2: 2023 | NI2: 2023 | NJ2: 2023
A3: Month | C3: January | D3: January | E3: January | F3: February | G3: February | H3: February | I3: March | J3: March | K3: March | L3: April | M3: April | N3: April | O3: May | P3: May | Q3: May | R3: June | S3: June | T3: June | U3: July | V3: July | W3: July | X3: August | Y3: August | Z3: August | AA3: September | AB3: September | AC3: September | AD3: October | AE3: October | AF3: October | AG3: November | AH3: November | AI3: November | AJ3: December | AK3: December | AL3: December | AM3: January | AN3: January | AO3: January | AP3: February | AQ3: February | AR3: February | AS3: March | AT3: March | AU3: Marcrh | AV3: April | AW3: April | AX3: April | AY3: May | AZ3: May | BA3: May | BB3: June | BC3: June | BD3: June | BE3: July | BF3: July | BG3: July | BH3: August | BI3: August | BJ3: August | BK3: September | BL3: September | BM3: September | BN3: October | BO3: October | BP3: October | BQ3: November | BR3: November | BS3: November | BT3: December | BU3: December | BV3: December | BW3: January | BX3: January | BY3: January | BZ3: February | CA3: February | CB3: February | CC3: March | CD3: March | CE3: March | CF3: April | CG3: April | CH3: April | CI3: May | CJ3: May | CK3: May | CL3: June | CM3: June | CN3: June | CO3: July | CP3: July | CQ3: July | CR3: August | CS3: August | CT3: August | CU3: September | CV3: September | CW3: September | CX3: October | CY3: October | CZ3: October | DA3: November | DB3: November | DC3: November | DD3: December | DE3: December | DF3: December | DG3: January | DH3: January | DI3: January | DJ3: February | DK3: February | DL3: February | DM3: March | DN3: March | DO3: March | DP3: April | DQ3: April | DR3: April | DS3: May | DT3: May | DU3: May | DV3: June | DW3: June | DX3: June | DY3: July | DZ3: July | EA3: July | EB3: August | EC3: August | ED3: August | EE3: September | EF3: September | EG3: September | EH3: October | EI3: October | EJ3: October | EK3: November | EL3: November | EM3: November | EN3: December | EO3: December | EP3: December | EQ3: January | ER3: January | ES3: January | ET3: February | EU3: February | EV3: February | EW3: March | EX3: March | EY3: March | EZ3: April | FA3: April | FB3: April | FC3: May | FD3: May | FE3: May | FF3: June | FG3: June | FH3: June | FI3: July | FJ3: July | FK3: July | FL3: August | FM3: August | FN3: August | FO3: September | FP3: September | FQ3: September | FR3: October | FS3: October | FT3: October | FU3: November | FV3: November | FW3: November | FX3: December | FY3: December | FZ3: December | GA3: January | GB3: January | GC3: January | GD3: February | GE3: February | GF3: February | GG3: March | GH3: March | GI3: March | GJ3: April | GK3: April | GL3: April | GM3: May | GN3: May | GO3: May | GP3: June | GQ3: June | GR3: June | GS3: July | GT3: July | GU3: July | GV3: August | GW3: August | GX3: August | GY3: September | GZ3: September | HA3: September | HB3: October | HC3: October | HD3: October | HE3: November | HF3: November | HG3: November | HH3: December | HI3: December | HJ3: December | HK3: January | HL3: January | HM3: January | HN3: February | HO3: February | HP3: February | HQ3: March | HR3: March | HS3: March | HT3: May | HU3: May | HV3: May | HW3: June | HX3: June | HY3: June | HZ3: July | IA3: July | IB3: July | IC3: August | ID3: August | IE3: August | IF3: September | IG3: September | IH3: September | II3: October | IJ3: October | IK3: October | IL3: November | IM3: November | IN3: November | IO3: December | IP3: December | IQ3: December | IR3: January | IS3: January | IT3: January | IU3: February | IV3: February | IW3: February | IX3: March | IY3: March | IZ3: March | JA3: April | JB3: April | JC3: April | JD3: May | JE3: May | JF3: May | JG3: June | JH3: June | JI3: June | JJ3: July | JK3: July | JL3: July | JM3: August | JN3: August | JO3: August | JP3: September | JQ3: September | JR3: September | JS3: October | JT3: October | JU3: October | JV3: November | JW3: November | JX3: November | JY3: December | JZ3: December | KA3: December | KB3: January | KC3: January | KD3: January | KE3: February | KF3: February | KG3: February | KH3: March | KI3: March | KJ3: March | KK3: April | KL3: April | KM3: April | KN3: May | KO3: May | KP3: May | KQ3: June | KR3: June | KS3: June | KT3: July | KU3: July | KV3: July | KW3: August | KX3: August | KY3: August | KZ3: September | LA3: September | LB3: September | LC3: October | LD3: October | LE3: October | LF3: November | LG3: November | LH3: November | LI3: December | LJ3: December | LK3: December | LL3: January | LM3: January | LN3: January | LO3: February | LP3: February | LQ3: February | LR3: March | LS3: March | LT3: March | LU3: April | LV3: April | LW3: April | LX3: May | LY3: May | LZ3: May | MA3: June | MB3: June | MC3: June | MD3: July | ME3: July | MF3: July | MG3: August | MH3: August | MI3: August | MJ3: September | MK3: September | ML3: September | MM3: October | MN3: October | MO3: October | MP3: November | MQ3: November | MR3: November | MS3: December | MT3: December | MU3: December | MV3: January | MW3: January | MX3: January | MY3: February | MZ3: February | NA3: February | NB3: March | NC3: March | ND3: March | NE3: April | NF3: April | NG3: April | NH3: May | NI3: May | NJ3: May
A4: Cereals and products | B4: =VLOOKUP(A4, NOTES!C5:D30, 2,0) -> Food | C4: 107.5 | D4: 110.5 | E4: 108.4 | F4: 109.2 | G4: 112.9 | H4: 110.4 | I4: 110.2 | J4: 113.9 | K4: 111.4 | L4: 110.2 | M4: 114.6 | N4: 111.6 | O4: 110.9 | P4: 115.4 | Q4: 112.3 | R4: 112.3 | S4: 117 | T4: 113.8 | U4: 113.4 | V4: 117.8 | W4: 114.8 | X4: 114.3 | Y4: 118.3 | Z4: 115.6 | AA4: 115.4 | AB4: 118.6 | AC4: 116.4 | AD4: 116.3 | AE4: 118.9 | AF4: 117.1 | AG4: 117.3 | AH4: 119.8 | AI4: 118.1 | AJ4: 118.4 | AK4: 120.5 | AL4: 119.1 | AM4: 118.9 | AN4: 121.2 | AO4: 119.6 | AP4: 119.4 | AQ4: 121.9 | AR4: 120.2 | AS4: 120.1 | AT4: 122.1 | AU4: 120.7 | AV4: 120.2 | AW4: 122.5 | AX4: 120.9 | AY4: 120.3 | AZ4: 122.7 | BA4: 121.1 | BB4: 120.7 | BC4: 123.1 | BD4: 121.5 | BE4: 121.7 | BF4: 123.8 | BG4: 122.4 | BH4: 121.8 | BI4: 124.8 | BJ4: 122.7 | BK4: 122.3 | BL4: 124.2 | BM4: 122.9 | BN4: 122.6 | BO4: 124.6 | BP4: 123.2 | BQ4: 122.7 | BR4: 124.5 | BS4: 123.3 | BT4: 122.4 | BU4: 124 | BV4: 122.9 | BW4: 123.1 | BX4: 124 | BY4: 123.4 | BZ4: 123.4 | CA4: 124.3 | CB4: 123.7 | CC4: 123.3 | CD4: 124 | CE4: 123.5 | CF4: 123.3 | CG4: 123.8 | CH4: 123.5 | CI4: 123.5 | CJ4: 123.8 | CK4: 123.6 | CL4: 124.1 | CM4: 123.6 | CN4: 123.9 | CO4: 124 | CP4: 123.2 | CQ4: 123.7 | CR4: 124.7 | CS4: 123.1 | CT4: 124.2 | CU4: 125.1 | CV4: 123.4 | CW4: 124.6 | CX4: 125.6 | CY4: 123.6 | CZ4: 125 | DA4: 126.1 | DB4: 124 | DC4: 125.4 | DD4: 126.3 | DE4: 124.3 | DF4: 125.7 | DG4: 126.8 | DH4: 124.7 | DI4: 126.1 | DJ4: 127.1 | DK4: 124.8 | DL4: 126.4 | DM4: 127.3 | DN4: 124.8 | DO4: 126.5 | DP4: 127.4 | DQ4: 124.9 | DR4: 126.6 | DS4: 127.6 | DT4: 125 | DU4: 126.8 | DV4: 128.6 | DW4: 125.9 | DX4: 127.7 | DY4: 129.3 | DZ4: 126.8 | EA4: 128.5 | EB4: 130.1 | EC4: 127.6 | ED4: 129.3 | EE4: 130.8 | EF4: 128.1 | EG4: 129.9 | EH4: 131.3 | EI4: 128.7 | EJ4: 130.5 | EK4: 132 | EL4: 130.2 | EM4: 131.4 | EN4: 132.6 | EO4: 131.6 | EP4: 132.3 | EQ4: 133.1 | ER4: 132.2 | ES4: 132.8 | ET4: 133.3 | EU4: 132.8 | EV4: 133.1 | EW4: 133.6 | EX4: 132.7 | EY4: 133.3 | EZ4: 133.2 | FA4: 132.7 | FB4: 133 | FC4: 133.1 | FD4: 132.6 | FE4: 132.9 | FF4: 133.5 | FG4: 132.9 | FH4: 133.3 | FI4: 134 | FJ4: 132.8 | FK4: 133.6 | FL4: 134.8 | FM4: 133.2 | FN4: 134.3 | FO4: 135.2 | FP4: 133.6 | FQ4: 134.7 | FR4: 135.9 | FS4: 133.9 | FT4: 135.3 | FU4: 136.3 | FV4: 134.3 | FW4: 135.7 | FX4: 136.4 | FY4: 134.4 | FZ4: 135.8 | GA4: 136.6 | GB4: 134.6 | GC4: 136 | GD4: 136.4 | GE4: 134.8 | GF4: 135.9 | GG4: 136.8 | GH4: 135 | GI4: 136.2 | GJ4: 137.1 | GK4: 135 | GL4: 136.4 | GM4: 137.4 | GN4: 135 | GO4: 136.6 | GP4: 137.6 | GQ4: 135.3 | GR4: 136.9 | GS4: 138.4 | GT4: 135.6 | GU4: 137.5 | GV4: 139.2 | GW4: 136.5 | GX4: 138.3 | GY4: 139.4 | GZ4: 137 | HA4: 138.6 | HB4: 139.3 | HC4: 137.6 | HD4: 137.4 | HE4: 137.1 | HF4: 138.1 | HG4: 137.4 | HH4: 137.1 | HI4: 138.5 | HJ4: 137.5 | HK4: 136.6 | HL4: 138.3 | HM4: 137.1 | HN4: 136.8 | HO4: 139.4 | HP4: 137.6 | HQ4: 136.9 | HR4: 139.7 | HS4: 137.8 | HT4: 137.4 | HU4: 140.4 | HV4: 138.3 | HW4: 137.8 | HX4: 140.7 | HY4: 138.7 | HZ4: 138.4 | IA4: 141.4 | IB4: 139.3 | IC4: 139.2 | ID4: 142.1 | IE4: 140.1 | IF4: 140.1 | IG4: 142.7 | IH4: 140.9 | II4: 141 | IJ4: 143.5 | IK4: 141.8 | IL4: 141.8 | IM4: 144.1 | IN4: 142.5 | IO4: 142.8 | IP4: 144.9 | IQ4: 143.5 | IR4: 143.7 | IS4: 145.6 | IT4: 144.3 | IU4: 144.2 | IV4: 146.2 | IW4: 144.8 | IX4: 144.4 | IY4: 146.5 | IZ4: 145.1 | JA4: 147.2 | JB4: 151.8 | JC4: 148.7 | JD4: NA | JE4: NA | JF4: NA | JG4: 148.2 | JH4: 152.7 | JI4: 149.6 | JJ4: 148.2 | JK4: 152.7 | JL4: 149.6 | JM4: 147.6 | JN4: 151.6 | JO4: 148.9 | JP4: 146.9 | JQ4: 151.5 | JR4: 148.4 | JS4: 146 | JT4: 150.6 | JU4: 147.5 | JV4: 145.4 | JW4: 149.7 | JX4: 146.8 | JY4: 144.6 | JZ4: 149 | KA4: 146 | KB4: 143.4 | KC4: 148 | KD4: 144.9 | KE4: 142.8 | KF4: 147.6 | KG4: 144.3 | KH4: 142.5 | KI4: 147.5 | KJ4: 144.1 | KK4: 142.7 | KL4: 147.6 | KM4: 144.3 | KN4: 145.1 | KO4: 148.8 | KP4: 146.3 | KQ4: 145.6 | KR4: 149.2 | KS4: 146.7 | KT4: 145.1 | KU4: 149.1 | KV4: 146.4 | KW4: 144.9 | KX4: 149.3 | KY4: 146.6 | KZ4: 145.4 | LA4: 149.3 | LB4: 146.6 | LC4: 146.1 | LD4: 150.1 | LE4: 147.4 | LF4: 146.9 | LG4: 151 | LH4: 148.2 | LI4: 147.4 | LJ4: 151.6 | LK4: 148.7 | LL4: 148.3 | LM4: 152.2 | LN4: 149.5 | LO4: 148.8 | LP4: 152.5 | LQ4: 150 | LR4: 150.2 | LS4: 153.7 | LT4: 151.3 | LU4: 151.8 | LV4: 155.4 | LW4: 152.9 | LX4: 152.9 | LY4: 156.7 | LZ4: 154.1 | MA4: 153.8 | MB4: 157.5 | MC4: 155 | MD4: 155.2 | ME4: 159.3 | MF4: 156.5 | MG4: 159.5 | MH4: 162.1 | MI4: 160.3 | MJ4: 162.9 | MK4: 164.9 | ML4: 163.5 | MM4: 164.7 | MN4: 166.4 | MO4: 165.2 | MP4: 166.9 | MQ4: 168.4 | MR4: 167.4 | MS4: 168.8 | MT4: 170.2 | MU4: 169.2 | MV4: 174 | MW4: 173.3 | MX4: 173.8 | MY4: 174.2 | MZ4: 174.7 | NA4: 174.4 | NB4: 174.3 | NC4: 174.7 | ND4: 174.4 | NE4: 173.3 | NF4: 174.8 | NG4: 173.8 | NH4: 173.2 | NI4: 174.7 | NJ4: 173.7
A5: Meat and fish | B5: =VLOOKUP(A5, NOTES!C6:D31, 2,0) -> Food | C5: 106.3 | D5: 109.1 | E5: 107.3 | F5: 108.7 | G5: 112.9 | H5: 110.2 | I5: 108.8 | J5: 111.4 | K5: 109.7 | L5: 109.5 | M5: 113.4 | N5: 110.9 | O5: 109.8 | P5: 114.2 | Q5: 111.3 | R5: 112.1 | S5: 120.1 | T5: 114.9 | U5: 114.9 | V5: 119.2 | W5: 116.4 | X5: 115.4 | Y5: 120.4 | Z5: 117.2 | AA5: 115.7 | AB5: 119.1 | AC5: 116.9 | AD5: 115.4 | AE5: 118.1 | AF5: 116.3 | AG5: 114.9 | AH5: 116.3 | AI5: 115.4 | AJ5: 115.9 | AK5: 118.1 | AL5: 116.7 | AM5: 117.1 | AN5: 122 | AO5: 118.8 | AP5: 117.7 | AQ5: 122 | AR5: 119.2 | AS5: 118.1 | AT5: 121.4 | AU5: 119.3 | AV5: 118.9 | AW5: 121.7 | AX5: 119.9 | AY5: 120.2 | AZ5: 124.1 | BA5: 121.6 | BB5: 121.6 | BC5: 125.9 | BD5: 123.1 | BE5: 122.5 | BF5: 126.4 | BG5: 123.9 | BH5: 122.8 | BI5: 127.3 | BJ5: 124.4 | BK5: 122.4 | BL5: 125.4 | BM5: 123.5 | BN5: 122.5 | BO5: 126.1 | BP5: 123.8 | BQ5: 122.6 | BR5: 125.6 | BS5: 123.7 | BT5: 122.4 | BU5: 124.7 | BV5: 123.2 | BW5: 123.1 | BX5: 125.5 | BY5: 123.9 | BZ5: 124.4 | CA5: 126.5 | CB5: 125.1 | CC5: 124.7 | CD5: 126.7 | CE5: 125.4 | CF5: 125.5 | CG5: 128.2 | CH5: 126.4 | CI5: 127.1 | CJ5: 129.7 | CK5: 128 | CL5: 130.4 | CM5: 134.4 | CN5: 131.8 | CO5: 131.5 | CP5: 134.3 | CQ5: 132.5 | CR5: 131.3 | CS5: 131.7 | CT5: 131.4 | CU5: 131.1 | CV5: 129 | CW5: 130.4 | CX5: 130.4 | CY5: 128.6 | CZ5: 129.8 | DA5: 130.6 | DB5: 129.8 | DC5: 130.3 | DD5: 131.3 | DE5: 131.7 | DF5: 131.4 | DG5: 133.2 | DH5: 135.9 | DI5: 134.1 | DJ5: 133.7 | DK5: 135.1 | DL5: 134.2 | DM5: 134.4 | DN5: 136.3 | DO5: 135.1 | DP5: 135.4 | DQ5: 139.3 | DR5: 136.8 | DS5: 137.5 | DT5: 142.1 | DU5: 139.1 | DV5: 138.6 | DW5: 143.9 | DX5: 140.5 | DY5: 139.5 | DZ5: 144.2 | EA5: 141.2 | EB5: 138.8 | EC5: 140.3 | ED5: 139.3 | EE5: 138.2 | EF5: 137.7 | EG5: 138 | EH5: 137.6 | EI5: 138.4 | EJ5: 137.9 | EK5: 137.4 | EL5: 138.5 | EM5: 137.8 | EN5: 137.3 | EO5: 138.2 | EP5: 137.6 | EQ5: 137.8 | ER5: 138.9 | ES5: 138.2 | ET5: 138.3 | EU5: 139.8 | EV5: 138.8 | EW5: 138.8 | EX5: 139.4 | EY5: 139 | EZ5: 138.7 | FA5: 140.6 | FB5: 139.4 | FC5: 140.3 | FD5: 144.1 | FE5: 141.6 | FF5: 143.7 | FG5: 148.7 | FH5: 145.5 | FI5: 144.2 | FJ5: 148.4 | FK5: 145.7 | FL5: 143.1 | FM5: 143.9 | FN5: 143.4 | FO5: 142 | FP5: 143 | FQ5: 142.4 | FR5: 141.9 | FS5: 142.8 | FT5: 142.2 | FU5: 142.5 | FV5: 142.1 | FW5: 142.4 | FX5: 143.7 | FY5: 142.6 | FZ5: 143.3 | GA5: 144.4 | GB5: 143.7 | GC5: 144.2 | GD5: 143.7 | GE5: 143 | GF5: 143.5 | GG5: 143.8 | GH5: 143.1 | GI5: 143.6 | GJ5: 144.5 | GK5: 144.3 | GL5: 144.4 | GM5: 145.7 | GN5: 148.2 | GO5: 146.6 | GP5: 148.1 | GQ5: 149.7 | GR5: 148.7 | GS5: 149.3 | GT5: 148.6 | GU5: 149.1 | GV5: 148.8 | GW5: 146.4 | GX5: 148 | GY5: 147.2 | GZ5: 143.1 | HA5: 145.8 | HB5: 147.6 | HC5: 144.9 | HD5: 149.5 | HE5: 150.8 | HF5: 146.3 | HG5: 149.2 | HH5: 151.9 | HI5: 147.8 | HJ5: 150.5 | HK5: 152.5 | HL5: 149.4 | HM5: 151.4 | HN5: 153 | HO5: 150.1 | HP5: 152 | HQ5: 154.1 | HR5: 151.1 | HS5: 153 | HT5: 159.5 | HU5: 156.7 | HV5: 158.5 | HW5: 163.5 | HX5: 159.6 | HY5: 162.1 | HZ5: 164 | IA5: 160.2 | IB5: 162.7 | IC5: 161.9 | ID5: 158.3 | IE5: 160.6 | IF5: 161.9 | IG5: 158.7 | IH5: 160.8 | II5: 161.6 | IJ5: 159.8 | IK5: 161 | IL5: 163.7 | IM5: 162.4 | IN5: 163.2 | IO5: 165.3 | IP5: 164.5 | IQ5: 165 | IR5: 167.3 | IS5: 167.6 | IT5: 167.4 | IU5: 167.5 | IV5: 167.6 | IW5: 167.5 | IX5: 166.8 | IY5: 167.5 | IZ5: 167 | JA5: NA | JB5: NA | JC5: NA | JD5: NA | JE5: NA | JF5: NA | JG5: 190.3 | JH5: 197 | JI5: 192.7 | JJ5: 190.3 | JK5: 197 | JL5: 192.7 | JM5: 187.2 | JN5: 197.8 | JO5: 190.9 | JP5: 183.9 | JQ5: 193.1 | JR5: 187.1 | JS5: 186.3 | JT5: 193.7 | JU5: 188.9 | JV5: 188.6 | JW5: 195.5 | JX5: 191 | JY5: 188.5 | JZ5: 195.7 | KA5: 191 | KB5: 187.5 | KC5: 194.8 | KD5: 190.1 | KE5: 184 | KF5: 191.2 | KG5: 186.5 | KH5: 189.4 | KI5: 197.5 | KJ5: 192.2 | KK5: 195.5 | KL5: 202.5 | KM5: 198 | KN5: 198.5 | KO5: 204.3 | KP5: 200.5 | KQ5: 200.1 | KR5: 205.5 | KS5: 202 | KT5: 204.5 | KU5: 210.9 | KV5: 206.8 | KW5: 202.3 | KX5: 207.4 | KY5: 204 | KZ5: 202.1 | LA5: 207.4 | LB5: 204 | LC5: 202.5 | LD5: 208.4 | LE5: 204.6 | LF5: 199.8 | LG5: 204.9 | LH5: 201.6 | LI5: 197 | LJ5: 202.2 | LK5: 198.8 | LL5: 196.9 | LM5: 202.1 | LN5: 198.7 | LO5: 198.1 | LP5: 205.2 | LQ5: 200.6 | LR5: 208 | LS5: 215.8 | LT5: 210.7 | LU5: 209.7 | LV5: 215.8 | LW5: 211.8 | LX5: 214.7 | LY5: 221.2 | LZ5: 217 | MA5: 217.2 | MB5: 223.4 | MC5: 219.4 | MD5: 210.8 | ME5: 217.1 | MF5: 213 | MG5: 204.1 | MH5: 210.9 | MI5: 206.5 | MJ5: 206.7 | MK5: 213.7 | ML5: 209.2 | MM5: 208.8 | MN5: 214.9 | MO5: 210.9 | MP5: 207.2 | MQ5: 213.4 | MR5: 209.4 | MS5: 206.9 | MT5: 212.9 | MU5: 209 | MV5: 208.3 | MW5: 215.2 | MX5: 210.7 | MY5: 205.2 | MZ5: 212.2 | NA5: 207.7 | NB5: 205.2 | NC5: 212.2 | ND5: 207.7 | NE5: 206.9 | NF5: 213.7 | NG5: 209.3 | NH5: 211.5 | NI5: 219.4 | NJ5: 214.3
A6: Egg | B6: =VLOOKUP(A6, NOTES!C7:D32, 2,0) -> Food | C6: 108.1 | D6: 113 | E6: 110 | F6: 110.2 | G6: 116.9 | H6: 112.8 | I6: 109.9 | J6: 113.2 | K6: 111.2 | L6: 106.9 | M6: 106 | N6: 106.6 | O6: 105.9 | P6: 102.7 | Q6: 104.7 | R6: 108.1 | S6: 112.5 | T6: 109.8 | U6: 110.5 | V6: 114 | W6: 111.9 | X6: 111.1 | Y6: 112.7 | Z6: 111.7 | AA6: 111.7 | AB6: 113.2 | AC6: 112.3 | AD6: 112.6 | AE6: 114.5 | AF6: 113.3 | AG6: 116.2 | AH6: 122.6 | AI6: 118.7 | AJ6: 120.4 | AK6: 128.5 | AL6: 123.5 | AM6: 120.5 | AN6: 129.9 | AO6: 124.1 | AP6: 121.2 | AQ6: 124.5 | AR6: 122.5 | AS6: 120.7 | AT6: 121.5 | AU6: 121 | AV6: 118.1 | AW6: 113.3 | AX6: 116.2 | AY6: 116.9 | AZ6: 114.2 | BA6: 115.9 | BB6: 116.1 | BC6: 115.4 | BD6: 115.8 | BE6: 117.7 | BF6: 118 | BG6: 117.8 | BH6: 117.8 | BI6: 116.5 | BJ6: 117.3 | BK6: 117.8 | BL6: 116.4 | BM6: 117.3 | BN6: 118.3 | BO6: 117.8 | BP6: 118.1 | BQ6: 119.9 | BR6: 122.7 | BS6: 121 | BT6: 121.8 | BU6: 126.3 | BV6: 123.5 | BW6: 122.1 | BX6: 126.6 | BY6: 123.8 | BZ6: 122.1 | CA6: 119.5 | CB6: 121.1 | CC6: 118.9 | CD6: 113.5 | CE6: 116.8 | CF6: 117.2 | CG6: 110 | CH6: 114.4 | CI6: 117.3 | CJ6: 111.3 | CK6: 115 | CL6: 122.1 | CM6: 120.9 | CN6: 121.6 | CO6: 122 | CP6: 119.5 | CQ6: 121 | CR6: 121.3 | CS6: 118.1 | CT6: 120.1 | CU6: 120.7 | CV6: 115.6 | CW6: 118.7 | CX6: 120.8 | CY6: 115.9 | CZ6: 118.9 | DA6: 121.7 | DB6: 121.5 | DC6: 121.6 | DD6: 123.3 | DE6: 127.1 | DF6: 124.8 | DG6: 126.5 | DH6: 132 | DI6: 128.6 | DJ6: 127.7 | DK6: 130.3 | DL6: 128.7 | DM6: 125.1 | DN6: 123.7 | DO6: 124.6 | DP6: 123.4 | DQ6: 119.9 | DR6: 122 | DS6: 124.4 | DT6: 127 | DU6: 125.4 | DV6: 126.6 | DW6: 130.9 | DX6: 128.3 | DY6: 129.6 | DZ6: 136.6 | EA6: 132.3 | EB6: 130.3 | EC6: 133.7 | ED6: 131.6 | EE6: 130.5 | EF6: 130.6 | EG6: 130.5 | EH6: 130.1 | EI6: 130.3 | EJ6: 130.2 | EK6: 130.6 | EL6: 134.1 | EM6: 132 | EN6: 131.6 | EO6: 134.9 | EP6: 132.9 | EQ6: 131.9 | ER6: 132.6 | ES6: 132.2 | ET6: 129.3 | EU6: 129.3 | EV6: 129.3 | EW6: 128.8 | EX6: 128.4 | EY6: 128.6 | EZ6: 127.1 | FA6: 124.5 | FB6: 126.1 | FC6: 126.8 | FD6: 125.6 | FE6: 126.3 | FF6: 128 | FG6: 128.3 | FH6: 128.1 | FI6: 129.8 | FJ6: 129.4 | FK6: 129.6 | FL6: 130 | FM6: 128.3 | FN6: 129.3 | FO6: 130.5 | FP6: 129.7 | FQ6: 130.2 | FR6: 131 | FS6: 131.4 | FT6: 131.2 | FU6: 140.5 | FV6: 146.7 | FW6: 142.9 | FX6: 144.8 | FY6: 145.9 | FZ6: 145.2 | GA6: 143.8 | GB6: 143.6 | GC6: 143.7 | GD6: 140.6 | GE6: 139.9 | GF6: 140.3 | GG6: 140 | GH6: 135.5 | GI6: 138.3 | GJ6: 135.9 | GK6: 130.8 | GL6: 133.9 | GM6: 135.5 | GN6: 130.5 | GO6: 133.6 | GP6: 136.7 | GQ6: 133.9 | GR6: 135.6 | GS6: 139.3 | GT6: 139.1 | GU6: 139.2 | GV6: 139.1 | GW6: 136.6 | GX6: 138.1 | GY6: 136.6 | GZ6: 132.8 | HA6: 135.1 | HB6: 134.6 | HC6: 133.5 | HD6: 137.3 | HE6: 136.7 | HF6: 137.8 | HG6: 137.1 | HH6: 137.4 | HI6: 141.1 | HJ6: 138.8 | HK6: 138.2 | HL6: 143.5 | HM6: 140.2 | HN6: 139.1 | HO6: 145.3 | HP6: 141.5 | HQ6: 138.7 | HR6: 142.9 | HS6: 140.3 | HT6: 134.5 | HU6: 138.3 | HV6: 136 | HW6: 136.2 | HX6: 140.4 | HY6: 137.8 | HZ6: 138.4 | IA6: 142.5 | IB6: 140 | IC6: 137.1 | ID6: 140.8 | IE6: 138.5 | IF6: 138.3 | IG6: 141.6 | IH6: 139.6 | II6: 141.2 | IJ6: 144.7 | IK6: 142.6 | IL6: 143.8 | IM6: 148.4 | IN6: 145.6 | IO6: 149.5 | IP6: 153.7 | IQ6: 151.1 | IR6: 153.5 | IS6: 157 | IT6: 154.9 | IU6: 150.9 | IV6: 153.1 | IW6: 151.8 | IX6: 147.6 | IY6: 148.9 | IZ6: 148.1 | JA6: 146.9 | JB6: 151.9 | JC6: 148.8 | JD6: NA | JE6: NA | JF6: NA | JG6: 149.4 | JH6: 154.6 | JI6: 151.4 | JJ6: 149.4 | JK6: 154.6 | JL6: 151.4 | JM6: 148.4 | JN6: 154.5 | JO6: 150.8 | JP6: 149.5 | JQ6: 157.3 | JR6: 152.5 | JS6: 159.2 | JT6: 164.8 | JU6: 161.4 | JV6: 171.6 | JW6: 176.9 | JX6: 173.6 | JY6: 173.4 | JZ6: 178.3 | KA6: 175.3 | KB6: 173.4 | KC6: 178.4 | KD6: 175.3 | KE6: 168 | KF6: 169.9 | KG6: 168.7 | KH6: 163.2 | KI6: 164.7 | KJ6: 163.8 | KK6: 163.4 | KL6: 166.4 | KM6: 164.6 | KN6: 168.6 | KO6: 173 | KP6: 170.3 | KQ6: 179.3 | KR6: 182.8 | KS6: 180.7 | KT6: 180.4 | KU6: 185 | KV6: 182.2 | KW6: 176.5 | KX6: 174.1 | KY6: 172.8 | KZ6: 172 | LA6: 174.1 | LB6: 172.8 | LC6: 170.1 | LD6: 173 | LE6: 171.2 | LF6: 171.5 | LG6: 175.4 | LH6: 173 | LI6: 176.5 | LJ6: 180 | LK6: 177.9 | LL6: 178 | LM6: 180.1 | LN6: 178.8 | LO6: 175.5 | LP6: 176.4 | LQ6: 175.8 | LR6: 167.9 | LS6: 167.7 | LT6: 167.8 | LU6: 164.5 | LV6: 164.6 | LW6: 164.5 | LX6: 161.4 | LY6: 164.1 | LZ6: 162.4 | MA6: 169.6 | MB6: 172.8 | MC6: 170.8 | MD6: 174.3 | ME6: 176.6 | MF6: 175.2 | MG6: 168.3 | MH6: 170.6 | MI6: 169.2 | MJ6: 169 | MK6: 170.9 | ML6: 169.7 | MM6: 170.3 | MN6: 171.9 | MO6: 170.9 | MP6: 180.2 | MQ6: 183.2 | MR6: 181.4 | MS6: 189.1 | MT6: 191.9 | MU6: 190.2 | MV6: 192.9 | MW6: 197 | MX6: 194.5 | MY6: 173.9 | MZ6: 177.2 | NA6: 175.2 | NB6: 173.9 | NC6: 177.2 | ND6: 175.2 | NE6: 167.9 | NF6: 172.4 | NG6: 169.6 | NH6: 171 | NI6: 176.7 | NJ6: 173.2
A7: Milk and products | B7: =VLOOKUP(A7, NOTES!C8:D33, 2,0) -> Food | C7: 104.9 | D7: 103.6 | E7: 104.4 | F7: 105.4 | G7: 104 | H7: 104.9 | I7: 105.6 | J7: 104.3 | K7: 105.1 | L7: 106.3 | M7: 104.7 | N7: 105.7 | O7: 107.5 | P7: 105.5 | Q7: 106.8 | R7: 108.3 | S7: 107.3 | T7: 107.9 | U7: 109.3 | V7: 108.3 | W7: 108.9 | X7: 110 | Y7: 108.9 | Z7: 109.6 | AA7: 111 | AB7: 109.6 | AC7: 110.5 | AD7: 111.7 | AE7: 110.4 | AF7: 111.2 | AG7: 112.8 | AH7: 112 | AI7: 112.5 | AJ7: 113.8 | AK7: 112.8 | AL7: 113.4 | AM7: 114.4 | AN7: 113.6 | AO7: 114.1 | AP7: 115 | AQ7: 115.2 | AR7: 115.1 | AS7: 116.1 | AT7: 116.2 | AU7: 116.1 | AV7: 117 | AW7: 117 | AX7: 117 | AY7: 118 | AZ7: 119.1 | BA7: 118.4 | BB7: 119.3 | BC7: 120.4 | BD7: 119.7 | BE7: 120.6 | BF7: 121.6 | BG7: 121 | BH7: 121.9 | BI7: 122.2 | BJ7: 122 | BK7: 122.7 | BL7: 122.7 | BM7: 122.7 | BN7: 123.2 | BO7: 123.1 | BP7: 123.2 | BQ7: 124 | BR7: 124.6 | BS7: 124.2 | BT7: 124.2 | BU7: 124.9 | BV7: 124.5 | BW7: 124.9 | BX7: 125.2 | BY7: 125 | BZ7: 125.8 | CA7: 125.6 | CB7: 125.7 | CC7: 126 | CD7: 125.9 | CE7: 126 | CF7: 126.8 | CG7: 126.3 | CH7: 126.6 | CI7: 127.7 | CJ7: 126.6 | CK7: 127.3 | CL7: 128.7 | CM7: 127.3 | CN7: 128.2 | CO7: 128.7 | CP7: 127.7 | CQ7: 128.3 | CR7: 128.8 | CS7: 128 | CT7: 128.5 | CU7: 129.2 | CV7: 128.3 | CW7: 128.9 | CX7: 129.4 | CY7: 128.5 | CZ7: 129.1 | DA7: 129.5 | DB7: 128.6 | DC7: 129.2 | DD7: 129.8 | DE7: 128.6 | DF7: 129.4 | DG7: 130.3 | DH7: 129.2 | DI7: 129.9 | DJ7: 130.7 | DK7: 129.6 | DL7: 130.3 | DM7: 130.5 | DN7: 129.7 | DO7: 130.2 | DP7: 131.3 | DQ7: 130.2 | DR7: 130.9 | DS7: 132.4 | DT7: 130.4 | DU7: 131.7 | DV7: 133.6 | DW7: 131 | DX7: 132.6 | DY7: 134.5 | DZ7: 131.8 | EA7: 133.5 | EB7: 135.3 | EC7: 132.2 | ED7: 134.1 | EE7: 135.5 | EF7: 132.6 | EG7: 134.4 | EH7: 136 | EI7: 132.7 | EJ7: 134.8 | EK7: 136.2 | EL7: 132.9 | EM7: 135 | EN7: 136.3 | EO7: 133.1 | EP7: 135.1 | EQ7: 136.7 | ER7: 133.1 | ES7: 135.4 | ET7: 137.2 | EU7: 133.5 | EV7: 135.8 | EW7: 137.2 | EX7: 134.9 | EY7: 136.3 | EZ7: 137.7 | FA7: 136.3 | FB7: 137.2 | FC7: 138.2 | FD7: 136.8 | FE7: 137.7 | FF7: 138.6 | FG7: 137.3 | FH7: 138.1 | FI7: 139 | FJ7: 137.7 | FK7: 138.5 | FL7: 139.4 | FM7: 138.3 | FN7: 139 | FO7: 140.2 | FP7: 138.7 | FQ7: 139.6 | FR7: 141.5 | FS7: 139.1 | FT7: 140.6 | FU7: 141.5 | FV7: 139.5 | FW7: 140.8 | FX7: 141.9 | FY7: 139.5 | FZ7: 141 | GA7: 142 | GB7: 139.6 | GC7: 141.1 | GD7: 141.5 | GE7: 139.9 | GF7: 140.9 | GG7: 142 | GH7: 139.9 | GI7: 141.2 | GJ7: 142.4 | GK7: 140.3 | GL7: 141.6 | GM7: 142.9 | GN7: 140.7 | GO7: 142.1 | GP7: 143.2 | GQ7: 140.8 | GR7: 142.3 | GS7: 143.4 | GT7: 141 | GU7: 142.5 | GV7: 143.5 | GW7: 141.2 | GX7: 142.6 | GY7: 143.7 | GZ7: 141.5 | HA7: 142.9 | HB7: 141.9 | HC7: 141.5 | HD7: 141.9 | HE7: 141.9 | HF7: 141.6 | HG7: 141.8 | HH7: 142.4 | HI7: 141.6 | HJ7: 142.1 | HK7: 142.4 | HL7: 141.7 | HM7: 142.1 | HN7: 142.5 | HO7: 141.7 | HP7: 142.2 | HQ7: 142.5 | HR7: 141.9 | HS7: 142.3 | HT7: 142.6 | HU7: 142.4 | HV7: 142.5 | HW7: 143.2 | HX7: 143.4 | HY7: 143.3 | HZ7: 143.9 | IA7: 144.1 | IB7: 144 | IC7: 144.6 | ID7: 144.9 | IE7: 144.7 | IF7: 145.7 | IG7: 144.9 | IH7: 145.4 | II7: 146.5 | IJ7: 145.6 | IK7: 146.2 | IL7: 147.1 | IM7: 145.9 | IN7: 146.7 | IO7: 148.7 | IP7: 147.5 | IQ7: 148.3 | IR7: 150.5 | IS7: 149.3 | IT7: 150.1 | IU7: 150.9 | IV7: 150.7 | IW7: 150.8 | IX7: 151.7 | IY7: 151.1 | IZ7: 151.5 | JA7: 155.6 | JB7: 155.5 | JC7: 155.6 | JD7: NA | JE7: NA | JF7: NA | JG7: 153.3 | JH7: 153.4 | JI7: 153.3 | JJ7: 153.3 | JK7: 153.4 | JL7: 153.3 | JM7: 153.3 | JN7: 153.4 | JO7: 153.3 | JP7: 153.4 | JQ7: 153.9 | JR7: 153.6 | JS7: 153.6 | JT7: 153.7 | JU7: 153.6 | JV7: 153.8 | JW7: 153.9 | JX7: 153.8 | JY7: 154 | JZ7: 154.2 | KA7: 154.1 | KB7: 154 | KC7: 154.4 | KD7: 154.1 | KE7: 154.4 | KF7: 155.1 | KG7: 154.7 | KH7: 154.5 | KI7: 155.6 | KJ7: 154.9 | KK7: 155 | KL7: 156 | KM7: 155.4 | KN7: 155.8 | KO7: 156.5 | KP7: 156.1 | KQ7: 156.1 | KR7: 156.5 | KS7: 156.2 | KT7: 157.1 | KU7: 158.2 | KV7: 157.5 | KW7: 157.5 | KX7: 159.2 | KY7: 158.4 | KZ7: 158 | LA7: 159.1 | LB7: 158.4 | LC7: 158.4 | LD7: 159.2 | LE7: 158.7 | LF7: 159.1 | LG7: 159.6 | LH7: 159.3 | LI7: 159.8 | LJ7: 160 | LK7: 159.9 | LL7: 160.5 | LM7: 160.4 | LN7: 160.5 | LO7: 160.7 | LP7: 160.6 | LQ7: 160.7 | LR7: 162 | LS7: 162.6 | LT7: 162.2 | LU7: 163.8 | LV7: 164.2 | LW7: 163.9 | LX7: 164.6 | LY7: 165.4 | LZ7: 164.9 | MA7: 165.4 | MB7: 166.4 | MC7: 165.8 | MD7: 166.3 | ME7: 167.1 | MF7: 166.6 | MG7: 167.9 | MH7: 168.4 | MI7: 168.1 | MJ7: 169.5 | MK7: 170.1 | ML7: 169.7 | MM7: 170.9 | MN7: 171 | MO7: 170.9 | MP7: 172.3 | MQ7: 172.3 | MR7: 172.3 | MS7: 173.4 | MT7: 173.9 | MU7: 173.6 | MV7: 174.3 | MW7: 175.2 | MX7: 174.6 | MY7: 177 | MZ7: 177.9 | NA7: 177.3 | NB7: 177 | NC7: 177.9 | ND7: 177.3 | NE7: 178.2 | NF7: 178.8 | NG7: 178.4 | NH7: 179.6 | NI7: 179.4 | NJ7: 179.5
A8: Oils and fats | B8: =VLOOKUP(A8, NOTES!C9:D34, 2,0) -> Food | C8: 106.1 | D8: 103.4 | E8: 105.1 | F8: 106.7 | G8: 103.5 | H8: 105.5 | I8: 106.2 | J8: 102.7 | K8: 104.9 | L8: 105.7 | M8: 102.1 | N8: 104.4 | O8: 105.3 | P8: 101.5 | Q8: 103.9 | R8: 105.9 | S8: 101.3 | T8: 104.2 | U8: 106.2 | V8: 101.1 | W8: 104.3 | X8: 106.4 | Y8: 101.1 | Z8: 104.5 | AA8: 107.4 | AB8: 101.7 | AC8: 105.3 | AD8: 107.7 | AE8: 102.3 | AF8: 105.7 | AG8: 108.9 | AH8: 103.2 | AI8: 106.8 | AJ8: 109.5 | AK8: 103.4 | AL8: 107.3 | AM8: 109 | AN8: 102.9 | AO8: 106.8 | AP8: 109 | AQ8: 102.5 | AR8: 106.6 | AS8: 109.3 | AT8: 102.8 | AU8: 106.9 | AV8: 109.7 | AW8: 103.1 | AX8: 107.3 | AY8: 110.1 | AZ8: 103.5 | BA8: 107.7 | BB8: 110.3 | BC8: 103.4 | BD8: 107.8 | BE8: 110.4 | BF8: 103.5 | BG8: 107.9 | BH8: 110.6 | BI8: 103.6 | BJ8: 108 | BK8: 110.4 | BL8: 103.5 | BM8: 107.9 | BN8: 110.5 | BO8: 103.5 | BP8: 107.9 | BQ8: 110.5 | BR8: 103.2 | BS8: 107.8 | BT8: 110.2 | BU8: 103 | BV8: 107.6 | BW8: 111 | BX8: 104.3 | BY8: 108.5 | BZ8: 111.5 | CA8: 104.9 | CB8: 109.1 | CC8: 111.8 | CD8: 104.8 | CE8: 109.2 | CF8: 111.9 | CG8: 104.5 | CH8: 109.2 | CI8: 112.5 | CJ8: 105.2 | CK8: 109.8 | CL8: 114.1 | CM8: 106 | CN8: 111.1 | CO8: 113.5 | CP8: 106.3 | CQ8: 110.9 | CR8: 114 | CS8: 106.8 | CT8: 111.4 | CU8: 114.7 | CV8: 107 | CW8: 111.9 | CX8: 115.8 | CY8: 109 | CZ8: 113.3 | DA8: 117.8 | DB8: 110 | DC8: 114.9 | DD8: 118.3 | DE8: 110 | DF8: 115.3 | DG8: 118.9 | DH8: 109.7 | DI8: 115.5 | DJ8: 118.5 | DK8: 108.4 | DL8: 114.8 | DM8: 118.3 | DN8: 107.9 | DO8: 114.5 | DP8: 118.2 | DQ8: 108.9 | DR8: 114.8 | DS8: 118.2 | DT8: 109.6 | DU8: 115 | DV8: 118.6 | DW8: 110.2 | DX8: 115.5 | DY8: 119.5 | DZ8: 111 | EA8: 116.4 | EB8: 119.9 | EC8: 111.8 | ED8: 116.9 | EE8: 120.2 | EF8: 111.9 | EG8: 117.2 | EH8: 120.8 | EI8: 112.5 | EJ8: 117.8 | EK8: 121.1 | EL8: 112.6 | EM8: 118 | EN8: 121.6 | EO8: 113.5 | EP8: 118.6 | EQ8: 122 | ER8: 114 | ES8: 119.1 | ET8: 122.1 | EU8: 114.3 | EV8: 119.2 | EW8: 121.6 | EX8: 114 | EY8: 118.8 | EZ8: 121.3 | FA8: 113.5 | FB8: 118.4 | FC8: 120.8 | FD8: 113.4 | FE8: 118.1 | FF8: 120.9 | FG8: 113.5 | FH8: 118.2 | FI8: 120.9 | FJ8: 113.4 | FK8: 118.1 | FL8: 120.5 | FM8: 114.1 | FN8: 118.1 | FO8: 120.7 | FP8: 114.5 | FQ8: 118.4 | FR8: 121.4 | FS8: 114.9 | FT8: 119 | FU8: 121.6 | FV8: 115.2 | FW8: 119.2 | FX8: 123.1 | FY8: 115.9 | FZ8: 120.5 | GA8: 123.2 | GB8: 116.4 | GC8: 120.7 | GD8: 122.9 | GE8: 116.2 | GF8: 120.4 | GG8: 123.2 | GH8: 116.5 | GI8: 120.7 | GJ8: 123.5 | GK8: 116.6 | GL8: 121 | GM8: 123.6 | GN8: 116.4 | GO8: 121 | GP8: 124 | GQ8: 116.6 | GR8: 121.3 | GS8: 124.1 | GT8: 116.7 | GU8: 121.4 | GV8: 125 | GW8: 117.4 | GX8: 122.2 | GY8: 124.6 | GZ8: 117.8 | HA8: 122.1 | HB8: 123.5 | HC8: 118 | HD8: 121.1 | HE8: 122.8 | HF8: 118.1 | HG8: 121.1 | HH8: 124.2 | HI8: 118.1 | HJ8: 122 | HK8: 123.9 | HL8: 118.1 | HM8: 121.8 | HN8: 124.1 | HO8: 118.4 | HP8: 122 | HQ8: 124.1 | HR8: 118.4 | HS8: 122 | HT8: 124 | HU8: 118.6 | HV8: 122 | HW8: 124.3 | HX8: 118.6 | HY8: 122.2 | HZ8: 124.4 | IA8: 119.3 | IB8: 122.5 | IC8: 124.7 | ID8: 119.9 | IE8: 122.9 | IF8: 125.1 | IG8: 120.8 | IH8: 123.5 | II8: 125.6 | IJ8: 121.1 | IK8: 123.9 | IL8: 126 | IM8: 121.5 | IN8: 124.3 | IO8: 127.5 | IP8: 122.7 | IQ8: 125.7 | IR8: 132 | IS8: 126.3 | IT8: 129.9 | IU8: 133.7 | IV8: 127.4 | IW8: 131.4 | IX8: 133.3 | IY8: 127.5 | IZ8: 131.2 | JA8: 137.1 | JB8: 131.6 | JC8: 135.1 | JD8: NA | JE8: NA | JF8: NA | JG8: 138.2 | JH8: 132.9 | JI8: 136.3 | JJ8: 138.2 | JK8: 132.9 | JL8: 136.3 | JM8: 139.8 | JN8: 133.4 | JO8: 137.4 | JP8: 140.4 | JQ8: 134.4 | JR8: 138.2 | JS8: 142.6 | JT8: 135.7 | JU8: 140.1 | JV8: 145.4 | JW8: 138 | JX8: 142.7 | JY8: 150 | JZ8: 140.7 | KA8: 146.6 | KB8: 154.8 | KC8: 144.1 | KD8: 150.9 | KE8: 163 | KF8: 151.4 | KG8: 158.7 | KH8: 168.2 | KI8: 156.4 | KJ8: 163.9 | KK8: 175.2 | KL8: 161.4 | KM8: 170.1 | KN8: 184.4 | KO8: 168.8 | KP8: 178.7 | KQ8: 190.4 | KR8: 172.2 | KS8: 183.7 | KT8: 188.7 | KU8: 170.6 | KV8: 182.1 | KW8: 190.9 | KX8: 175 | KY8: 188 | KZ8: 195.5 | LA8: 175 | LB8: 188 | LC8: 198.8 | LD8: 176.6 | LE8: 190.6 | LF8: 198.4 | LG8: 175.8 | LH8: 190.1 | LI8: 195.8 | LJ8: 173.5 | LK8: 187.6 | LL8: 192.6 | LM8: 171 | LN8: 184.7 | LO8: 192.6 | LP8: 171.5 | LQ8: 184.9 | LR8: 203.1 | LS8: 180 | LT8: 194.6 | LU8: 207.4 | LV8: 186 | LW8: 199.5 | LX8: 209.9 | LY8: 189.5 | LZ8: 202.4 | MA8: 208.1 | MB8: 188.6 | MC8: 200.9 | MD8: 202.2 | ME8: 184.8 | MF8: 195.8 | MG8: 198.1 | MH8: 182.5 | MI8: 192.4 | MJ8: 194.1 | MK8: 179.3 | ML8: 188.7 | MM8: 191.6 | MN8: 177.7 | MO8: 186.5 | MP8: 194 | MQ8: 180 | MR8: 188.9 | MS8: 193.9 | MT8: 179.1 | MU8: 188.5 | MV8: 192.6 | MW8: 178 | MX8: 187.2 | MY8: 183.4 | MZ8: 172.2 | NA8: 179.3 | NB8: 183.3 | NC8: 172.2 | ND8: 179.2 | NE8: 178.5 | NF8: 168.7 | NG8: 174.9 | NH8: 173.3 | NI8: 164.4 | NJ8: 170
A9: Fruits | B9: =VLOOKUP(A9, NOTES!C10:D35, 2,0) -> Food | C9: 103.9 | D9: 102.3 | E9: 103.2 | F9: 104 | G9: 103.1 | H9: 103.6 | I9: 105.7 | J9: 104.9 | K9: 105.3 | L9: 108.3 | M9: 109.5 | N9: 108.9 | O9: 108.1 | P9: 110.6 | Q9: 109.3 | R9: 109.2 | S9: 112.4 | T9: 110.7 | U9: 110.3 | V9: 113.2 | W9: 111.7 | X9: 110.8 | Y9: 108.7 | Z9: 109.8 | AA9: 110.9 | AB9: 103.2 | AC9: 107.3 | AD9: 113.2 | AE9: 106.2 | AF9: 109.9 | AG9: 116.6 | AH9: 110 | AI9: 113.5 | AJ9: 115.5 | AK9: 110.7 | AL9: 113.3 | AM9: 115.5 | AN9: 112.1 | AO9: 113.9 | AP9: 116.6 | AQ9: 114.1 | AR9: 115.4 | AS9: 119.6 | AT9: 117.7 | AU9: 118.7 | AV9: 125.5 | AW9: 126.7 | AX9: 126.1 | AY9: 126.3 | AZ9: 129.2 | BA9: 127.7 | BB9: 125.8 | BC9: 131.2 | BD9: 128.3 | BE9: 129.1 | BF9: 133.7 | BG9: 131.2 | BH9: 129.7 | BI9: 132.7 | BJ9: 131.1 | BK9: 129.8 | BL9: 124.5 | BM9: 127.3 | BN9: 128.9 | BO9: 123.5 | BP9: 126.4 | BQ9: 128.8 | BR9: 122.2 | BS9: 125.7 | BT9: 128.6 | BU9: 122.3 | BV9: 125.7 | BW9: 130.4 | BX9: 121.3 | BY9: 126.2 | BZ9: 129.4 | CA9: 121.6 | CB9: 125.8 | CC9: 130.9 | CD9: 123.8 | CE9: 127.6 | CF9: 134.2 | CG9: 130.6 | CH9: 132.5 | CI9: 134.1 | CJ9: 130.8 | CK9: 132.6 | CL9: 133.2 | CM9: 132.3 | CN9: 132.8 | CO9: 133.3 | CP9: 132.8 | CQ9: 133.1 | CR9: 134.2 | CS9: 130.1 | CT9: 132.3 | CU9: 132.3 | CV9: 124 | CW9: 128.4 | CX9: 133.2 | CY9: 124.1 | CZ9: 129 | DA9: 132.1 | DB9: 123.7 | DC9: 128.2 | DD9: 131.6 | DE9: 120.8 | DF9: 126.6 | DG9: 131.6 | DH9: 119 | DI9: 125.7 | DJ9: 130.4 | DK9: 118.6 | DL9: 124.9 | DM9: 131.7 | DN9: 119.9 | DO9: 126.2 | DP9: 138.1 | DQ9: 131.1 | DR9: 134.8 | DS9: 138.1 | DT9: 133.5 | DU9: 136 | DV9: 137.4 | DW9: 135.5 | DX9: 136.5 | DY9: 138.5 | DZ9: 137 | EA9: 137.8 | EB9: 140.2 | EC9: 135.8 | ED9: 138.1 | EE9: 139.2 | EF9: 132.5 | EG9: 136.1 | EH9: 138.4 | EI9: 130.4 | EJ9: 134.7 | EK9: 136.9 | EL9: 130.8 | EM9: 134.1 | EN9: 135.6 | EO9: 129.3 | EP9: 132.7 | EQ9: 136 | ER9: 129.6 | ES9: 133 | ET9: 138.7 | EU9: 131.4 | EV9: 135.3 | EW9: 139.7 | EX9: 136.8 | EY9: 138.3 | EZ9: 141.8 | FA9: 137.7 | FB9: 139.9 | FC9: 140.2 | FD9: 135.2 | FE9: 137.9 | FF9: 140.9 | FG9: 137.2 | FH9: 139.2 | FI9: 143.9 | FJ9: 139.4 | FK9: 141.8 | FL9: 148 | FM9: 142.7 | FN9: 145.5 | FO9: 147.8 | FP9: 137.5 | FQ9: 143 | FR9: 146.7 | FS9: 135.6 | FT9: 141.5 | FU9: 147.3 | FV9: 136.4 | FW9: 142.2 | FX9: 147.2 | FY9: 135 | FZ9: 141.5 | GA9: 147.9 | GB9: 133.8 | GC9: 141.3 | GD9: 149.4 | GE9: 135.5 | GF9: 142.9 | GG9: 152.9 | GH9: 138.5 | GI9: 146.2 | GJ9: 156.4 | GK9: 150.1 | GL9: 153.5 | GM9: 157.5 | GN9: 151.3 | GO9: 154.6 | GP9: 154.1 | GQ9: 152.2 | GR9: 153.2 | GS9: 153.3 | GT9: 149.7 | GU9: 151.6 | GV9: 154.4 | GW9: 146.3 | GX9: 150.6 | GY9: 150.1 | GZ9: 140 | HA9: 145.4 | HB9: 144.5 | HC9: 139.5 | HD9: 142.5 | HE9: 143.9 | HF9: 141.5 | HG9: 142.8 | HH9: 140.2 | HI9: 138.5 | HJ9: 139.4 | HK9: 135.5 | HL9: 135.2 | HM9: 135.4 | HN9: 135.8 | HO9: 137 | HP9: 136.4 | HQ9: 136.1 | HR9: 139.4 | HS9: 137.6 | HT9: 143.7 | HU9: 149.7 | HV9: 146.5 | HW9: 143.3 | HX9: 150.9 | HY9: 146.8 | HZ9: 146.4 | IA9: 154.7 | IB9: 150.3 | IC9: 145.5 | ID9: 153.9 | IE9: 149.4 | IF9: 143.8 | IG9: 149.8 | IH9: 146.6 | II9: 145.7 | IJ9: 150.6 | IK9: 148 | IL9: 146.2 | IM9: 148.8 | IN9: 147.4 | IO9: 144.3 | IP9: 147.2 | IQ9: 145.7 | IR9: 142.2 | IS9: 144.4 | IT9: 143.2 | IU9: 140.7 | IV9: 143.1 | IW9: 141.8 | IX9: 141.8 | IY9: 143.3 | IZ9: 142.5 | JA9: 147.3 | JB9: 152.9 | JC9: 149.9 | JD9: NA | JE9: NA | JF9: NA | JG9: 143.2 | JH9: 151.8 | JI9: 147.2 | JJ9: 143.2 | JK9: 151.8 | JL9: 147.2 | JM9: 146.9 | JN9: 154.5 | JO9: 150.4 | JP9: 147 | JQ9: 155.4 | JR9: 150.9 | JS9: 147.2 | JT9: 155.7 | JU9: 151.2 | JV9: 146.5 | JW9: 150.5 | JX9: 148.4 | JY9: 145.9 | JZ9: 149.7 | KA9: 147.7 | KB9: 147 | KC9: 152.6 | KD9: 149.6 | KE9: 147.8 | KF9: 154 | KG9: 150.7 | KH9: 150.5 | KI9: 157.3 | KJ9: 153.7 | KK9: 160.6 | KL9: 168.8 | KM9: 164.4 | KN9: 162.3 | KO9: 172.5 | KP9: 167.1 | KQ9: 158.6 | KR9: 171.5 | KS9: 164.6 | KT9: 157.7 | KU9: 170.9 | KV9: 163.9 | KW9: 155.7 | KX9: 161.3 | KY9: 156.8 | KZ9: 152.7 | LA9: 161.2 | LB9: 156.7 | LC9: 152.6 | LD9: 159.3 | LE9: 155.7 | LF9: 153.2 | LG9: 160.3 | LH9: 156.5 | LI9: 152 | LJ9: 158.3 | LK9: 154.9 | LL9: 151.2 | LM9: 156.5 | LN9: 153.7 | LO9: 151.4 | LP9: 156.4 | LQ9: 153.7 | LR9: 155.9 | LS9: 159.6 | LT9: 157.6 | LU9: 169.7 | LV9: 175.9 | LW9: 172.6 | LX9: 168 | LY9: 174.5 | LZ9: 171 | MA9: 165.8 | MB9: 174.1 | MC9: 169.7 | MD9: 169.6 | ME9: 179.5 | MF9: 174.2 | MG9: 169.2 | MH9: 177.1 | MI9: 172.9 | MJ9: 164.1 | MK9: 167.5 | ML9: 165.7 | MM9: 162.2 | MN9: 165.7 | MO9: 163.8 | MP9: 159.1 | MQ9: 162.6 | MR9: 160.7 | MS9: 156.7 | MT9: 159.5 | MU9: 158 | MV9: 156.3 | MW9: 160.5 | MX9: 158.3 | MY9: 167.2 | MZ9: 172.1 | NA9: 169.5 | NB9: 167.2 | NC9: 172.1 | ND9: 169.5 | NE9: 173.7 | NF9: 179.2 | NG9: 176.3 | NH9: 169 | NI9: 175.8 | NJ9: 172.2
A10: Vegetables | B10: =VLOOKUP(A10, NOTES!C11:D36, 2,0) -> Food | C10: 101.9 | D10: 102.9 | E10: 102.2 | F10: 102.4 | G10: 104.9 | H10: 103.2 | I10: 101.4 | J10: 103.8 | K10: 102.2 | L10: 103.4 | M10: 109.7 | N10: 105.5 | O10: 107.3 | P10: 123.7 | Q10: 112.9 | R10: 118 | S10: 143.6 | T10: 126.7 | U10: 129.2 | V10: 160.9 | W10: 140 | X10: 138.9 | Y10: 177 | Z10: 151.8 | AA10: 154 | AB10: 174.3 | AC10: 160.9 | AD10: 164.9 | AE10: 183.5 | AF10: 171.2 | AG10: 178.1 | AH10: 192.8 | AI10: 183.1 | AJ10: 145.7 | AK10: 144.8 | AL10: 145.4 | AM10: 123.9 | AN10: 118.9 | AO10: 122.2 | AP10: 116 | AQ10: 111.5 | AR10: 114.5 | AS10: 117.9 | AT10: 113.3 | AU10: 116.3 | AV10: 120.5 | AW10: 121.2 | AX10: 120.7 | AY10: 123.9 | AZ10: 127 | BA10: 125 | BB10: 129.3 | BC10: 137.5 | BD10: 132.1 | BE10: 150.1 | BF10: 172.4 | BG10: 157.7 | BH10: 161.1 | BI10: 181.9 | BJ10: 168.2 | BK10: 158.8 | BL10: 168.6 | BM10: 162.1 | BN10: 155.3 | BO10: 159.6 | BP10: 156.8 | BQ10: 152 | BR10: 153.2 | BS10: 152.4 | BT10: 140.3 | BU10: 141 | BV10: 140.5 | BW10: 132.3 | BX10: 134.4 | BY10: 133 | BZ10: 128.2 | CA10: 131.8 | CB10: 129.4 | CC10: 128 | CD10: 131.4 | CE10: 129.2 | CF10: 127.5 | CG10: 130.8 | CH10: 128.6 | CI10: 128.5 | CJ10: 135.6 | CK10: 130.9 | CL10: 135.2 | CM10: 146.7 | CN10: 139.1 | CO10: 140.8 | CP10: 153.5 | CQ10: 145.1 | CR10: 153.6 | CS10: 165.5 | CT10: 157.6 | CU10: 158.9 | CV10: 168.5 | CW10: 162.2 | CX10: 157.7 | CY10: 165.8 | CZ10: 160.4 | DA10: 155.2 | DB10: 164.6 | DC10: 158.4 | DD10: 145.5 | DE10: 149 | DF10: 146.7 | DG10: 140.1 | DH10: 144.1 | DI10: 141.5 | DJ10: 130.9 | DK10: 129.2 | DL10: 130.3 | DM10: 130.7 | DN10: 128.1 | DO10: 129.8 | DP10: 134.1 | DQ10: 136.8 | DR10: 135 | DS10: 141.8 | DT10: 151.4 | DU10: 145.1 | DV10: 152.5 | DW10: 173.7 | DX10: 159.7 | DY10: 158.2 | DZ10: 179.5 | EA10: 165.4 | EB10: 156.9 | EC10: 163.5 | ED10: 159.1 | EE10: 149.5 | EF10: 152.9 | EG10: 150.7 | EH10: 149.2 | EI10: 155.1 | EJ10: 151.2 | EK10: 141.8 | EL10: 142 | EM10: 141.9 | EN10: 127.5 | EO10: 121.1 | EP10: 125.3 | EQ10: 119.8 | ER10: 118.7 | ES10: 119.4 | ET10: 119.1 | EU10: 120.2 | EV10: 119.5 | EW10: 119.7 | EX10: 122.2 | EY10: 120.5 | EZ10: 121.5 | FA10: 127.1 | FB10: 123.4 | FC10: 123.8 | FD10: 129.2 | FE10: 125.6 | FF10: 128.8 | FG10: 142.2 | FH10: 133.3 | FI10: 151.5 | FJ10: 175.1 | FK10: 159.5 | FL10: 162.9 | FM10: 179.8 | FN10: 168.6 | FO10: 154.5 | FP10: 160.7 | FQ10: 156.6 | FR10: 157.1 | FS10: 173.2 | FT10: 162.6 | FU10: 168 | FV10: 185.2 | FW10: 173.8 | FX10: 161 | FY10: 163.2 | FZ10: 161.7 | GA10: 152.1 | GB10: 150.5 | GC10: 151.6 | GD10: 142.4 | GE10: 136.9 | GF10: 140.5 | GG10: 138 | GH10: 128 | GI10: 134.6 | GJ10: 135.1 | GK10: 127.6 | GL10: 132.6 | GM10: 137.8 | GN10: 131.4 | GO10: 135.6 | GP10: 143.5 | GQ10: 144 | GR10: 143.7 | GS10: 154.2 | GT10: 159.2 | GU10: 155.9 | GV10: 156.3 | GW10: 157.3 | GX10: 156.6 | GY10: 149.4 | GZ10: 151.3 | HA10: 150 | HB10: 147.6 | HC10: 153 | HD10: 146.7 | HE10: 147.5 | HF10: 145.2 | HG10: 146.7 | HH10: 136.6 | HI10: 132.4 | HJ10: 135.2 | HK10: 131.7 | HL10: 130.5 | HM10: 131.3 | HN10: 128.7 | HO10: 131.6 | HP10: 129.7 | HQ10: 128.2 | HR10: 141.2 | HS10: 132.6 | HT10: 133.4 | HU10: 161.6 | HV10: 143 | HW10: 140.6 | HX10: 169.8 | HY10: 150.5 | HZ10: 150.1 | IA10: 180.1 | IB10: 160.3 | IC10: 156.2 | ID10: 189.1 | IE10: 167.4 | IF10: 163.4 | IG10: 192.4 | IH10: 173.2 | II10: 178.8 | IJ10: 207.2 | IK10: 188.4 | IL10: 191.4 | IM10: 215.7 | IN10: 199.6 | IO10: 209.5 | IP10: 231.5 | IQ10: 217 | IR10: 191.5 | IS10: 207.8 | IT10: 197 | IU10: 165.1 | IV10: 181.7 | IW10: 170.7 | IX10: 152.3 | IY10: 167 | IZ10: 157.3 | JA10: 162.7 | JB10: 180 | JC10: 168.6 | JD10: NA | JE10: NA | JF10: NA | JG10: 148.9 | JH10: 171.2 | JI10: 156.5 | JJ10: 148.9 | JK10: 171.2 | JL10: 156.5 | JM10: 171 | JN10: 191.9 | JO10: 178.1 | JP10: 178.8 | JQ10: 202 | JR10: 186.7 | JS10: 200.6 | JT10: 226 | JU10: 209.2 | JV10: 222.2 | JW10: 245.3 | JX10: 230 | JY10: 225.2 | JZ10: 240.9 | KA10: 230.5 | KB10: 187.8 | KC10: 206.8 | KD10: 194.2 | KE10: 149.7 | KF10: 180.2 | KG10: 160 | KH10: 141 | KI10: 166.1 | KJ10: 149.5 | KK10: 135.1 | KL10: 161.6 | KM10: 144.1 | KN10: 138.4 | KO10: 166.5 | KP10: 147.9 | KQ10: 144.7 | KR10: 176.2 | KS10: 155.4 | KT10: 152.8 | KU10: 186.4 | KV10: 164.2 | KW10: 153.9 | KX10: 183.3 | KY10: 162.2 | KZ10: 151.4 | LA10: 183.5 | LB10: 162.3 | LC10: 170.4 | LD10: 214.4 | LE10: 185.3 | LF10: 183.9 | LG10: 229.1 | LH10: 199.2 | LI10: 172.3 | LJ10: 219.5 | LK10: 188.3 | LL10: 159.2 | LM10: 203.6 | LN10: 174.3 | LO10: 155.2 | LP10: 198 | LQ10: 169.7 | LR10: 155.8 | LS10: 188.4 | LT10: 166.9 | LU10: 153.6 | LV10: 190.7 | LW10: 166.2 | LX10: 160.4 | LY10: 203.2 | LZ10: 174.9 | MA10: 167.3 | MB10: 211.5 | MC10: 182.3 | MD10: 168.6 | ME10: 208.5 | MF10: 182.1 | MG10: 173.1 | MH10: 213.1 | MI10: 186.7 | MJ10: 176.9 | MK10: 220.8 | ML10: 191.8 | MM10: 184.8 | MN10: 228.6 | MO10: 199.7 | MP10: 171.6 | MQ10: 205.5 | MR10: 183.1 | MS10: 150.2 | MT10: 178.7 | MU10: 159.9 | MV10: 142.9 | MW10: 175.3 | MX10: 153.9 | MY10: 140.9 | MZ10: 175.8 | NA10: 152.7 | NB10: 140.9 | NC10: 175.9 | ND10: 152.8 | NE10: 142.8 | NF10: 179.9 | NG10: 155.4 | NH10: 148.7 | NI10: 185 | NJ10: 161
A11: Pulses and products | B11: =VLOOKUP(A11, NOTES!C12:D37, 2,0) -> Food | C11: 106.1 | D11: 105.8 | E11: 106 | F11: 105.9 | G11: 104.1 | H11: 105.3 | I11: 105.7 | J11: 103.5 | K11: 105 | L11: 105.7 | M11: 104.6 | N11: 105.3 | O11: 106.1 | P11: 105.2 | Q11: 105.8 | R11: 106.8 | S11: 105.4 | T11: 106.3 | U11: 107.1 | V11: 105.1 | W11: 106.4 | X11: 107.4 | Y11: 104.7 | Z11: 106.5 | AA11: 108.1 | AB11: 105.1 | AC11: 107.1 | AD11: 108.3 | AE11: 105.3 | AF11: 107.3 | AG11: 109.1 | AH11: 106.3 | AI11: 108.2 | AJ11: 109.5 | AK11: 107.1 | AL11: 108.7 | AM11: 109.6 | AN11: 107.5 | AO11: 108.9 | AP11: 109.8 | AQ11: 108.2 | AR11: 109.3 | AS11: 110.2 | AT11: 108.9 | AU11: 109.8 | AV11: 111 | AW11: 111 | AX11: 111 | AY11: 111.5 | AZ11: 112.6 | BA11: 111.9 | BB11: 112.2 | BC11: 112.8 | BD11: 112.4 | BE11: 113.2 | BF11: 113.1 | BG11: 113.2 | BH11: 114.1 | BI11: 115.2 | BJ11: 114.5 | BK11: 115 | BL11: 116.9 | BM11: 115.6 | BN11: 115.5 | BO11: 117.4 | BP11: 116.1 | BQ11: 116.2 | BR11: 119.3 | BS11: 117.2 | BT11: 116.3 | BU11: 120.1 | BV11: 117.6 | BW11: 117.2 | BX11: 122.9 | BY11: 119.1 | BZ11: 118.8 | CA11: 125.1 | CB11: 120.9 | CC11: 119.9 | CD11: 127.2 | CE11: 122.4 | CF11: 121.5 | CG11: 131.3 | CH11: 124.8 | CI11: 124.3 | CJ11: 142.6 | CK11: 130.5 | CL11: 131.9 | CM11: 148.1 | CN11: 137.4 | CO11: 133.8 | CP11: 149.5 | CQ11: 139.1 | CR11: 137.9 | CS11: 156 | CT11: 144 | CU11: 142.1 | CV11: 165.4 | CW11: 150 | CX11: 154.2 | CY11: 187.2 | CZ11: 165.3 | DA11: 160.8 | DB11: 191.6 | DC11: 171.2 | DD11: 162.1 | DE11: 190.1 | DF11: 171.5 | DG11: 163.8 | DH11: 184.2 | DI11: 170.7 | DJ11: 162.8 | DK11: 176.4 | DL11: 167.4 | DM11: 161.2 | DN11: 170.3 | DO11: 164.3 | DP11: 162.7 | DQ11: 176.9 | DR11: 167.5 | DS11: 166 | DT11: 182.8 | DU11: 171.7 | DV11: 169.2 | DW11: 184.4 | DX11: 174.3 | DY11: 171.8 | DZ11: 188.4 | EA11: 177.4 | EB11: 172.2 | EC11: 182.3 | ED11: 175.6 | EE11: 170.4 | EF11: 173.6 | EG11: 171.5 | EH11: 170.2 | EI11: 175.7 | EJ11: 172.1 | EK11: 170 | EL11: 174.9 | EM11: 171.7 | EN11: 167.9 | EO11: 170.3 | EP11: 168.7 | EQ11: 161.7 | ER11: 155.1 | ES11: 159.5 | ET11: 156.9 | EU11: 143.1 | EV11: 152.2 | EW11: 148 | EX11: 135.8 | EY11: 143.9 | EZ11: 144.5 | FA11: 133.8 | FB11: 140.9 | FC11: 141.8 | FD11: 131.5 | FE11: 138.3 | FF11: 140.2 | FG11: 128.2 | FH11: 136.2 | FI11: 138.1 | FJ11: 124.7 | FK11: 133.6 | FL11: 137.4 | FM11: 123.5 | FN11: 132.7 | FO11: 137.1 | FP11: 124.5 | FQ11: 132.9 | FR11: 136.4 | FS11: 124.1 | FT11: 132.3 | FU11: 135.8 | FV11: 122.2 | FW11: 131.2 | FX11: 133.8 | FY11: 119.8 | FZ11: 129.1 | GA11: 131.8 | GB11: 118.4 | GC11: 127.3 | GD11: 130.2 | GE11: 117 | GF11: 125.8 | GG11: 129.3 | GH11: 115.5 | GI11: 124.6 | GJ11: 128.4 | GK11: 114 | GL11: 123.5 | GM11: 127.2 | GN11: 112.8 | GO11: 122.3 | GP11: 126 | GQ11: 112.3 | GR11: 121.4 | GS11: 126.4 | GT11: 112.6 | GU11: 121.7 | GV11: 126.8 | GW11: 113.6 | GX11: 122.4 | GY11: 125.4 | GZ11: 113.5 | HA11: 121.4 | HB11: 121.4 | HC11: 113.2 | HD11: 119.1 | HE11: 121 | HF11: 115.3 | HG11: 119.1 | HH11: 120.9 | HI11: 117.5 | HJ11: 119.8 | HK11: 121.3 | HL11: 118.2 | HM11: 120.3 | HN11: 121.5 | HO11: 119.9 | HP11: 121 | HQ11: 122.3 | HR11: 120.7 | HS11: 121.8 | HT11: 125.1 | HU11: 124.4 | HV11: 124.9 | HW11: 128.7 | HX11: 127.4 | HY11: 128.3 | HZ11: 130.6 | IA11: 128.9 | IB11: 130 | IC11: 131.5 | ID11: 129.8 | IE11: 130.9 | IF11: 132.2 | IG11: 130.3 | IH11: 131.6 | II11: 133.1 | IJ11: 131.2 | IK11: 132.5 | IL11: 136.2 | IM11: 134.6 | IN11: 135.7 | IO11: 138.8 | IP11: 137.2 | IQ11: 138.3 | IR11: 141.1 | IS11: 139.1 | IT11: 140.4 | IU11: 141.8 | IV11: 139.6 | IW11: 141.1 | IX11: 141.8 | IY11: 139.7 | IZ11: 141.1 | JA11: 150.2 | JB11: 150.8 | JC11: 150.4 | JD11: NA | JE11: NA | JF11: NA | JG11: 150.3 | JH11: 152 | JI11: 150.9 | JJ11: 150.3 | JK11: 152 | JL11: 150.9 | JM11: 149.9 | JN11: 151.3 | JO11: 150.4 | JP11: 149.3 | JQ11: 150.8 | JR11: 149.8 | JS11: 150.3 | JT11: 152.2 | JU11: 150.9 | JV11: 155.9 | JW11: 158.7 | JX11: 156.8 | JY11: 159.5 | JZ11: 161.5 | KA11: 160.2 | KB11: 159.5 | KC11: 162.1 | KD11: 160.4 | KE11: 158.3 | KF11: 159.8 | KG11: 158.8 | KH11: 159.2 | KI11: 161.1 | KJ11: 159.8 | KK11: 161.1 | KL11: 162.8 | KM11: 161.7 | KN11: 165.1 | KO11: 165.9 | KP11: 165.4 | KQ11: 165.5 | KR11: 166.9 | KS11: 166 | KT11: 163.6 | KU11: 164.7 | KV11: 164 | KW11: 162.8 | KX11: 164.5 | KY11: 164.1 | KZ11: 163.9 | LA11: 164.5 | LB11: 164.1 | LC11: 165.2 | LD11: 165.3 | LE11: 165.2 | LF11: 165.4 | LG11: 165.1 | LH11: 165.3 | LI11: 164.5 | LJ11: 164.2 | LK11: 164.4 | LL11: 164 | LM11: 163.8 | LN11: 163.9 | LO11: 163.9 | LP11: 163.2 | LQ11: 163.7 | LR11: 164.2 | LS11: 163.4 | LT11: 163.9 | LU11: 165.1 | LV11: 164 | LW11: 164.7 | LX11: 165 | LY11: 164.1 | LZ11: 164.7 | MA11: 164.6 | MB11: 163.6 | MC11: 164.3 | MD11: 164.4 | ME11: 164 | MF11: 164.3 | MG11: 167.1 | MH11: 167.3 | MI11: 167.2 | MJ11: 169 | MK11: 169.2 | ML11: 169.1 | MM11: 169.7 | MN11: 169.9 | MO11: 169.8 | MP11: 170.2 | MQ11: 171 | MR11: 170.5 | MS11: 170.5 | MT11: 171.3 | MU11: 170.8 | MV11: 170.7 | MW11: 171.2 | MX11: 170.9 | MY11: 170.4 | MZ11: 172.2 | NA11: 171 | NB11: 170.5 | NC11: 172.2 | ND11: 171.1 | NE11: 172.8 | NF11: 174.7 | NG11: 173.4 | NH11: 174.9 | NI11: 176.9 | NJ11: 175.6
A12: Sugar and Confectionery | B12: =VLOOKUP(A12, NOTES!C13:D38, 2,0) -> Food | C12: 106.8 | D12: 105.1 | E12: 106.2 | F12: 105.7 | G12: 103.8 | H12: 105.1 | I12: 105 | J12: 102.6 | K12: 104.2 | L12: 104.2 | M12: 102 | N12: 103.5 | O12: 103.7 | P12: 101.9 | Q12: 103.1 | R12: 104.1 | S12: 101.4 | T12: 103.2 | U12: 104.3 | V12: 101.3 | W12: 103.3 | X12: 104.1 | Y12: 101 | Z12: 103.1 | AA12: 104.2 | AB12: 100.8 | AC12: 103.1 | AD12: 103.9 | AE12: 100.2 | AF12: 102.7 | AG12: 103.6 | AH12: 99.5 | AI12: 102.2 | AJ12: 102.9 | AK12: 98.6 | AL12: 101.5 | AM12: 101.8 | AN12: 96.9 | AO12: 100.2 | AP12: 101.1 | AQ12: 95.4 | AR12: 99.2 | AS12: 101.2 | AT12: 96.3 | AU12: 99.6 | AV12: 102.6 | AW12: 100.3 | AX12: 101.8 | AY12: 103.5 | AZ12: 101.3 | BA12: 102.8 | BB12: 103.6 | BC12: 101.4 | BD12: 102.9 | BE12: 104.8 | BF12: 102.7 | BG12: 104.1 | BH12: 105.1 | BI12: 102.7 | BJ12: 104.3 | BK12: 104.7 | BL12: 101.9 | BM12: 103.8 | BN12: 104 | BO12: 101.2 | BP12: 103.1 | BQ12: 103.3 | BR12: 99.8 | BS12: 102.1 | BT12: 102 | BU12: 97.8 | BV12: 100.6 | BW12: 100.5 | BX12: 96.1 | BY12: 99 | BZ12: 100 | CA12: 95 | CB12: 98.3 | CC12: 98.9 | CD12: 93.2 | CE12: 97 | CF12: 97.8 | CG12: 91.6 | CH12: 95.7 | CI12: 97.6 | CJ12: 90.8 | CK12: 95.3 | CL12: 96.3 | CM12: 89.8 | CN12: 94.1 | CO12: 94.1 | CP12: 85.7 | CQ12: 91.3 | CR12: 93.1 | CS12: 85.3 | CT12: 90.5 | CU12: 92.5 | CV12: 86.3 | CW12: 90.4 | CX12: 93.7 | CY12: 89.4 | CZ12: 92.3 | DA12: 94.5 | DB12: 90.8 | DC12: 93.3 | DD12: 95.4 | DE12: 92.7 | DF12: 94.5 | DG12: 97.7 | DH12: 96.7 | DI12: 97.4 | DJ12: 98.7 | DK12: 99.1 | DL12: 98.8 | DM12: 100.4 | DN12: 101.8 | DO12: 100.9 | DP12: 105 | DQ12: 109.1 | DR12: 106.4 | DS12: 107.5 | DT12: 111.1 | DU12: 108.7 | DV12: 108.8 | DW12: 112 | DX12: 109.9 | DY12: 110.3 | DZ12: 113.3 | EA12: 111.3 | EB12: 112.1 | EC12: 114.6 | ED12: 112.9 | EE12: 113.1 | EF12: 115.1 | EG12: 113.8 | EH12: 113.4 | EI12: 115.4 | EJ12: 114.1 | EK12: 113.4 | EL12: 115.6 | EM12: 114.1 | EN12: 113.8 | EO12: 115.5 | EP12: 114.4 | EQ12: 114.8 | ER12: 117.3 | ES12: 115.6 | ET12: 116.2 | EU12: 119.5 | EV12: 117.3 | EW12: 116.9 | EX12: 120.3 | EY12: 118 | EZ12: 117.4 | FA12: 120.8 | FB12: 118.5 | FC12: 118.6 | FD12: 121 | FE12: 119.4 | FF12: 118.9 | FG12: 120.9 | FH12: 119.6 | FI12: 120 | FJ12: 121.5 | FK12: 120.5 | FL12: 120.8 | FM12: 122.1 | FN12: 121.2 | FO12: 121 | FP12: 122.4 | FQ12: 121.5 | FR12: 121.4 | FS12: 122.6 | FT12: 121.8 | FU12: 122.5 | FV12: 123.9 | FW12: 123 | FX12: 121.9 | FY12: 120.7 | FZ12: 121.5 | GA12: 119.5 | GB12: 117.3 | GC12: 118.8 | GD12: 117.9 | GE12: 115.4 | GF12: 117.1 | GG12: 117.1 | GH12: 114.2 | GI12: 116.1 | GJ12: 115.2 | GK12: 110.6 | GL12: 113.7 | GM12: 111.8 | GN12: 105.3 | GO12: 109.6 | GP12: 112.4 | GQ12: 108.4 | GR12: 111.1 | GS12: 114.3 | GT12: 111.8 | GU12: 113.5 | GV12: 115.4 | GW12: 113.3 | GX12: 114.7 | GY12: 114.4 | GZ12: 112.3 | HA12: 113.7 | HB12: 112.3 | HC12: 112.8 | HD12: 111.9 | HE12: 111.6 | HF12: 112.5 | HG12: 111.9 | HH12: 109.9 | HI12: 111 | HJ12: 110.3 | HK12: 108.4 | HL12: 110.4 | HM12: 109.1 | HN12: 108.3 | HO12: 110.4 | HP12: 109 | HQ12: 108.3 | HR12: 110.4 | HS12: 109 | HT12: 109.3 | HU12: 111.2 | HV12: 109.9 | HW12: 110.6 | HX12: 111.8 | HY12: 111 | HZ12: 110.8 | IA12: 111.8 | IB12: 111.1 | IC12: 111.7 | ID12: 112.7 | IE12: 112 | IF12: 112.8 | IG12: 114 | IH12: 113.2 | II12: 113.6 | IJ12: 114.8 | IK12: 114 | IL12: 113.8 | IM12: 115 | IN12: 114.2 | IO12: 113.6 | IP12: 114.7 | IQ12: 114 | IR12: 113.8 | IS12: 114.8 | IT12: 114.1 | IU12: 113.1 | IV12: 114.6 | IW12: 113.6 | IX12: 112.6 | IY12: 114.4 | IZ12: 113.2 | JA12: 119.8 | JB12: 121.2 | JC12: 120.3 | JD12: NA | JE12: NA | JF12: NA | JG12: 113.2 | JH12: 116.3 | JI12: 114.2 | JJ12: 113.2 | JK12: 116.3 | JL12: 114.2 | JM12: 114.2 | JN12: 116.8 | JO12: 115.1 | JP12: 115.1 | JQ12: 118.9 | JR12: 116.4 | JS12: 115.3 | JT12: 118.1 | JU12: 116.2 | JV12: 114.9 | JW12: 117.2 | JX12: 115.7 | JY12: 114.4 | JZ12: 117.1 | KA12: 115.3 | KB12: 113.8 | KC12: 116.3 | KD12: 114.6 | KE12: 111.8 | KF12: 114.9 | KG12: 112.8 | KH12: 111.7 | KI12: 114.3 | KJ12: 112.6 | KK12: 112.2 | KL12: 114.8 | KM12: 113.1 | KN12: 114.3 | KO12: 115.9 | KP12: 114.8 | KQ12: 114.6 | KR12: 116.1 | KS12: 115.1 | KT12: 113.9 | KU12: 115.7 | KV12: 114.5 | KW12: 115.2 | KX12: 120.4 | KY12: 119.7 | KZ12: 119.3 | LA12: 120.4 | LB12: 119.7 | LC12: 121.6 | LD12: 122.5 | LE12: 121.9 | LF12: 122.1 | LG12: 123.1 | LH12: 122.4 | LI12: 120.6 | LJ12: 121.9 | LK12: 121 | LL12: 119.3 | LM12: 121.3 | LN12: 120 | LO12: 118.1 | LP12: 120.6 | LQ12: 118.9 | LR12: 118.1 | LS12: 120.3 | LT12: 118.8 | LU12: 118.2 | LV12: 120.5 | LW12: 119 | LX12: 118.9 | LY12: 121.2 | LZ12: 119.7 | MA12: 119.1 | MB12: 121.4 | MC12: 119.9 | MD12: 119.2 | ME12: 121.5 | MF12: 120 | MG12: 120.2 | MH12: 122.2 | MI12: 120.9 | MJ12: 120.8 | MK12: 123.1 | ML12: 121.6 | MM12: 121.1 | MN12: 123.4 | MO12: 121.9 | MP12: 121.5 | MQ12: 123.4 | MR12: 122.1 | MS12: 121.2 | MT12: 123.1 | MU12: 121.8 | MV12: 120.3 | MW12: 122.7 | MX12: 121.1 | MY12: 119.1 | MZ12: 121.9 | NA12: 120 | NB12: 119.1 | NC12: 121.9 | ND12: 120 | NE12: 120.4 | NF12: 123.1 | NG12: 121.3 | NH12: 121.9 | NI12: 124.2 | NJ12: 122.7
A13: Spices | B13: =VLOOKUP(A13, NOTES!C14:D39, 2,0) -> Food | C13: 103.1 | D13: 101.8 | E13: 102.7 | F13: 103.1 | G13: 102.3 | H13: 102.8 | I13: 103.3 | J13: 102.4 | K13: 103 | L13: 103.2 | M13: 103.5 | N13: 103.3 | O13: 104 | P13: 105 | Q13: 104.3 | R13: 105.4 | S13: 106.4 | T13: 105.7 | U13: 106.4 | V13: 107.5 | W13: 106.8 | X13: 106.9 | Y13: 108.5 | Z13: 107.4 | AA13: 107.9 | AB13: 109.1 | AC13: 108.3 | AD13: 108.2 | AE13: 109.6 | AF13: 108.7 | AG13: 109 | AH13: 110.3 | AI13: 109.4 | AJ13: 109.8 | AK13: 111.9 | AL13: 110.5 | AM13: 110.2 | AN13: 112.7 | AO13: 111 | AP13: 110.4 | AQ13: 113.5 | AR13: 111.4 | AS13: 110.7 | AT13: 114.1 | AU13: 111.8 | AV13: 111.2 | AW13: 115.3 | AX13: 112.6 | AY13: 111.6 | AZ13: 117 | BA13: 113.4 | BB13: 112.3 | BC13: 118.3 | BD13: 114.3 | BE13: 113.3 | BF13: 120 | BG13: 115.5 | BH13: 114.6 | BI13: 122.1 | BJ13: 117.1 | BK13: 114.9 | BL13: 122.9 | BM13: 117.6 | BN13: 115.3 | BO13: 123.8 | BP13: 118.1 | BQ13: 115.8 | BR13: 124.6 | BS13: 118.7 | BT13: 116 | BU13: 125.4 | BV13: 119.1 | BW13: 117.2 | BX13: 126.6 | BY13: 120.3 | BZ13: 118.6 | CA13: 127.7 | CB13: 121.6 | CC13: 119.4 | CD13: 127.4 | CE13: 122.1 | CF13: 119.8 | CG13: 127.7 | CH13: 122.4 | CI13: 120.7 | CJ13: 128.8 | CK13: 123.4 | CL13: 123 | CM13: 130.5 | CN13: 125.5 | CO13: 123.4 | CP13: 131.5 | CQ13: 126.1 | CR13: 123.9 | CS13: 132.7 | CT13: 126.8 | CU13: 125.4 | CV13: 134.4 | CW13: 128.4 | CX13: 126.6 | CY13: 135.8 | CZ13: 129.7 | DA13: 128.3 | DB13: 137.1 | DC13: 131.2 | DD13: 128.9 | DE13: 138.6 | DF13: 132.1 | DG13: 129.6 | DH13: 139.5 | DI13: 132.9 | DJ13: 130.6 | DK13: 139.7 | DL13: 133.6 | DM13: 130.8 | DN13: 140.1 | DO13: 133.9 | DP13: 131.4 | DQ13: 140.4 | DR13: 134.4 | DS13: 132.2 | DT13: 141.5 | DU13: 135.3 | DV13: 133.1 | DW13: 142.8 | DX13: 136.3 | DY13: 134.3 | DZ13: 143.9 | EA13: 137.5 | EB13: 134.9 | EC13: 144.6 | ED13: 138.1 | EE13: 135.8 | EF13: 144.8 | EG13: 138.8 | EH13: 136.3 | EI13: 145.3 | EJ13: 139.3 | EK13: 136.8 | EL13: 145.4 | EM13: 139.7 | EN13: 137.5 | EO13: 145.5 | EP13: 140.2 | EQ13: 136.9 | ER13: 144.9 | ES13: 139.6 | ET13: 136 | EU13: 144 | EV13: 138.7 | EW13: 135.6 | EX13: 142.6 | EY13: 137.9 | EZ13: 134.1 | FA13: 141.3 | FB13: 136.5 | FC13: 134 | FD13: 139.9 | FE13: 136 | FF13: 133.5 | FG13: 138.8 | FH13: 135.3 | FI13: 133.9 | FJ13: 137.8 | FK13: 135.2 | FL13: 134.7 | FM13: 137.5 | FN13: 135.6 | FO13: 134.7 | FP13: 137.3 | FQ13: 135.6 | FR13: 135.6 | FS13: 137.8 | FT13: 136.3 | FU13: 136 | FV13: 138.3 | FW13: 136.8 | FX13: 135.8 | FY13: 139.7 | FZ13: 137.1 | GA13: 136 | GB13: 140.5 | GC13: 137.5 | GD13: 135.6 | GE13: 140.7 | GF13: 137.3 | GG13: 136.3 | GH13: 140.7 | GI13: 137.8 | GJ13: 137.2 | GK13: 140.2 | GL13: 138.2 | GM13: 137.4 | GN13: 139.6 | GO13: 138.1 | GP13: 137.6 | GQ13: 140 | GR13: 138.4 | GS13: 138.2 | GT13: 140.3 | GU13: 138.9 | GV13: 138.6 | GW13: 141.1 | GX13: 139.4 | GY13: 138.7 | GZ13: 141.2 | HA13: 139.5 | HB13: 139.5 | HC13: 141.1 | HD13: 141 | HE13: 140.6 | HF13: 141.4 | HG13: 140.9 | HH13: 140.2 | HI13: 141.5 | HJ13: 140.6 | HK13: 138.9 | HL13: 140.4 | HM13: 139.4 | HN13: 139.2 | HO13: 140.8 | HP13: 139.7 | HQ13: 138.9 | HR13: 140.7 | HS13: 139.5 | HT13: 139.3 | HU13: 141 | HV13: 139.9 | HW13: 140.4 | HX13: 141 | HY13: 140.6 | HZ13: 141.7 | IA13: 141.6 | IB13: 141.7 | IC13: 142.7 | ID13: 142.5 | IE13: 142.6 | IF13: 144.2 | IG13: 143.8 | IH13: 144.1 | II13: 145.5 | IJ13: 145.2 | IK13: 145.4 | IL13: 147.3 | IM13: 146.3 | IN13: 147 | IO13: 149.1 | IP13: 148 | IQ13: 148.7 | IR13: 151.6 | IS13: 149.5 | IT13: 150.9 | IU13: 152.8 | IV13: 150.4 | IW13: 152 | IX13: 154 | IY13: 151.5 | IZ13: 153.2 | JA13: 158.7 | JB13: 154 | JC13: 157.1 | JD13: NA | JE13: NA | JF13: NA | JG13: 159.8 | JH13: 158.8 | JI13: 159.5 | JJ13: 159.8 | JK13: 158.8 | JL13: 159.5 | JM13: 160 | JN13: 160 | JO13: 160 | JP13: 160 | JQ13: 160.9 | JR13: 160.3 | JS13: 160.9 | JT13: 161.3 | JU13: 161 | JV13: 162 | JW13: 161.4 | JX13: 161.8 | JY13: 163.5 | JZ13: 161.9 | KA13: 163 | KB13: 164.5 | KC13: 163 | KD13: 164 | KE13: 165 | KF13: 162.5 | KG13: 164.2 | KH13: 164 | KI13: 162.6 | KJ13: 163.5 | KK13: 164.4 | KL13: 162.8 | KM13: 163.9 | KN13: 169.7 | KO13: 165.2 | KP13: 168.2 | KQ13: 170 | KR13: 165.5 | KS13: 168.5 | KT13: 169.7 | KU13: 165.5 | KV13: 168.3 | KW13: 169.8 | KX13: 166.2 | KY13: 168.8 | KZ13: 170.1 | LA13: 166.2 | LB13: 168.8 | LC13: 170.6 | LD13: 166.8 | LE13: 169.3 | LF13: 170.8 | LG13: 167.2 | LH13: 169.6 | LI13: 171.7 | LJ13: 168.2 | LK13: 170.5 | LL13: 173.3 | LM13: 169.8 | LN13: 172.1 | LO13: 175.4 | LP13: 172.2 | LQ13: 174.3 | LR13: 178.7 | LS13: 174.7 | LT13: 177.4 | LU13: 182.9 | LV13: 178 | LW13: 181.3 | LX13: 186.6 | LY13: 181.4 | LZ13: 184.9 | MA13: 188.9 | MB13: 183.5 | MC13: 187.1 | MD13: 191.8 | ME13: 186.3 | MF13: 190 | MG13: 195.6 | MH13: 189.7 | MI13: 193.6 | MJ13: 199.1 | MK13: 193.6 | ML13: 197.3 | MM13: 201.6 | MN13: 196.4 | MO13: 199.9 | MP13: 204.8 | MQ13: 198.8 | MR13: 202.8 | MS13: 207.5 | MT13: 200.5 | MU13: 205.2 | MV13: 210.5 | MW13: 204.3 | MX13: 208.4 | MY13: 212.1 | MZ13: 204.8 | NA13: 209.7 | NB13: 212.1 | NC13: 204.8 | ND13: 209.7 | NE13: 215.5 | NF13: 207.8 | NG13: 212.9 | NH13: 221 | NI13: 211.9 | NJ13: 218
A14: Non-alcoholic beverages | B14: =VLOOKUP(A14, NOTES!C15:D40, 2,0) -> Beverages and Intoxicants | C14: 104.8 | D14: 105.1 | E14: 104.9 | F14: 105.1 | G14: 106 | H14: 105.5 | I14: 105.6 | J14: 107 | K14: 106.2 | L14: 106.5 | M14: 108.2 | N14: 107.2 | O14: 107.4 | P14: 109.1 | Q14: 108.1 | R14: 108.2 | S14: 110 | T14: 109 | U14: 109.1 | V14: 110.4 | W14: 109.6 | X14: 109.7 | Y14: 110.9 | Z14: 110.2 | AA14: 110.4 | AB14: 111.1 | AC14: 110.7 | AD14: 111.1 | AE14: 111.4 | AF14: 111.2 | AG14: 111.8 | AH14: 111.8 | AI14: 111.8 | AJ14: 112.1 | AK14: 112.1 | AL14: 112.1 | AM14: 112.4 | AN14: 112.1 | AO14: 112.3 | AP14: 112.9 | AQ14: 112.1 | AR14: 112.6 | AS14: 113 | AT14: 112.2 | AU14: 112.7 | AV14: 113.5 | AW14: 112.7 | AX14: 113.2 | AY14: 114.2 | AZ14: 112.9 | BA14: 113.7 | BB14: 114.9 | BC14: 113.2 | BD14: 114.2 | BE14: 115.6 | BF14: 113.8 | BG14: 114.8 | BH14: 115.8 | BI14: 114.4 | BJ14: 115.2 | BK14: 116.5 | BL14: 114.8 | BM14: 115.8 | BN14: 116.8 | BO14: 115.2 | BP14: 116.1 | BQ14: 116.8 | BR14: 115.8 | BS14: 116.4 | BT14: 117.3 | BU14: 116.1 | BV14: 116.8 | BW14: 117.9 | BX14: 116.5 | BY14: 117.3 | BZ14: 118.8 | CA14: 116.8 | CB14: 118 | CC14: 118.9 | CD14: 117 | CE14: 118.1 | CF14: 119.4 | CG14: 117.2 | CH14: 118.5 | CI14: 120.2 | CJ14: 117.7 | CK14: 119.2 | CL14: 121.1 | CM14: 118 | CN14: 119.8 | CO14: 121 | CP14: 118.3 | CQ14: 119.9 | CR14: 121.5 | CS14: 118.8 | CT14: 120.4 | CU14: 121.9 | CV14: 119.1 | CW14: 120.7 | CX14: 122.3 | CY14: 119.4 | CZ14: 121.1 | DA14: 123.1 | DB14: 119.8 | DC14: 121.7 | DD14: 123.3 | DE14: 120.2 | DF14: 122 | DG14: 124.3 | DH14: 120.5 | DI14: 122.7 | DJ14: 124.8 | DK14: 120.6 | DL14: 123 | DM14: 124.9 | DN14: 120.7 | DO14: 123.1 | DP14: 125.4 | DQ14: 121.1 | DR14: 123.6 | DS14: 126.1 | DT14: 121.5 | DU14: 124.2 | DV14: 126.4 | DW14: 121.6 | DX14: 124.4 | DY14: 127.3 | DZ14: 121.7 | EA14: 125 | EB14: 128.1 | EC14: 121.9 | ED14: 125.5 | EE14: 128.8 | EF14: 122.1 | EG14: 126 | EH14: 128.7 | EI14: 122.5 | EJ14: 126.1 | EK14: 128.7 | EL14: 122.7 | EM14: 126.2 | EN14: 129.1 | EO14: 123.1 | EP14: 126.6 | EQ14: 129 | ER14: 123.2 | ES14: 126.6 | ET14: 129.4 | EU14: 123.4 | EV14: 126.9 | EW14: 129.8 | EX14: 123.6 | EY14: 127.2 | EZ14: 130 | FA14: 123.8 | FB14: 127.4 | FC14: 130.3 | FD14: 123.8 | FE14: 127.6 | FF14: 130.4 | FG14: 124.2 | FH14: 127.8 | FI14: 131.4 | FJ14: 124.4 | FK14: 128.5 | FL14: 131.6 | FM14: 124.6 | FN14: 128.7 | FO14: 131.7 | FP14: 124.8 | FQ14: 128.8 | FR14: 131.3 | FS14: 125.1 | FT14: 128.7 | FU14: 131.9 | FV14: 125.4 | FW14: 129.2 | FX14: 131.1 | FY14: 125.7 | FZ14: 128.8 | GA14: 131.2 | GB14: 125.9 | GC14: 129 | GD14: 130.5 | GE14: 125.9 | GF14: 128.6 | GG14: 131.2 | GH14: 126.2 | GI14: 129.1 | GJ14: 131.9 | GK14: 126.5 | GL14: 129.6 | GM14: 132.2 | GN14: 126.6 | GO14: 129.9 | GP14: 132.8 | GQ14: 126.7 | GR14: 130.3 | GS14: 132.8 | GT14: 126.8 | GU14: 130.3 | GV14: 133.8 | GW14: 127.4 | GX14: 131.1 | GY14: 133.1 | GZ14: 127.7 | HA14: 130.8 | HB14: 134.6 | HC14: 127.6 | HD14: 133.6 | HE14: 137.5 | HF14: 128 | HG14: 133.5 | HH14: 137.8 | HI14: 128.1 | HJ14: 133.8 | HK14: 137 | HL14: 128.1 | HM14: 133.3 | HN14: 137.4 | HO14: 128.3 | HP14: 133.6 | HQ14: 137.4 | HR14: 128.5 | HS14: 133.7 | HT14: 137.7 | HU14: 128.9 | HV14: 134 | HW14: 138 | HX14: 129 | HY14: 134.2 | HZ14: 138.5 | IA14: 129.5 | IB14: 134.7 | IC14: 138.5 | ID14: 129.8 | IE14: 134.9 | IF14: 138.5 | IG14: 130 | IH14: 135 | II14: 138.6 | IJ14: 130.2 | IK14: 135.1 | IL14: 138.7 | IM14: 130.5 | IN14: 135.3 | IO14: 139.3 | IP14: 130.8 | IQ14: 135.8 | IR14: 139.7 | IS14: 131.1 | IT14: 136.1 | IU14: 140.1 | IV14: 131.5 | IW14: 136.5 | IX14: 140.1 | IY14: 131.9 | IZ14: 136.7 | JA14: 139.2 | JB14: 133.5 | JC14: 136.8 | JD14: NA | JE14: NA | JF14: NA | JG14: 142.1 | JH14: 135.6 | JI14: 139.4 | JJ14: 142.1 | JK14: 135.6 | JL14: 139.4 | JM14: 143.5 | JN14: 136.5 | JO14: 140.6 | JP14: 145.4 | JQ14: 137.7 | JR14: 142.2 | JS14: 147.4 | JT14: 139.2 | JU14: 144 | JV14: 150 | JW14: 141.5 | JX14: 146.5 | JY14: 153.4 | JZ14: 143.3 | KA14: 149.2 | KB14: 156.1 | KC14: 145.9 | KD14: 151.8 | KE14: 160 | KF14: 149.2 | KG14: 155.5 | KH14: 160.6 | KI14: 150.7 | KJ14: 156.5 | KK14: 161.9 | KL14: 151.5 | KM14: 157.6 | KN14: 164.6 | KO14: 152 | KP14: 159.3 | KQ14: 165.5 | KR14: 152.3 | KS14: 160 | KT14: 166.2 | KU14: 153.4 | KV14: 160.9 | KW14: 167.6 | KX14: 154.8 | KY14: 162.7 | KZ14: 168.3 | LA14: 154.8 | LB14: 162.7 | LC14: 168.8 | LD14: 155.4 | LE14: 163.2 | LF14: 169.1 | LG14: 156.1 | LH14: 163.7 | LI14: 169.7 | LJ14: 156.5 | LK14: 164.2 | LL14: 169.8 | LM14: 156.6 | LN14: 164.3 | LO14: 170.5 | LP14: 156.7 | LQ14: 164.7 | LR14: 171.2 | LS14: 157.1 | LT14: 165.3 | LU14: 172.4 | LV14: 157.5 | LW14: 166.2 | LX14: 173.2 | LY14: 158.5 | LZ14: 167.1 | MA14: 174.2 | MB14: 159.1 | MC14: 167.9 | MD14: 174.5 | ME14: 159.8 | MF14: 168.4 | MG14: 174.8 | MH14: 160.5 | MI14: 168.8 | MJ14: 175.4 | MK14: 161.1 | ML14: 169.4 | MM14: 175.8 | MN14: 161.6 | MO14: 169.9 | MP14: 176.4 | MQ14: 162.1 | MR14: 170.4 | MS14: 176.8 | MT14: 162.8 | MU14: 171 | MV14: 176.9 | MW14: 163.7 | MX14: 171.4 | MY14: 177.6 | MZ14: 164.9 | NA14: 172.3 | NB14: 177.6 | NC14: 164.9 | ND14: 172.3 | NE14: 178.2 | NF14: 165.5 | NG14: 172.9 | NH14: 178.7 | NI14: 165.9 | NJ14: 173.4
A15: Prepared meals, snacks, sweets etc. | B15: =VLOOKUP(A15, NOTES!C16:D41, 2,0) -> Beverages and Intoxicants | C15: 106.7 | D15: 107.9 | E15: 107.3 | F15: 107.7 | G15: 109 | H15: 108.3 | I15: 108.2 | J15: 109.8 | K15: 108.9 | L15: 108.8 | M15: 110.6 | N15: 109.6 | O15: 109.9 | P15: 111.3 | Q15: 110.5 | R15: 111 | S15: 112.2 | T15: 111.6 | U15: 112.1 | V15: 113.1 | W15: 112.6 | X15: 112.6 | Y15: 114.3 | Z15: 113.4 | AA15: 114 | AB15: 115.4 | AC15: 114.6 | AD15: 114.9 | AE15: 116 | AF15: 115.4 | AG15: 116 | AH15: 117.1 | AI15: 116.5 | AJ15: 116.8 | AK15: 118.1 | AL15: 117.4 | AM15: 117.3 | AN15: 119 | AO15: 118.1 | AP15: 117.8 | AQ15: 119.9 | AR15: 118.8 | AS15: 118.3 | AT15: 120.5 | AU15: 119.3 | AV15: 118.7 | AW15: 121 | AX15: 119.8 | AY15: 119.2 | AZ15: 121.7 | BA15: 120.4 | BB15: 120.1 | BC15: 122.4 | BD15: 121.2 | BE15: 120.9 | BF15: 123.4 | BG15: 122.1 | BH15: 121.7 | BI15: 124.7 | BJ15: 123.1 | BK15: 122.6 | BL15: 125.2 | BM15: 123.8 | BN15: 123.2 | BO15: 125.9 | BP15: 124.5 | BQ15: 124.5 | BR15: 126.9 | BS15: 125.6 | BT15: 124.8 | BU15: 127.6 | BV15: 126.1 | BW15: 125.6 | BX15: 128 | BY15: 126.7 | BZ15: 126.8 | CA15: 128.6 | CB15: 127.6 | CC15: 127.7 | CD15: 129.2 | CE15: 128.4 | CF15: 128.7 | CG15: 129.5 | CH15: 129.1 | CI15: 129.8 | CJ15: 129.9 | CK15: 129.8 | CL15: 131.2 | CM15: 130.5 | CN15: 130.9 | CO15: 131.7 | CP15: 131.1 | CQ15: 131.4 | CR15: 132.5 | CS15: 131.7 | CT15: 132.1 | CU15: 132.7 | CV15: 132.3 | CW15: 132.5 | CX15: 133.1 | CY15: 132.9 | CZ15: 133 | DA15: 134.2 | DB15: 133.7 | DC15: 134 | DD15: 135.1 | DE15: 134.2 | DF15: 134.7 | DG15: 135.9 | DH15: 134.7 | DI15: 135.3 | DJ15: 136.4 | DK15: 135.2 | DL15: 135.8 | DM15: 137 | DN15: 135.4 | DO15: 136.3 | DP15: 137.4 | DQ15: 135.9 | DR15: 136.7 | DS15: 138.3 | DT15: 136.3 | DU15: 137.4 | DV15: 139.2 | DW15: 136.9 | DX15: 138.1 | DY15: 139.9 | DZ15: 137.5 | EA15: 138.8 | EB15: 140.7 | EC15: 138.1 | ED15: 139.5 | EE15: 141.5 | EF15: 138.8 | EG15: 140.2 | EH15: 142.4 | EI15: 139.6 | EJ15: 141.1 | EK15: 143.1 | EL15: 140.3 | EM15: 141.8 | EN15: 143.6 | EO15: 140.9 | EP15: 142.3 | EQ15: 143.9 | ER15: 141.6 | ES15: 142.8 | ET15: 144.4 | EU15: 141.9 | EV15: 143.2 | EW15: 145.4 | EX15: 142.4 | EY15: 144 | EZ15: 145.5 | FA15: 142.6 | FB15: 144.2 | FC15: 145.8 | FD15: 142.9 | FE15: 144.5 | FF15: 146.5 | FG15: 143.1 | FH15: 144.9 | FI15: 147.7 | FJ15: 143.7 | FK15: 145.8 | FL15: 148.7 | FM15: 144.5 | FN15: 146.8 | FO15: 149.3 | FP15: 145 | FQ15: 147.3 | FR15: 150.3 | FS15: 145.5 | FT15: 148.1 | FU15: 151.4 | FV15: 146 | FW15: 148.9 | FX15: 151.4 | FY15: 146.3 | FZ15: 149 | GA15: 151.8 | GB15: 146.8 | GC15: 149.5 | GD15: 151.7 | GE15: 147.1 | GF15: 149.6 | GG15: 152.8 | GH15: 147.6 | GI15: 150.4 | GJ15: 153.8 | GK15: 148.3 | GL15: 151.2 | GM15: 154.3 | GN15: 148.7 | GO15: 151.7 | GP15: 154.3 | GQ15: 149 | GR15: 151.8 | GS15: 154.8 | GT15: 149.4 | GU15: 152.3 | GV15: 155.2 | GW15: 150.4 | GX15: 153 | GY15: 155.9 | GZ15: 151.3 | HA15: 153.8 | HB15: 155.2 | HC15: 152 | HD15: 154.5 | HE15: 156.1 | HF15: 152.6 | HG15: 154.5 | HH15: 156 | HI15: 152.9 | HJ15: 154.6 | HK15: 155.8 | HL15: 153.2 | HM15: 154.6 | HN15: 156.2 | HO15: 153.5 | HP15: 154.9 | HQ15: 156.4 | HR15: 153.9 | HS15: 155.2 | HT15: 156.4 | HU15: 154.5 | HV15: 155.5 | HW15: 156.6 | HX15: 155.1 | HY15: 155.9 | HZ15: 156.7 | IA15: 155.6 | IB15: 156.2 | IC15: 156.9 | ID15: 156.2 | IE15: 156.6 | IF15: 157.2 | IG15: 156.4 | IH15: 156.8 | II15: 157.4 | IJ15: 156.8 | IK15: 157.1 | IL15: 157.7 | IM15: 157.2 | IN15: 157.5 | IO15: 158.3 | IP15: 157.7 | IQ15: 158 | IR15: 158.7 | IS15: 158.5 | IT15: 158.6 | IU15: 159.2 | IV15: 159 | IW15: 159.1 | IX15: 160 | IY15: 159.1 | IZ15: 159.6 | JA15: NA | JB15: NA | JC15: NA | JD15: NA | JE15: NA | JF15: NA | JG15: 161.8 | JH15: 161.7 | JI15: 161.8 | JJ15: 161.8 | JK15: 161.7 | JL15: 161.8 | JM15: 161.5 | JN15: 163.3 | JO15: 162.3 | JP15: 161.6 | JQ15: 164.4 | JR15: 162.9 | JS15: 161.9 | JT15: 164.8 | JU15: 163.2 | JV15: 162.7 | JW15: 165.1 | JX15: 163.8 | JY15: 163.6 | JZ15: 166.1 | KA15: 164.8 | KB15: 164.3 | KC15: 167.2 | KD15: 165.6 | KE15: 165.8 | KF15: 169.4 | KG15: 167.5 | KH15: 166.4 | KI15: 170.3 | KJ15: 168.2 | KK15: 166.8 | KL15: 171.4 | KM15: 168.9 | KN15: 169.8 | KO15: 171.1 | KP15: 170.4 | KQ15: 171.7 | KR15: 173.3 | KS15: 172.4 | KT15: 171 | KU15: 173.5 | KV15: 172.2 | KW15: 171.9 | KX15: 175.1 | KY15: 173.9 | KZ15: 172.8 | LA15: 175.1 | LB15: 173.9 | LC15: 173.6 | LD15: 175.9 | LE15: 174.7 | LF15: 174.3 | LG15: 176.8 | LH15: 175.5 | LI15: 175.1 | LJ15: 178.2 | LK15: 176.5 | LL15: 175.8 | LM15: 179 | LN15: 177.3 | LO15: 176.3 | LP15: 180 | LQ15: 178 | LR15: 177.4 | LS15: 181.5 | LT15: 179.3 | LU15: 178.9 | LV15: 183.3 | LW15: 180.9 | LX15: 180.4 | LY15: 184.9 | LZ15: 182.5 | MA15: 181.9 | MB15: 186.3 | MC15: 183.9 | MD15: 183.1 | ME15: 187.7 | MF15: 185.2 | MG15: 184 | MH15: 188.9 | MI15: 186.3 | MJ15: 184.8 | MK15: 190.4 | ML15: 187.4 | MM15: 185.6 | MN15: 191.5 | MO15: 188.3 | MP15: 186.9 | MQ15: 192.4 | MR15: 189.5 | MS15: 187.7 | MT15: 193.3 | MU15: 190.3 | MV15: 188.5 | MW15: 194.3 | MX15: 191.2 | MY15: 189.9 | MZ15: 196.6 | NA15: 193 | NB15: 189.9 | NC15: 196.6 | ND15: 193 | NE15: 190.5 | NF15: 197 | NG15: 193.5 | NH15: 191.1 | NI15: 197.7 | NJ15: 194.2
A16: Food and beverages | B16: =VLOOKUP(A16, NOTES!C17:D42, 2,0) -> Beverages and Intoxicants | C16: 105.5 | D16: 105.9 | E16: 105.6 | F16: 106.3 | G16: 107.2 | H16: 106.6 | I16: 106.6 | J16: 107.3 | K16: 106.9 | L16: 107.1 | M16: 108.8 | N16: 107.7 | O16: 108.1 | P16: 111.1 | Q16: 109.2 | R16: 110.6 | S16: 115 | T16: 112.2 | U16: 113.1 | V16: 117.5 | W16: 114.7 | X16: 114.9 | Y16: 119.6 | Z16: 116.6 | AA16: 117.8 | AB16: 119.2 | AC16: 118.3 | AD16: 119.8 | AE16: 120.8 | AF16: 120.2 | AG16: 122.5 | AH16: 122.9 | AI16: 122.6 | AJ16: 118.7 | AK16: 117.8 | AL16: 118.4 | AM16: 116 | AN16: 115.5 | AO16: 115.8 | AP16: 115.3 | AQ16: 115.2 | AR16: 115.3 | AS16: 116.2 | AT16: 116 | AU16: 116.1 | AV16: 117.2 | AW16: 118.2 | AX16: 117.6 | AY16: 118.2 | AZ16: 120 | BA16: 118.9 | BB16: 119.5 | BC16: 122 | BD16: 120.4 | BE16: 123.3 | BF16: 127.1 | BG16: 124.7 | BH16: 125.3 | BI16: 128.9 | BJ16: 126.6 | BK16: 125.3 | BL16: 126.7 | BM16: 125.8 | BN16: 125.1 | BO16: 125.8 | BP16: 125.4 | BQ16: 124.9 | BR16: 125.4 | BS16: 125.1 | BT16: 123.3 | BU16: 124 | BV16: 123.6 | BW16: 122.8 | BX16: 123.5 | BY16: 123.1 | BZ16: 122.8 | CA16: 123.7 | CB16: 123.1 | CC16: 123.1 | CD16: 123.9 | CE16: 123.4 | CF16: 123.6 | CG16: 124.6 | CH16: 124 | CI16: 124.4 | CJ16: 126.1 | CK16: 125 | CL16: 126.6 | CM16: 128.5 | CN16: 127.3 | CO16: 127.5 | CP16: 129.5 | CQ16: 128.2 | CR16: 129.8 | CS16: 131.1 | CT16: 130.3 | CU16: 131 | CV16: 131.5 | CW16: 131.2 | CX16: 131.8 | CY16: 132.6 | CZ16: 132.1 | DA16: 132.4 | DB16: 133.3 | DC16: 132.7 | DD16: 131.4 | DE16: 131.5 | DF16: 131.4 | DG16: 131.4 | DH16: 131.2 | DI16: 131.3 | DJ16: 130.3 | DK16: 129.1 | DL16: 129.9 | DM16: 130.4 | DN16: 128.9 | DO16: 129.8 | DP16: 131.8 | DQ16: 131.8 | DR16: 131.8 | DS16: 133.6 | DT16: 134.6 | DU16: 134 | DV16: 136 | DW16: 138.2 | DX16: 136.8 | DY16: 137.6 | DZ16: 139.8 | EA16: 138.4 | EB16: 138 | EC16: 137.6 | ED16: 137.9 | EE16: 137.2 | EF16: 135.7 | EG16: 136.6 | EH16: 137.4 | EI16: 136.3 | EJ16: 137 | EK16: 136.6 | EL16: 135.2 | EM16: 136.1 | EN16: 134.7 | EO16: 132.8 | EP16: 134 | EQ16: 133.7 | ER16: 132 | ES16: 133.1 | ET16: 133.6 | EU16: 132.1 | EV16: 133 | EW16: 133.4 | EX16: 132.6 | EY16: 133.1 | EZ16: 133.5 | FA16: 133.4 | FB16: 133.5 | FC16: 133.8 | FD16: 133.6 | FE16: 133.7 | FF16: 134.9 | FG16: 135.7 | FH16: 135.2 | FI16: 138.5 | FJ16: 139.8 | FK16: 139 | FL16: 140.6 | FM16: 140.5 | FN16: 140.6 | FO16: 139.6 | FP16: 138 | FQ16: 139 | FR16: 140.4 | FS16: 139.7 | FT16: 140.1 | FU16: 142.4 | FV16: 141.5 | FW16: 142.1 | FX16: 141.5 | FY16: 138.8 | FZ16: 140.5 | GA16: 140.4 | GB16: 137.2 | GC16: 139.2 | GD16: 138.7 | GE16: 135.6 | GF16: 137.6 | GG16: 138.6 | GH16: 134.8 | GI16: 137.2 | GJ16: 138.6 | GK16: 135.7 | GL16: 137.5 | GM16: 139.1 | GN16: 136.4 | GO16: 138.1 | GP16: 140 | GQ16: 138.4 | GR16: 139.4 | GS16: 142 | GT16: 140.3 | GU16: 141.4 | GV16: 142.7 | GW16: 140.1 | GX16: 141.7 | GY16: 141.3 | GZ16: 138.9 | HA16: 140.4 | HB16: 140.2 | HC16: 139.4 | HD16: 139.7 | HE16: 140 | HF16: 139.1 | HG16: 139.7 | HH16: 138.5 | HI16: 137.6 | HJ16: 138.2 | HK16: 137.4 | HL16: 137.3 | HM16: 137.4 | HN16: 137.2 | HO16: 138 | HP16: 137.5 | HQ16: 137.3 | HR16: 139.6 | HS16: 138.1 | HT16: 139.2 | HU16: 143.8 | HV16: 140.9 | HW16: 141 | HX16: 145.6 | HY16: 142.7 | HZ16: 143 | IA16: 147.7 | IB16: 144.7 | IC16: 144 | ID16: 149.1 | IE16: 145.9 | IF16: 145.5 | IG16: 149.5 | IH16: 147 | II16: 148.3 | IJ16: 151.9 | IK16: 149.6 | IL16: 150.9 | IM16: 153.6 | IN16: 151.9 | IO16: 154.3 | IP16: 156.3 | IQ16: 155 | IR16: 153 | IS16: 154.4 | IT16: 153.5 | IU16: 149.8 | IV16: 151.7 | IW16: 150.5 | IX16: 148.2 | IY16: 150.1 | IZ16: 148.9 | JA16: 150.1 | JB16: 153.5 | JC16: 151.4 | JD16: NA | JE16: NA | JF16: NA | JG16: 152.3 | JH16: 157 | JI16: 154 | JJ16: 152.3 | JK16: 157 | JL16: 154 | JM16: 155.3 | JN16: 159.9 | JO16: 157 | JP16: 156.1 | JQ16: 161.3 | JR16: 158 | JS16: 159.6 | JT16: 164.4 | JU16: 161.4 | JV16: 163.4 | JW16: 167 | JX16: 164.7 | JY16: 164.5 | JZ16: 167 | KA16: 165.4 | KB16: 159.6 | KC16: 163.4 | KD16: 161 | KE16: 154.7 | KF16: 160.8 | KG16: 156.9 | KH16: 154.5 | KI16: 160.4 | KJ16: 156.7 | KK16: 155.6 | KL16: 162 | KM16: 158 | KN16: 158.7 | KO16: 164.2 | KP16: 160.7 | KQ16: 160.5 | KR16: 166.2 | KS16: 162.6 | KT16: 161.7 | KU16: 167.9 | KV16: 164 | KW16: 161.8 | KX16: 167.3 | KY16: 164 | KZ16: 162.1 | LA16: 167.3 | LB16: 164 | LC16: 165.5 | LD16: 171.5 | LE16: 167.7 | LF16: 167.5 | LG16: 173.5 | LH16: 169.7 | LI16: 165.8 | LJ16: 172.2 | LK16: 168.2 | LL16: 164.1 | LM16: 170.3 | LN16: 166.4 | LO16: 163.9 | LP16: 170.2 | LQ16: 166.2 | LR16: 166.6 | LS16: 171.5 | LT16: 168.4 | LU16: 168.6 | LV16: 174.5 | LW16: 170.8 | LX16: 170.8 | LY16: 177.5 | LZ16: 173.3 | MA16: 172.4 | MB16: 179.3 | MC16: 174.9 | MD16: 172.5 | ME16: 179.4 | MF16: 175 | MG16: 173.9 | MH16: 180.4 | MI16: 176.3 | MJ16: 175.5 | MK16: 181.8 | ML16: 177.8 | MM16: 177.4 | MN16: 183.3 | MO16: 179.6 | MP16: 176.6 | MQ16: 181.3 | MR16: 178.3 | MS16: 174.4 | MT16: 178.6 | MU16: 175.9 | MV16: 175 | MW16: 179.5 | MX16: 176.7 | MY16: 174.8 | MZ16: 180.7 | NA16: 177 | NB16: 174.8 | NC16: 180.8 | ND16: 177 | NE16: 175.5 | NF16: 182.1 | NG16: 177.9 | NH16: 176.8 | NI16: 183.1 | NJ16: 179.1
A17: Pan, tobacco and intoxicants | B17: Beverages and Intoxicants | C17: 105.1 | D17: 105.2 | E17: 105.1 | F17: 105.6 | G17: 106 | H17: 105.7 | I17: 106.5 | J17: 106.8 | K17: 106.6 | L17: 107.1 | M17: 108.5 | N17: 107.5 | O17: 108.1 | P17: 109.8 | Q17: 108.6 | R17: 109 | S17: 110.9 | T17: 109.5 | U17: 109.8 | V17: 111.7 | W17: 110.3 | X17: 110.7 | Y17: 112.4 | Z17: 111.2 | AA17: 111.7 | AB17: 112.9 | AC17: 112 | AD17: 112.2 | AE17: 113.5 | AF17: 112.5 | AG17: 112.8 | AH17: 114.1 | AI17: 113.1 | AJ17: 113.6 | AK17: 115 | AL17: 114 | AM17: 114 | AN17: 115.7 | AO17: 114.5 | AP17: 114.2 | AQ17: 116.2 | AR17: 114.7 | AS17: 114.6 | AT17: 116.7 | AU17: 115.2 | AV17: 115.4 | AW17: 117.6 | AX17: 116 | AY17: 116.3 | AZ17: 118.3 | BA17: 116.8 | BB17: 117.3 | BC17: 119 | BD17: 117.8 | BE17: 118 | BF17: 121 | BG17: 118.8 | BH17: 118.8 | BI17: 123 | BJ17: 119.9 | BK17: 119.5 | BL17: 124.3 | BM17: 120.8 | BN17: 120 | BO17: 124.3 | BP17: 121.1 | BQ17: 120.8 | BR17: 125.8 | BS17: 122.1 | BT17: 121.7 | BU17: 126.4 | BV17: 123 | BW17: 122.7 | BX17: 127.4 | BY17: 124 | BZ17: 124.2 | CA17: 128.1 | CB17: 125.2 | CC17: 124.7 | CD17: 128.8 | CE17: 125.8 | CF17: 125.7 | CG17: 130.1 | CH17: 126.9 | CI17: 126.7 | CJ17: 131.3 | CK17: 127.9 | CL17: 128.2 | CM17: 132.1 | CN17: 129.2 | CO17: 129.4 | CP17: 133.1 | CQ17: 130.4 | CR17: 130.1 | CS17: 134.2 | CT17: 131.2 | CU17: 131 | CV17: 134.7 | CW17: 132 | CX17: 131.5 | CY17: 135.3 | CZ17: 132.5 | DA17: 132.2 | DB17: 137.6 | DC17: 133.6 | DD17: 133.1 | DE17: 138.2 | DF17: 134.5 | DG17: 133.6 | DH17: 139.5 | DI17: 135.2 | DJ17: 134.4 | DK17: 140 | DL17: 135.9 | DM17: 135 | DN17: 140.6 | DO17: 136.5 | DP17: 135.5 | DQ17: 141.5 | DR17: 137.1 | DS17: 136 | DT17: 142.2 | DU17: 137.7 | DV17: 137.2 | DW17: 142.7 | DX17: 138.7 | DY17: 138 | DZ17: 142.9 | EA17: 139.3 | EB17: 138.9 | EC17: 143.6 | ED17: 140.2 | EE17: 139.9 | EF17: 143.9 | EG17: 141 | EH17: 140.9 | EI17: 144.3 | EJ17: 141.8 | EK17: 141.2 | EL17: 144.3 | EM17: 142 | EN17: 142.4 | EO17: 145 | EP17: 143.1 | EQ17: 143.1 | ER17: 145.6 | ES17: 143.8 | ET17: 143.7 | EU17: 146.3 | EV17: 144.4 | EW17: 144.2 | EX17: 147.5 | EY17: 145.1 | EZ17: 144.4 | FA17: 148 | FB17: 145.4 | FC17: 145.5 | FD17: 148.3 | FE17: 146.2 | FF17: 145.8 | FG17: 148.6 | FH17: 146.5 | FI17: 147.4 | FJ17: 150.5 | FK17: 148.2 | FL17: 149 | FM17: 152.1 | FN17: 149.8 | FO17: 149.8 | FP17: 153.6 | FQ17: 150.8 | FR17: 150.5 | FS17: 154.6 | FT17: 151.6 | FU17: 152.1 | FV17: 156.2 | FW17: 153.2 | FX17: 153.2 | FY17: 157 | FZ17: 154.2 | GA17: 153.6 | GB17: 157.7 | GC17: 154.7 | GD17: 153.3 | GE17: 159.3 | GF17: 154.9 | GG17: 155.1 | GH17: 159.7 | GI17: 156.3 | GJ17: 156.1 | GK17: 159.2 | GL17: 156.9 | GM17: 157 | GN17: 160.3 | GO17: 157.9 | GP17: 157.3 | GQ17: 161 | GR17: 158.3 | GS17: 156.1 | GT17: 161.4 | GU17: 157.5 | GV17: 156.4 | GW17: 162.1 | GX17: 157.9 | GY17: 157.7 | GZ17: 163.3 | HA17: 159.2 | HB17: 159.6 | HC17: 164 | HD17: 162.6 | HE17: 161.9 | HF17: 164.4 | HG17: 162.6 | HH17: 162.4 | HI17: 164.6 | HJ17: 163 | HK17: 162.7 | HL17: 164.7 | HM17: 163.2 | HN17: 162.8 | HO17: 164.9 | HP17: 163.4 | HQ17: 162.9 | HR17: 165.3 | HS17: 163.5 | HT17: 163.3 | HU17: 166.2 | HV17: 164.1 | HW17: 164.2 | HX17: 166.7 | HY17: 164.9 | HZ17: 164.5 | IA17: 167.2 | IB17: 165.2 | IC17: 165.1 | ID17: 167.9 | IE17: 165.8 | IF17: 165.7 | IG17: 168.6 | IH17: 166.5 | II17: 166.3 | IJ17: 169.3 | IK17: 167.1 | IL17: 167.2 | IM17: 169.9 | IN17: 167.9 | IO17: 167.8 | IP17: 170.4 | IQ17: 168.5 | IR17: 168.6 | IS17: 170.8 | IT17: 169.2 | IU17: 169.4 | IV17: 172 | IW17: 170.1 | IX17: 170.5 | IY17: 173.3 | IZ17: 171.2 | JA17: NA | JB17: NA | JC17: NA | JD17: NA | JE17: NA | JF17: NA | JG17: 182.4 | JH17: 186.7 | JI17: 183.5 | JJ17: 182.4 | JK17: 186.7 | JL17: 183.5 | JM17: 180.9 | JN17: 187.2 | JO17: 182.6 | JP17: 182.9 | JQ17: 188.7 | JR17: 184.4 | JS17: 182.7 | JT17: 188.7 | JU17: 184.3 | JV17: 183.4 | JW17: 188.8 | JX17: 184.8 | JY17: 183.6 | JZ17: 190.2 | KA17: 185.4 | KB17: 184.6 | KC17: 191.8 | KD17: 186.5 | KE17: 186.5 | KF17: 193.3 | KG17: 188.3 | KH17: 186.1 | KI17: 193.5 | KJ17: 188.1 | KK17: 186.8 | KL17: 194.4 | KM17: 188.8 | KN17: 189.6 | KO17: 198.2 | KP17: 191.9 | KQ17: 189.1 | KR17: 195.6 | KS17: 190.8 | KT17: 189.7 | KU17: 195.5 | KV17: 191.2 | KW17: 190.2 | KX17: 196.5 | KY17: 192.1 | KZ17: 190.5 | LA17: 196.5 | LB17: 192.1 | LC17: 191.2 | LD17: 197 | LE17: 192.7 | LF17: 191.4 | LG17: 197 | LH17: 192.9 | LI17: 190.8 | LJ17: 196.8 | LK17: 192.4 | LL17: 190.7 | LM17: 196.4 | LN17: 192.2 | LO17: 191.5 | LP17: 196.5 | LQ17: 192.8 | LR17: 192.3 | LS17: 197.5 | LT17: 193.7 | LU17: 192.8 | LV17: 197.1 | LW17: 193.9 | LX17: 192.9 | LY17: 197.5 | LZ17: 194.1 | MA17: 192.9 | MB17: 198.3 | MC17: 194.3 | MD17: 193.2 | ME17: 198.6 | MF17: 194.6 | MG17: 193.7 | MH17: 198.7 | MI17: 195 | MJ17: 194.5 | MK17: 199.7 | ML17: 195.9 | MM17: 194.9 | MN17: 200.1 | MO17: 196.3 | MP17: 195.5 | MQ17: 200.6 | MR17: 196.9 | MS17: 195.9 | MT17: 201.1 | MU17: 197.3 | MV17: 196.9 | MW17: 201.6 | MX17: 198.2 | MY17: 198.3 | MZ17: 202.7 | NA17: 199.5 | NB17: 198.4 | NC17: 202.7 | ND17: 199.5 | NE17: 199.5 | NF17: 203.5 | NG17: 200.6 | NH17: 199.9 | NI17: 204.2 | NJ17: 201
A18: Clothing | B18: =VLOOKUP(A18, NOTES!C19:D44, 2,0) -> Clothing and Housing | C18: 106.5 | E18: 106.3 | F18: 107.1 | G18: 106.6 | H18: 106.9 | I18: 107.6 | J18: 107.2 | K18: 107.4 | L18: 108.1 | M18: 107.9 | N18: 108 | O18: 108.8 | P18: 108.5 | Q18: 108.7 | R18: 109.7 | S18: 109.2 | T18: 109.5 | U18: 110.5 | V18: 109.8 | W18: 110.2 | X18: 111.3 | Y18: 110.6 | Z18: 111 | AA18: 112.7 | AB18: 111.4 | AC18: 112.2 | AD18: 113.6 | AE18: 112.5 | AF18: 113.2 | AG18: 114.6 | AH18: 113.5 | AI18: 114.2 | AJ18: 115.8 | AK18: 114.2 | AL18: 115.2 | AM18: 116.5 | AN18: 114.8 | AO18: 115.8 | AP18: 117.1 | AQ18: 115.3 | AR18: 116.4 | AS18: 117.5 | AT18: 115.8 | AU18: 116.8 | AV18: 118.1 | AW18: 116.3 | AX18: 117.4 | AY18: 118.7 | AZ18: 116.8 | BA18: 118 | BB18: 119.7 | BC18: 117.4 | BD18: 118.8 | BE18: 120.7 | BF18: 118 | BG18: 119.6 | BH18: 120.9 | BI18: 118.6 | BJ18: 120 | BK18: 121.7 | BL18: 119.2 | BM18: 120.7 | BN18: 122.7 | BO18: 119.6 | BP18: 121.5 | BQ18: 123.3 | BR18: 120.3 | BS18: 122.1 | BT18: 123.8 | BU18: 120.7 | BV18: 122.6 | BW18: 124.4 | BX18: 121 | BY18: 123.1 | BZ18: 125.4 | CA18: 121.3 | CB18: 123.8 | CC18: 126 | CD18: 121.7 | CE18: 124.3 | CF18: 126.4 | CG18: 122.1 | CH18: 124.7 | CI18: 127.3 | CJ18: 122.4 | CK18: 125.4 | CL18: 128.4 | CM18: 123.2 | CN18: 126.4 | CO18: 128.8 | CP18: 123.5 | CQ18: 126.7 | CR18: 129.5 | CS18: 123.7 | CT18: 127.2 | CU18: 130.4 | CV18: 124 | CW18: 127.9 | CX18: 131.1 | CY18: 124.4 | CZ18: 128.5 | DA18: 132.1 | DB18: 125 | DC18: 129.3 | DD18: 132.5 | DE18: 125.4 | DF18: 129.7 | DG18: 133.2 | DH18: 125.8 | DI18: 130.3 | DJ18: 133.9 | DK18: 126.2 | DL18: 130.9 | DM18: 134.4 | DN18: 126.4 | DO18: 131.3 | DP18: 135 | DQ18: 126.8 | DR18: 131.8 | DS18: 135.4 | DT18: 127.2 | DU18: 132.2 | DV18: 136.3 | DW18: 127.6 | DX18: 132.9 | DY18: 137.2 | DZ18: 127.9 | EA18: 133.5 | EB18: 137.8 | EC18: 128.3 | ED18: 134.1 | EE18: 138.5 | EF18: 128.7 | EG18: 134.6 | EH18: 139.6 | EI18: 129.1 | EJ18: 135.5 | EK18: 139.9 | EL18: 129.6 | EM18: 135.8 | EN18: 140.4 | EO18: 130 | EP18: 136.3 | EQ18: 140.7 | ER18: 130.2 | ES18: 136.6 | ET18: 140.9 | EU18: 130.5 | EV18: 136.8 | EW18: 141.6 | EX18: 130.8 | EY18: 137.3 | EZ18: 142.4 | FA18: 131.2 | FB18: 138 | FC18: 142.5 | FD18: 131.5 | FE18: 138.2 | FF18: 143.1 | FG18: 131.5 | FH18: 138.5 | FI18: 144.3 | FJ18: 131.6 | FK18: 139.3 | FL18: 145.3 | FM18: 132.7 | FN18: 140.3 | FO18: 146.1 | FP18: 133.3 | FQ18: 141.1 | FR18: 147.2 | FS18: 134 | FT18: 142 | FU18: 148.2 | FV18: 135 | FW18: 143 | FX18: 148 | FY18: 135.6 | FZ18: 143.1 | GA18: 148.3 | GB18: 136 | GC18: 143.5 | GD18: 148.7 | GE18: 136.3 | GF18: 143.8 | GG18: 149.2 | GH18: 136.7 | GI18: 144.3 | GJ18: 150.1 | GK18: 137.8 | GL18: 145.3 | GM18: 150.8 | GN18: 138.6 | GO18: 146 | GP18: 151.3 | GQ18: 138.9 | GR18: 146.4 | GS18: 151.5 | GT18: 139.6 | GU18: 146.8 | GV18: 152.1 | GW18: 140 | GX18: 147.3 | GY18: 152.1 | GZ18: 140.8 | HA18: 147.7 | HB18: 150.7 | HC18: 141.5 | HD18: 148 | HE18: 151.7 | HF18: 142.4 | HG18: 148 | HH18: 151.6 | HI18: 142.7 | HJ18: 148.1 | HK18: 150.6 | HL18: 143 | HM18: 147.6 | HN18: 150.5 | HO18: 143.3 | HP18: 147.7 | HQ18: 150.8 | HR18: 143.5 | HS18: 147.9 | HT18: 151.3 | HU18: 144 | HV18: 148.4 | HW18: 151.4 | HX18: 144.3 | HY18: 148.6 | HZ18: 151.6 | IA18: 144.7 | IB18: 148.9 | IC18: 151.8 | ID18: 145 | IE18: 149.1 | IF18: 151.7 | IG18: 145.3 | IH18: 149.2 | II18: 151.7 | IJ18: 145.9 | IK18: 149.4 | IL18: 152.3 | IM18: 146.3 | IN18: 149.9 | IO18: 152.6 | IP18: 146.8 | IQ18: 150.3 | IR18: 152.8 | IS18: 147 | IT18: 150.5 | IU18: 153 | IV18: 147.3 | IW18: 150.8 | IX18: 153.4 | IY18: 147.7 | IZ18: 151.2 | JA18: NA | JB18: NA | JC18: NA | JD18: NA | JE18: NA | JF18: NA | JG18: 154.7 | JH18: 149.1 | JI18: 152.5 | JJ18: 154.7 | JK18: 149.1 | JL18: 152.5 | JM18: 155.1 | JN18: 150 | JO18: 153.1 | JP18: 155.4 | JQ18: 150.2 | JR18: 153.4 | JS18: 155.7 | JT18: 150.5 | JU18: 153.7 | JV18: 156.3 | JW18: 151.1 | JX18: 154.3 | JY18: 157 | JZ18: 151.9 | KA18: 155 | KB18: 157.5 | KC18: 152.5 | KD18: 155.5 | KE18: 159.1 | KF18: 154.2 | KG18: 157.2 | KH18: 159.6 | KI18: 155.1 | KJ18: 157.8 | KK18: 160.7 | KL18: 155.9 | KM18: 158.8 | KN18: 165.3 | KO18: 156.5 | KP18: 161.8 | KQ18: 165.3 | KR18: 157.3 | KS18: 162.2 | KT18: 166 | KU18: 157.9 | KV18: 162.8 | KW18: 167 | KX18: 159.8 | KY18: 164.5 | KZ18: 167.7 | LA18: 159.8 | LB18: 164.6 | LC18: 168.9 | LD18: 160.8 | LE18: 165.7 | LF18: 170.4 | LG18: 162.3 | LH18: 167.2 | LI18: 171.8 | LJ18: 163.3 | LK18: 168.5 | LL18: 173.2 | LM18: 164.7 | LN18: 169.9 | LO18: 174.1 | LP18: 165.7 | LQ18: 170.8 | LR18: 175.4 | LS18: 167.1 | LT18: 172.1 | LU18: 177.5 | LV18: 168.4 | LW18: 173.9 | LX18: 179.3 | LY18: 170 | LZ18: 175.6 | MA18: 180.7 | MB18: 171.6 | MC18: 177.1 | MD18: 182 | ME18: 172.7 | MF18: 178.3 | MG18: 183.2 | MH18: 173.7 | MI18: 179.5 | MJ18: 184.7 | MK18: 175 | ML18: 180.9 | MM18: 186.1 | MN18: 175.5 | MO18: 181.9 | MP18: 187.2 | MQ18: 176.7 | MR18: 183.1 | MS18: 188.1 | MT18: 177.7 | MU18: 184 | MV18: 189 | MW18: 178.7 | MX18: 184.9 | MY18: 190 | MZ18: 180.3 | NA18: 186.2 | NB18: 190 | NC18: 180.2 | ND18: 186.1 | NE18: 190.7 | NF18: 181 | NG18: 186.9 | NH18: 191.2 | NI18: 181.3 | NJ18: 187.3
A19: Footwear | B19: =VLOOKUP(A19, NOTES!C20:D45, 2,0) -> Clothing and Housing | C19: 105.8 | D19: 105 | E19: 105.5 | F19: 106.3 | G19: 105.5 | H19: 106 | I19: 106.8 | J19: 106 | K19: 106.5 | L19: 107.4 | M19: 106.4 | N19: 107 | O19: 107.9 | P19: 106.7 | Q19: 107.4 | R19: 108.8 | S19: 107.2 | T19: 108.1 | U19: 109.5 | V19: 107.8 | W19: 108.8 | X19: 110.2 | Y19: 108.3 | Z19: 109.4 | AA19: 111.4 | AB19: 109 | AC19: 110.4 | AD19: 112.3 | AE19: 109.7 | AF19: 111.2 | AG19: 113.1 | AH19: 110.3 | AI19: 111.9 | AJ19: 114 | AK19: 110.9 | AL19: 112.7 | AM19: 114.5 | AN19: 111.3 | AO19: 113.2 | AP19: 114.5 | AQ19: 111.7 | AR19: 113.3 | AS19: 114.9 | AT19: 112.1 | AU19: 113.7 | AV19: 116.1 | AW19: 112.5 | AX19: 114.6 | AY19: 116.8 | AZ19: 112.9 | BA19: 115.2 | BB19: 117.3 | BC19: 113.2 | BD19: 115.6 | BE19: 118.3 | BF19: 113.6 | BG19: 116.3 | BH19: 118.8 | BI19: 114.1 | BJ19: 116.8 | BK19: 119.2 | BL19: 114.5 | BM19: 117.2 | BN19: 120.3 | BO19: 114.9 | BP19: 118.1 | BQ19: 120.5 | BR19: 115.4 | BS19: 118.4 | BT19: 120.6 | BU19: 115.8 | BV19: 118.6 | BW19: 121.6 | BX19: 116.1 | BY19: 119.3 | BZ19: 122.7 | CA19: 116.5 | CB19: 120.1 | CC19: 122.9 | CD19: 116.9 | CE19: 120.4 | CF19: 123.3 | CG19: 117.2 | CH19: 120.8 | CI19: 124.1 | CJ19: 117.4 | CK19: 121.3 | CL19: 125.1 | CM19: 117.6 | CN19: 122 | CO19: 125.5 | CP19: 117.9 | CQ19: 122.3 | CR19: 126.3 | CS19: 118.2 | CT19: 122.9 | CU19: 126.8 | CV19: 118.6 | CW19: 123.4 | CX19: 127.3 | CY19: 118.8 | CZ19: 123.8 | DA19: 128.2 | DB19: 119.3 | DC19: 124.5 | DD19: 128.5 | DE19: 119.5 | DF19: 124.8 | DG19: 128.9 | DH19: 119.8 | DI19: 125.1 | DJ19: 129.8 | DK19: 120.1 | DL19: 125.8 | DM19: 130.2 | DN19: 120.3 | DO19: 126.1 | DP19: 130.6 | DQ19: 120.5 | DR19: 126.4 | DS19: 131.1 | DT19: 120.7 | DU19: 126.8 | DV19: 131.6 | DW19: 121.1 | DX19: 127.2 | DY19: 132.2 | DZ19: 121.1 | EA19: 127.6 | EB19: 133 | EC19: 121.4 | ED19: 128.2 | EE19: 133.5 | EF19: 121.6 | EG19: 128.6 | EH19: 134.3 | EI19: 121.9 | EJ19: 129.1 | EK19: 134.5 | EL19: 122.1 | EM19: 129.3 | EN19: 135.2 | EO19: 122.2 | EP19: 129.8 | EQ19: 135.8 | ER19: 122.3 | ES19: 130.2 | ET19: 135.8 | EU19: 122.5 | EV19: 130.3 | EW19: 136.2 | EX19: 122.8 | EY19: 130.6 | EZ19: 136.8 | FA19: 123 | FB19: 131.1 | FC19: 137.3 | FD19: 123.2 | FE19: 131.4 | FF19: 137.7 | FG19: 123.2 | FH19: 131.7 | FI19: 138.1 | FJ19: 123.7 | FK19: 132.1 | FL19: 139.2 | FM19: 124.3 | FN19: 133 | FO19: 139.7 | FP19: 124.6 | FQ19: 133.4 | FR19: 140.6 | FS19: 124.9 | FT19: 134.1 | FU19: 141.5 | FV19: 125.4 | FW19: 134.8 | FX19: 141.9 | FY19: 125.6 | FZ19: 135.1 | GA19: 142.3 | GB19: 125.9 | GC19: 135.5 | GD19: 142.4 | GE19: 126.1 | GF19: 135.6 | GG19: 143 | GH19: 126.7 | GI19: 136.2 | GJ19: 143.3 | GK19: 127.4 | GL19: 136.7 | GM19: 144.1 | GN19: 127.9 | GO19: 137.4 | GP19: 144.7 | GQ19: 128.7 | GR19: 138.1 | GS19: 145.1 | GT19: 128.9 | GU19: 138.4 | GV19: 145.8 | GW19: 129 | GX19: 138.8 | GY19: 146.1 | GZ19: 129.3 | HA19: 139.1 | HB19: 144.5 | HC19: 129.8 | HD19: 139.2 | HE19: 145.5 | HF19: 130.2 | HG19: 139.1 | HH19: 145.9 | HI19: 130.3 | HJ19: 139.4 | HK19: 145.1 | HL19: 130.4 | HM19: 139 | HN19: 146.1 | HO19: 130.8 | HP19: 139.7 | HQ19: 146.1 | HR19: 131.2 | HS19: 139.9 | HT19: 146.6 | HU19: 131.7 | HV19: 140.4 | HW19: 146.5 | HX19: 131.7 | HY19: 140.4 | HZ19: 146.6 | IA19: 131.9 | IB19: 140.5 | IC19: 146.6 | ID19: 132.2 | IE19: 140.6 | IF19: 146.6 | IG19: 132.2 | IH19: 140.6 | II19: 146.7 | IJ19: 132.4 | IK19: 140.8 | IL19: 147 | IM19: 132.6 | IN19: 141 | IO19: 147.3 | IP19: 132.8 | IQ19: 141.3 | IR19: 147.4 | IS19: 133.2 | IT19: 141.5 | IU19: 147.5 | IV19: 133.5 | IW19: 141.7 | IX19: 147.6 | IY19: 133.8 | IZ19: 141.9 | JA19: NA | JB19: NA | JC19: NA | JD19: NA | JE19: NA | JF19: NA | JG19: 150 | JH19: 136.6 | JI19: 144.4 | JJ19: 150 | JK19: 136.6 | JL19: 144.4 | JM19: 149.3 | JN19: 135.2 | JO19: 143.4 | JP19: 149.9 | JQ19: 136.3 | JR19: 144.3 | JS19: 150.6 | JT19: 136.1 | JU19: 144.6 | JV19: 151 | JW19: 136.4 | JX19: 144.9 | JY19: 151.6 | JZ19: 136.7 | KA19: 145.4 | KB19: 152.4 | KC19: 137.3 | KD19: 146.1 | KE19: 153.9 | KF19: 138.2 | KG19: 147.4 | KH19: 154.4 | KI19: 138.7 | KJ19: 147.9 | KK19: 155.1 | KL19: 139.3 | KM19: 148.5 | KN19: 160.6 | KO19: 140.2 | KP19: 152.1 | KQ19: 159.9 | KR19: 140.5 | KS19: 151.8 | KT19: 161.1 | KU19: 141.9 | KV19: 153.1 | KW19: 162.6 | KX19: 143.6 | KY19: 155.3 | KZ19: 163.6 | LA19: 143.6 | LB19: 155.3 | LC19: 164.8 | LD19: 144.4 | LE19: 156.3 | LF19: 166 | LG19: 145.3 | LH19: 157.4 | LI19: 167.3 | LJ19: 146.7 | LK19: 158.7 | LL19: 169.3 | LM19: 148.5 | LN19: 160.7 | LO19: 171 | LP19: 150.4 | LQ19: 162.4 | LR19: 173.2 | LS19: 152.6 | LT19: 164.6 | LU19: 175.1 | LV19: 154.5 | LW19: 166.5 | LX19: 177.2 | LY19: 155.9 | LZ19: 168.4 | MA19: 178.7 | MB19: 157.4 | MC19: 169.9 | MD19: 180.3 | ME19: 158.7 | MF19: 171.3 | MG19: 181.7 | MH19: 160 | MI19: 172.7 | MJ19: 183.3 | MK19: 161.7 | ML19: 174.3 | MM19: 184.4 | MN19: 162.6 | MO19: 175.3 | MP19: 185.2 | MQ19: 163.5 | MR19: 176.2 | MS19: 185.9 | MT19: 164.5 | MU19: 177 | MV19: 186.3 | MW19: 165.3 | MX19: 177.6 | MY19: 187 | MZ19: 167 | NA19: 178.7 | NB19: 187 | NC19: 167 | ND19: 178.7 | NE19: 187.3 | NF19: 167.7 | NG19: 179.2 | NH19: 187.9 | NI19: 168.1 | NJ19: 179.7
A20: Clothing and footwear | B20: =VLOOKUP(A20, NOTES!C21:D46, 2,0) -> Clothing and Housing | C20: 106.4 | D20: 105.8 | E20: 106.2 | F20: 107 | G20: 106.4 | H20: 106.8 | I20: 107.5 | J20: 107 | K20: 107.3 | L20: 108 | M20: 107.7 | N20: 107.9 | O20: 108.6 | P20: 108.3 | Q20: 108.5 | R20: 109.5 | S20: 108.9 | T20: 109.3 | U20: 110.3 | V20: 109.5 | W20: 110 | X20: 111.1 | Y20: 110.2 | Z20: 110.7 | AA20: 112.5 | AB20: 111.1 | AC20: 111.9 | AD20: 113.4 | AE20: 112 | AF20: 112.8 | AG20: 114.4 | AH20: 113 | AI20: 113.8 | AJ20: 115.5 | AK20: 113.7 | AL20: 114.8 | AM20: 116.2 | AN20: 114.3 | AO20: 115.4 | AP20: 116.7 | AQ20: 114.7 | AR20: 115.9 | AS20: 117.2 | AT20: 115.2 | AU20: 116.4 | AV20: 117.8 | AW20: 115.7 | AX20: 117 | AY20: 118.5 | AZ20: 116.2 | BA20: 117.6 | BB20: 119.3 | BC20: 116.7 | BD20: 118.3 | BE20: 120.3 | BF20: 117.4 | BG20: 119.1 | BH20: 120.7 | BI20: 117.9 | BJ20: 119.6 | BK20: 121.3 | BL20: 118.4 | BM20: 120.1 | BN20: 122.3 | BO20: 118.9 | BP20: 121 | BQ20: 122.9 | BR20: 119.5 | BS20: 121.6 | BT20: 123.3 | BU20: 120 | BV20: 122 | BW20: 124 | BX20: 120.2 | BY20: 122.5 | BZ20: 125 | CA20: 120.6 | CB20: 123.3 | CC20: 125.5 | CD20: 120.9 | CE20: 123.7 | CF20: 126 | CG20: 121.3 | CH20: 124.1 | CI20: 126.8 | CJ20: 121.6 | CK20: 124.7 | CL20: 128 | CM20: 122.3 | CN20: 125.7 | CO20: 128.3 | CP20: 122.7 | CQ20: 126.1 | CR20: 129 | CS20: 122.9 | CT20: 126.6 | CU20: 129.9 | CV20: 123.2 | CW20: 127.2 | CX20: 130.6 | CY20: 123.6 | CZ20: 127.8 | DA20: 131.5 | DB20: 124.2 | DC20: 128.6 | DD20: 131.9 | DE20: 124.5 | DF20: 129 | DG20: 132.6 | DH20: 124.9 | DI20: 129.5 | DJ20: 133.4 | DK20: 125.3 | DL20: 130.2 | DM20: 133.8 | DN20: 125.5 | DO20: 130.5 | DP20: 134.4 | DQ20: 125.8 | DR20: 131 | DS20: 134.8 | DT20: 126.2 | DU20: 131.4 | DV20: 135.6 | DW20: 126.6 | DX20: 132 | DY20: 136.5 | DZ20: 126.9 | EA20: 132.7 | EB20: 137.1 | EC20: 127.3 | ED20: 133.2 | EE20: 137.8 | EF20: 127.7 | EG20: 133.8 | EH20: 138.8 | EI20: 128 | EJ20: 134.5 | EK20: 139.2 | EL20: 128.5 | EM20: 135 | EN20: 139.7 | EO20: 128.8 | EP20: 135.4 | EQ20: 140 | ER20: 129 | ES20: 135.6 | ET20: 140.2 | EU20: 129.3 | EV20: 135.9 | EW20: 140.8 | EX20: 129.6 | EY20: 136.4 | EZ20: 141.6 | FA20: 130 | FB20: 137 | FC20: 141.8 | FD20: 130.2 | FE20: 137.2 | FF20: 142.3 | FG20: 130.2 | FH20: 137.5 | FI20: 143.5 | FJ20: 130.4 | FK20: 138.3 | FL20: 144.5 | FM20: 131.4 | FN20: 139.3 | FO20: 145.2 | FP20: 132 | FQ20: 140 | FR20: 146.2 | FS20: 132.6 | FT20: 140.8 | FU20: 147.3 | FV20: 133.5 | FW20: 141.8 | FX20: 147.2 | FY20: 134 | FZ20: 142 | GA20: 147.5 | GB20: 134.4 | GC20: 142.3 | GD20: 147.8 | GE20: 134.7 | GF20: 142.6 | GG20: 148.3 | GH20: 135.2 | GI20: 143.1 | GJ20: 149.1 | GK20: 136.2 | GL20: 144 | GM20: 149.8 | GN20: 137 | GO20: 144.7 | GP20: 150.3 | GQ20: 137.4 | GR20: 145.2 | GS20: 150.6 | GT20: 137.9 | GU20: 145.6 | GV20: 151.3 | GW20: 138.3 | GX20: 146.1 | GY20: 151.3 | GZ20: 139.1 | HA20: 146.5 | HB20: 149.8 | HC20: 139.7 | HD20: 146.8 | HE20: 150.8 | HF20: 140.5 | HG20: 146.7 | HH20: 150.8 | HI20: 140.8 | HJ20: 146.8 | HK20: 149.9 | HL20: 141.1 | HM20: 146.4 | HN20: 149.9 | HO20: 141.4 | HP20: 146.5 | HQ20: 150.1 | HR20: 141.6 | HS20: 146.7 | HT20: 150.7 | HU20: 142.2 | HV20: 147.3 | HW20: 150.7 | HX20: 142.4 | HY20: 147.4 | HZ20: 150.9 | IA20: 142.7 | IB20: 147.6 | IC20: 151.1 | ID20: 143 | IE20: 147.9 | IF20: 151 | IG20: 143.3 | IH20: 147.9 | II20: 151 | IJ20: 143.9 | IK20: 148.2 | IL20: 151.5 | IM20: 144.2 | IN20: 148.6 | IO20: 151.9 | IP20: 144.6 | IQ20: 149 | IR20: 152.1 | IS20: 144.9 | IT20: 149.2 | IU20: 152.3 | IV20: 145.2 | IW20: 149.5 | IX20: 152.5 | IY20: 145.6 | IZ20: 149.8 | JA20: NA | JB20: NA | JC20: NA | JD20: NA | JE20: NA | JF20: NA | JG20: 154.1 | JH20: 147.2 | JI20: 151.4 | JJ20: 154.1 | JK20: 147.2 | JL20: 151.4 | JM20: 154.3 | JN20: 147.8 | JO20: 151.7 | JP20: 154.6 | JQ20: 148.1 | JR20: 152 | JS20: 155 | JT20: 148.3 | JU20: 152.3 | JV20: 155.5 | JW20: 148.8 | JX20: 152.8 | JY20: 156.3 | JZ20: 149.6 | KA20: 153.6 | KB20: 156.8 | KC20: 150.2 | KD20: 154.2 | KE20: 158.4 | KF20: 151.8 | KG20: 155.8 | KH20: 158.9 | KI20: 152.6 | KJ20: 156.4 | KK20: 159.9 | KL20: 153.4 | KM20: 157.3 | KN20: 164.5 | KO20: 154.1 | KP20: 160.4 | KQ20: 164.6 | KR20: 154.8 | KS20: 160.7 | KT20: 165.3 | KU20: 155.5 | KV20: 161.4 | KW20: 166.3 | KX20: 157.3 | KY20: 163.2 | KZ20: 167.1 | LA20: 157.4 | LB20: 163.3 | LC20: 168.3 | LD20: 158.3 | LE20: 164.3 | LF20: 169.8 | LG20: 159.7 | LH20: 165.8 | LI20: 171.2 | LJ20: 160.7 | LK20: 167 | LL20: 172.7 | LM20: 162.2 | LN20: 168.5 | LO20: 173.7 | LP20: 163.4 | LQ20: 169.6 | LR20: 175.1 | LS20: 164.9 | LT20: 171.1 | LU20: 177.1 | LV20: 166.3 | LW20: 172.8 | LX20: 179 | LY20: 167.8 | LZ20: 174.6 | MA20: 180.4 | MB20: 169.4 | MC20: 176 | MD20: 181.7 | ME20: 170.6 | MF20: 177.3 | MG20: 183 | MH20: 171.6 | MI20: 178.5 | MJ20: 184.5 | MK20: 173 | ML20: 179.9 | MM20: 185.9 | MN20: 173.6 | MO20: 181 | MP20: 186.9 | MQ20: 174.7 | MR20: 182.1 | MS20: 187.8 | MT20: 175.7 | MU20: 183 | MV20: 188.6 | MW20: 176.6 | MX20: 183.8 | MY20: 189.6 | MZ20: 178.2 | NA20: 185.1 | NB20: 189.6 | NC20: 178.2 | ND20: 185.1 | NE20: 190.2 | NF20: 178.9 | NG20: 185.7 | NH20: 190.8 | NI20: 179.3 | NJ20: 186.2
A21: Housing | B21: =VLOOKUP(A21, NOTES!C22:D47, 2,0) -> Clothing and Housing | C21: NA | D21: 100.3 | E21: =SUMPRODUCT((Sheet3!$MA$1:$NJ$1="Rural+Urban")*(Sheet3!$A$4:$A$13=QUES_3!K22)*Sheet3!$MA$4:$NJ$13) -> 0 | F21: =E21/$E$31 -> 0 | G21: 100.4 | H21: 100.4 | I21: NA | J21: 100.4 | K21: 100.4 | L21: NA | M21: 100.5 | N21: 100.5 | O21: NA | P21: 100.5 | Q21: 100.5 | R21: NA | S21: 106.6 | T21: 106.6 | U21: NA | V21: 107.7 | W21: 107.7 | X21: NA | Y21: 108.9 | Z21: 108.9 | AA21: NA | AB21: 109.7 | AC21: 109.7 | AD21: NA | AE21: 110.5 | AF21: 110.5 | AG21: NA | AH21: 111.1 | AI21: 111.1 | AJ21: NA | AK21: 110.7 | AL21: 110.7 | AM21: NA | AN21: 111.6 | AO21: 111.6 | AP21: NA | AQ21: 112.5 | AR21: 112.5 | AS21: NA | AT21: 113.2 | AU21: 113.2 | AV21: NA | AW21: 113.9 | AX21: 113.9 | AY21: NA | AZ21: 114.3 | BA21: 114.3 | BB21: NA | BC21: 113.9 | BD21: 113.9 | BE21: NA | BF21: 114.8 | BG21: 114.8 | BH21: NA | BI21: 115.5 | BJ21: 115.5 | BK21: NA | BL21: 116.1 | BM21: 116.1 | BN21: NA | BO21: 116.7 | BP21: 116.7 | BQ21: NA | BR21: 117.1 | BS21: 117.1 | BT21: NA | BU21: 116.5 | BV21: 116.5 | BW21: NA | BX21: 117.3 | BY21: 117.3 | BZ21: NA | CA21: 118.1 | CB21: 118.1 | CC21: NA | CD21: 118.6 | CE21: 118.6 | CF21: NA | CG21: 119.2 | CH21: 119.2 | CI21: NA | CJ21: 119.6 | CK21: 119.6 | CL21: NA | CM21: 119 | CN21: 119 | CO21: NA | CP21: 119.9 | CQ21: 119.9 | CR21: NA | CS21: 120.9 | CT21: 120.9 | CU21: NA | CV21: 121.6 | CW21: 121.6 | CX21: NA | CY21: 122.4 | CZ21: 122.4 | DA21: NA | DB21: 122.9 | DC21: 122.9 | DD21: NA | DE21: 122.4 | DF21: 122.4 | DG21: NA | DH21: 123.4 | DI21: 123.4 | DJ21: NA | DK21: 124.4 | DL21: 124.4 | DM21: NA | DN21: 124.9 | DO21: 124.9 | DP21: NA | DQ21: 125.6 | DR21: 125.6 | DS21: NA | DT21: 126 | DU21: 126 | DV21: NA | DW21: 125.5 | DX21: 125.5 | DY21: NA | DZ21: 126.4 | EA21: 126.4 | EB21: NA | EC21: 127.3 | ED21: 127.3 | EE21: NA | EF21: 127.9 | EG21: 127.9 | EH21: NA | EI21: 128.7 | EJ21: 128.7 | EK21: NA | EL21: 129.1 | EM21: 129.1 | EN21: NA | EO21: 128.5 | EP21: 128.5 | EQ21: NA | ER21: 129.6 | ES21: 129.6 | ET21: NA | EU21: 130.5 | EV21: 130.5 | EW21: NA | EX21: 131.1 | EY21: 131.1 | EZ21: NA | FA21: 131.7 | FB21: 131.7 | FC21: NA | FD21: 132.1 | FE21: 132.1 | FF21: NA | FG21: 131.4 | FH21: 131.4 | FI21: NA | FJ21: 132.6 | FK21: 132.6 | FL21: NA | FM21: 134.4 | FN21: 134.4 | FO21: NA | FP21: 135.7 | FQ21: 135.7 | FR21: NA | FS21: 137.3 | FT21: 137.3 | FU21: NA | FV21: 138.6 | FW21: 138.6 | FX21: NA | FY21: 139.1 | FZ21: 139.1 | GA21: NA | GB21: 140.4 | GC21: 140.4 | GD21: NA | GE21: 141.3 | GF21: 141.3 | GG21: NA | GH21: 142 | GI21: 142 | GJ21: NA | GK21: 142.9 | GL21: 142.9 | GM21: NA | GN21: 143.2 | GO21: 143.2 | GP21: NA | GQ21: 142.5 | GR21: 142.5 | GS21: NA | GT21: 143.6 | GU21: 143.6 | GV21: NA | GW21: 144.6 | GX21: 144.6 | GY21: NA | GZ21: 145.3 | HA21: 145.3 | HB21: NA | HC21: 146.3 | HD21: 146.9 | HE21: NA | HF21: 146.9 | HG21: 146.9 | HH21: NA | HI21: 146.5 | HJ21: 146.5 | HK21: NA | HL21: 147.7 | HM21: 147.7 | HN21: NA | HO21: 148.5 | HP21: 148.5 | HQ21: NA | HR21: 149 | HS21: 149 | HT21: NA | HU21: 150.1 | HV21: 150.1 | HW21: NA | HX21: 149.4 | HY21: 149.4 | HZ21: NA | IA21: 150.6 | IB21: 150.6 | IC21: NA | ID21: 151.6 | IE21: 151.6 | IF21: NA | IG21: 152.2 | IH21: 152.2 | II21: NA | IJ21: 153 | IK21: 153 | IL21: NA | IM21: 153.5 | IN21: 153.5 | IO21: NA | IP21: 152.8 | IQ21: 152.8 | IR21: NA | IS21: 153.9 | IT21: 153.9 | IU21: NA | IV21: 154.8 | IW21: 154.8 | IX21: NA | IY21: 154.5 | IZ21: 154.5 | JA21: NA | JB21: 155.6 | JC21: 155.6 | JD21: NA | JE21: NA | JF21: NA | JG21: NA | JH21: 154.7 | JI21: 154.7 | JJ21: NA | JK21: 154.7 | JL21: 154.7 | JM21: NA | JN21: 155.5 | JO21: 155.5 | JP21: NA | JQ21: 156.3 | JR21: 156.3 | JS21: NA | JT21: 156.5 | JU21: 156.5 | JV21: NA | JW21: 158 | JX21: 158 | JY21: NA | JZ21: 158.4 | KA21: 158.4 | KB21: NA | KC21: 157.7 | KD21: 157.7 | KE21: NA | KF21: 159.8 | KG21: 159.8 | KH21: - | KI21: 159.9 | KJ21: 159.9 | KK21: - | KL21: 161.4 | KM21: 161.4 | KN21: NA | KO21: 161.6 | KP21: 161.6 | KQ21: NA | KR21: 160.5 | KS21: 160.5 | KT21: NA | KU21: 161.5 | KV21: 161.5 | KW21: NA | KX21: 162.1 | KY21: 162.1 | KZ21: NA | LA21: 162.1 | LB21: 162.1 | LC21: NA | LD21: 163.6 | LE21: 163.6 | LF21: NA | LG21: 164.2 | LH21: 164.2 | LI21: NA | LJ21: 163.4 | LK21: 163.4 | LL21: NA | LM21: 164.5 | LN21: 164.5 | LO21: NA | LP21: 165.5 | LQ21: 165.5 | LR21: NA | LS21: 165.3 | LT21: 165.3 | LU21: NA | LV21: 167 | LW21: 167 | LX21: NA | LY21: 167.5 | LZ21: 167.5 | MA21: NA | MB21: 166.8 | MC21: 166.8 | MD21: NA | ME21: 167.8 | MF21: 167.8 | MG21: NA | MH21: 169 | MI21: 169 | MJ21: NA | MK21: 169.5 | ML21: 169.5 | MM21: NA | MN21: 171.2 | MO21: 171.2 | MP21: NA | MQ21: 171.8 | MR21: 171.8 | MS21: NA | MT21: 170.7 | MU21: 170.7 | MV21: NA | MW21: 172.1 | MX21: 172.1 | MY21: NA | MZ21: 173.5 | NA21: 173.5 | NB21: NA | NC21: 173.5 | ND21: 173.5 | NE21: - | NF21: 175.2 | NG21: 175.2 | NH21: - | NI21: 175.6 | NJ21: 175.6
A22: Fuel and light | B22: =VLOOKUP(A22, NOTES!C23:D48, 2,0) -> Clothing and Housing | C22: 105.5 | D22: 105.4 | E22: =SUMPRODUCT((Sheet3!$MA$1:$NJ$1="Rural+Urban")*(Sheet3!$A$4:$A$13=QUES_3!K23)*Sheet3!$MA$4:$NJ$13) -> 0 | F22: =E22/$E$31 -> 0 | G22: 105.7 | H22: 106 | I22: 106.1 | J22: 106 | K22: 106.1 | L22: 106.5 | M22: 106.4 | N22: 106.5 | O22: 107.5 | P22: 107.2 | Q22: 107.4 | R22: 108.5 | S22: 108 | T22: 108.3 | U22: 109.5 | V22: 108.6 | W22: 109.2 | X22: 109.9 | Y22: 109.3 | Z22: 109.7 | AA22: 111.1 | AB22: 109.5 | AC22: 110.5 | AD22: 111.6 | AE22: 109.7 | AF22: 110.9 | AG22: 112.6 | AH22: 110 | AI22: 111.6 | AJ22: 112.8 | AK22: 110.4 | AL22: 111.9 | AM22: 113 | AN22: 111 | AO22: 112.2 | AP22: 113.2 | AQ22: 111.1 | AR22: 112.4 | AS22: 113.4 | AT22: 110.9 | AU22: 112.5 | AV22: 113.4 | AW22: 110.9 | AX22: 112.5 | AY22: 113.4 | AZ22: 111.1 | BA22: 112.5 | BB22: 114.4 | BC22: 111.2 | BD22: 113.2 | BE22: 115.3 | BF22: 111.6 | BG22: 113.9 | BH22: 115.4 | BI22: 111.8 | BJ22: 114 | BK22: 115.8 | BL22: 111.8 | BM22: 114.3 | BN22: 116.4 | BO22: 112 | BP22: 114.7 | BQ22: 117.3 | BR22: 112.6 | BS22: 115.5 | BT22: 117.4 | BU22: 113 | BV22: 115.7 | BW22: 118.4 | BX22: 113.4 | BY22: 116.5 | BZ22: 120 | CA22: 114 | CB22: 117.7 | CC22: 120.6 | CD22: 114.4 | CE22: 118.3 | CF22: 121.2 | CG22: 114.7 | CH22: 118.7 | CI22: 121.9 | CJ22: 114.9 | CK22: 119.2 | CL22: 122.6 | CM22: 115.1 | CN22: 119.8 | CO22: 123 | CP22: 115.3 | CQ22: 120.1 | CR22: 123.8 | CS22: 115.3 | CT22: 120.6 | CU22: 123.7 | CV22: 115.1 | CW22: 120.4 | CX22: 124.4 | CY22: 114.9 | CZ22: 120.8 | DA22: 125.6 | DB22: 115.1 | DC22: 121.6 | DD22: 125.7 | DE22: 116 | DF22: 122 | DG22: 126.2 | DH22: 116.9 | DI22: 122.7 | DJ22: 127.5 | DK22: 116 | DL22: 123.1 | DM22: 127 | DN22: 114.8 | DO22: 122.4 | DP22: 127 | DQ22: 114.6 | DR22: 122.3 | DS22: 127.4 | DT22: 115 | DU22: 122.7 | DV22: 128 | DW22: 115.5 | DX22: 123.3 | DY22: 128.2 | DZ22: 115.5 | EA22: 123.4 | EB22: 129.1 | EC22: 114.7 | ED22: 123.6 | EE22: 129.7 | EF22: 114.8 | EG22: 124.1 | EH22: 129.8 | EI22: 115.2 | EJ22: 124.3 | EK22: 130.3 | EL22: 116.2 | EM22: 125 | EN22: 132 | EO22: 117.8 | EP22: 126.6 | EQ22: 132.1 | ER22: 118 | ES22: 126.8 | ET22: 133.2 | EU22: 119.2 | EV22: 127.9 | EW22: 134.2 | EX22: 120.8 | EY22: 129.1 | EZ22: 135 | FA22: 121.4 | FB22: 129.8 | FC22: 135 | FD22: 120.1 | FE22: 129.4 | FF22: 134.8 | FG22: 119 | FH22: 128.8 | FI22: 135.3 | FJ22: 119.7 | FK22: 129.4 | FL22: 136.4 | FM22: 118.9 | FN22: 129.8 | FO22: 137.4 | FP22: 120.6 | FQ22: 131 | FR22: 138.1 | FS22: 122.6 | FT22: 132.2 | FU22: 141.1 | FV22: 125.7 | FW22: 135.3 | FX22: 142.6 | FY22: 126.8 | FZ22: 136.6 | GA22: 142.3 | GB22: 127.3 | GC22: 136.6 | GD22: 142.4 | GE22: 127.3 | GF22: 136.7 | GG22: 142.6 | GH22: 126.4 | GI22: 136.5 | GJ22: 143.8 | GK22: 124.6 | GL22: 136.5 | GM22: 144.3 | GN22: 124.7 | GO22: 136.9 | GP22: 145.1 | GQ22: 126.5 | GR22: 138.1 | GS22: 146.8 | GT22: 128.1 | GU22: 139.7 | GV22: 147.7 | GW22: 129.8 | GX22: 140.9 | GY22: 149 | GZ22: 131.2 | HA22: 142.3 | HB22: 149.7 | HC22: 133.4 | HD22: 145.3 | HE22: 150.3 | HF22: 136.7 | HG22: 145.1 | HH22: 149 | HI22: 132.4 | HJ22: 142.7 | HK22: 146.2 | HL22: 128.6 | HM22: 139.5 | HN22: 145.3 | HO22: 127.1 | HP22: 138.4 | HQ22: 146.4 | HR22: 128.8 | HS22: 139.7 | HT22: 146.9 | HU22: 129.4 | HV22: 140.3 | HW22: 147.8 | HX22: 130.5 | HY22: 141.2 | HZ22: 146.8 | IA22: 127 | IB22: 139.3 | IC22: 146.4 | ID22: 125.5 | IE22: 138.5 | IF22: 146.9 | IG22: 126.6 | IH22: 139.2 | II22: 147.7 | IJ22: 128.9 | IK22: 140.6 | IL22: 148.4 | IM22: 132.2 | IN22: 142.3 | IO22: 149.9 | IP22: 133.6 | IQ22: 143.7 | IR22: 150.4 | IS22: 135.1 | IT22: 144.6 | IU22: 152.3 | IV22: 138.9 | IW22: 147.2 | IX22: 153.4 | IY22: 141.4 | IZ22: 148.9 | JA22: 148.4 | JB22: 137.1 | JC22: 144.1 | JD22: NA | JE22: NA | JF22: NA | JG22: 144.9 | JH22: 137.1 | JI22: 141.9 | JJ22: 144.9 | JK22: 137.1 | JL22: 141.9 | JM22: 145.8 | JN22: 138.3 | JO22: 143 | JP22: 146.4 | JQ22: 137.2 | JR22: 142.9 | JS22: 146.8 | JT22: 137.1 | JU22: 143.1 | JV22: 147.5 | JW22: 137.3 | JX22: 143.6 | JY22: 148.7 | JZ22: 137.9 | KA22: 144.6 | KB22: 150.9 | KC22: 142.9 | KD22: 147.9 | KE22: 154.4 | KF22: 149.1 | KG22: 152.4 | KH22: 156 | KI22: 154.8 | KJ22: 155.5 | KK22: 156 | KL22: 154.9 | KM22: 155.6 | KN22: 161.7 | KO22: 155.5 | KP22: 159.4 | KQ22: 162.1 | KR22: 156.1 | KS22: 159.8 | KT22: 162.5 | KU22: 157.7 | KV22: 160.7 | KW22: 163.1 | KX22: 160.7 | KY22: 162.6 | KZ22: 163.7 | LA22: 160.8 | LB22: 162.6 | LC22: 165.5 | LD22: 162.2 | LE22: 164.2 | LF22: 165.3 | LG22: 161.6 | LH22: 163.9 | LI22: 165.6 | LJ22: 161.7 | LK22: 164.1 | LL22: 165.8 | LM22: 161.6 | LN22: 164.2 | LO22: 167.4 | LP22: 163 | LQ22: 165.7 | LR22: 168.9 | LS22: 164.5 | LT22: 167.2 | LU22: 173.3 | LV22: 170.5 | LW22: 172.2 | LX22: 175.3 | LY22: 173.5 | LZ22: 174.6 | MA22: 176.7 | MB22: 174.9 | MC22: 176 | MD22: 179.6 | ME22: 179.5 | MF22: 179.6 | MG22: 179.1 | MH22: 178.4 | MI22: 178.8 | MJ22: 179.7 | MK22: 179.2 | ML22: 179.5 | MM22: 180.8 | MN22: 180 | MO22: 180.5 | MP22: 181.9 | MQ22: 180.3 | MR22: 181.3 | MS22: 182.8 | MT22: 180.6 | MU22: 182 | MV22: 183.2 | MW22: 180.1 | MX22: 182 | MY22: 181.6 | MZ22: 182.8 | NA22: 182.1 | NB22: 181.4 | NC22: 182.6 | ND22: 181.9 | NE22: 181.5 | NF22: 182.1 | NG22: 181.7 | NH22: 182.5 | NI22: 183.4 | NJ22: 182.8
A23: Household goods and services | B23: =VLOOKUP(A23, NOTES!C24:D49, 2,0) -> Goods, Services and Transport | C23: 104.8 | D23: 104.8 | E23: =SUMPRODUCT((Sheet3!$MA$1:$NJ$1="Rural+Urban")*(Sheet3!$A$4:$A$13=QUES_3!K24)*Sheet3!$MA$4:$NJ$13) -> 2115.1 | F23: =E23/$E$31 -> 0.24531716 | G23: 105.2 | H23: 105.2 | I23: 105.6 | J23: 105.7 | K23: 105.6 | L23: 106.1 | M23: 106.5 | N23: 106.3 | O23: 106.8 | P23: 107.1 | Q23: 106.9 | R23: 107.5 | S23: 107.7 | T23: 107.6 | U23: 108.3 | V23: 108.1 | W23: 108.2 | X23: 108.7 | Y23: 108.7 | Z23: 108.7 | AA23: 109.6 | AB23: 109.6 | AC23: 109.6 | AD23: 110.4 | AE23: 110.2 | AF23: 110.3 | AG23: 111.3 | AH23: 110.9 | AI23: 111.1 | AJ23: 112.1 | AK23: 111.3 | AL23: 111.7 | AM23: 112.6 | AN23: 111.9 | AO23: 112.3 | AP23: 112.9 | AQ23: 112.6 | AR23: 112.8 | AS23: 113.4 | AT23: 113 | AU23: 113.2 | AV23: 113.7 | AW23: 113.4 | AX23: 113.6 | AY23: 114.1 | AZ23: 114.1 | BA23: 114.1 | BB23: 114.9 | BC23: 114.3 | BD23: 114.6 | BE23: 115.4 | BF23: 114.9 | BG23: 115.2 | BH23: 115.9 | BI23: 115.3 | BJ23: 115.6 | BK23: 116.7 | BL23: 115.5 | BM23: 116.1 | BN23: 117.5 | BO23: 115.8 | BP23: 116.7 | BQ23: 118.1 | BR23: 116.4 | BS23: 117.3 | BT23: 118.2 | BU23: 116.8 | BV23: 117.5 | BW23: 118.9 | BX23: 117.2 | BY23: 118.1 | BZ23: 119.6 | CA23: 117.7 | CB23: 118.7 | CC23: 120.2 | CD23: 118 | CE23: 119.2 | CF23: 120.9 | CG23: 118.4 | CH23: 119.7 | CI23: 121.5 | CJ23: 118.7 | CK23: 120.2 | CL23: 122.8 | CM23: 119.2 | CN23: 121.1 | CO23: 123 | CP23: 119.5 | CQ23: 121.3 | CR23: 123.7 | CS23: 120 | CT23: 122 | CU23: 124.5 | CV23: 120.4 | CW23: 122.6 | CX23: 125.1 | CY23: 120.7 | CZ23: 123 | DA23: 125.6 | DB23: 121 | DC23: 123.4 | DD23: 126 | DE23: 121 | DF23: 123.6 | DG23: 126.6 | DH23: 121.6 | DI23: 124.2 | DJ23: 127.1 | DK23: 121.8 | DL23: 124.6 | DM23: 127.7 | DN23: 122.3 | DO23: 125.1 | DP23: 128 | DQ23: 122.8 | DR23: 125.5 | DS23: 128.5 | DT23: 123.2 | DU23: 126 | DV23: 129.3 | DW23: 123.2 | DX23: 126.4 | DY23: 130 | DZ23: 123.5 | EA23: 126.9 | EB23: 130.6 | EC23: 123.9 | ED23: 127.4 | EE23: 131.1 | EF23: 124.3 | EG23: 127.9 | EH23: 131.8 | EI23: 124.5 | EJ23: 128.4 | EK23: 132.1 | EL23: 124.7 | EM23: 128.6 | EN23: 132.9 | EO23: 125 | EP23: 129.2 | EQ23: 133.2 | ER23: 125.1 | ES23: 129.4 | ET23: 133.6 | EU23: 125.3 | EV23: 129.7 | EW23: 134.1 | EX23: 125.6 | EY23: 130.1 | EZ23: 134.3 | FA23: 126 | FB23: 130.4 | FC23: 134.9 | FD23: 126.5 | FE23: 130.9 | FF23: 135.2 | FG23: 126.8 | FH23: 131.2 | FI23: 136.1 | FJ23: 127.2 | FK23: 131.9 | FL23: 137.3 | FM23: 127.7 | FN23: 132.8 | FO23: 137.9 | FP23: 128.1 | FQ23: 133.3 | FR23: 138.4 | FS23: 128.3 | FT23: 133.6 | FU23: 139.4 | FV23: 128.8 | FW23: 134.4 | FX23: 139.5 | FY23: 129.3 | FZ23: 134.7 | GA23: 139.8 | GB23: 129.5 | GC23: 134.9 | GD23: 139.9 | GE23: 129.9 | GF23: 135.2 | GG23: 139.9 | GH23: 130.8 | GI23: 135.6 | GJ23: 140.9 | GK23: 131.8 | GL23: 136.6 | GM23: 141.8 | GN23: 132.5 | GO23: 137.4 | GP23: 142.2 | GQ23: 133.1 | GR23: 137.9 | GS23: 143.1 | GT23: 133.6 | GU23: 138.6 | GV23: 143.8 | GW23: 134.4 | GX23: 139.4 | GY23: 144 | GZ23: 134.9 | HA23: 139.7 | HB23: 147.5 | HC23: 135.1 | HD23: 142.2 | HE23: 148 | HF23: 135.8 | HG23: 142.2 | HH23: 149.5 | HI23: 136.2 | HJ23: 143.2 | HK23: 150.1 | HL23: 136.3 | HM23: 143.6 | HN23: 150.1 | HO23: 136.6 | HP23: 143.7 | HQ23: 150 | HR23: 136.8 | HS23: 143.8 | HT23: 149.5 | HU23: 137.2 | HV23: 143.7 | HW23: 149.6 | HX23: 137.4 | HY23: 143.8 | HZ23: 150 | IA23: 137.7 | IB23: 144.2 | IC23: 150.2 | ID23: 138.1 | IE23: 144.5 | IF23: 150.3 | IG23: 138.3 | IH23: 144.6 | II23: 150.6 | IJ23: 138.7 | IK23: 145 | IL23: 150.9 | IM23: 139.1 | IN23: 145.3 | IO23: 151.2 | IP23: 139.8 | IQ23: 145.8 | IR23: 151.7 | IS23: 140.1 | IT23: 146.2 | IU23: 151.8 | IV23: 140.4 | IW23: 146.4 | IX23: 151.5 | IY23: 140.8 | IZ23: 146.4 | JA23: NA | JB23: NA | JC23: NA | JD23: NA | JE23: NA | JF23: NA | JG23: 151.7 | JH23: 140.4 | JI23: 146.4 | JJ23: 151.7 | JK23: 140.4 | JL23: 146.4 | JM23: 151.9 | JN23: 144.5 | JO23: 148.4 | JP23: 151.6 | JQ23: 145.4 | JR23: 148.7 | JS23: 152 | JT23: 145.1 | JU23: 148.7 | JV23: 152.8 | JW23: 145.1 | JX23: 149.2 | JY23: 153.4 | JZ23: 145.5 | KA23: 149.7 | KB23: 153.9 | KC23: 145.7 | KD23: 150 | KE23: 154.8 | KF23: 146.5 | KG23: 150.9 | KH23: 154.8 | KI23: 147.2 | KJ23: 151.2 | KK23: 155.5 | KL23: 147.6 | KM23: 151.8 | KN23: 158.8 | KO23: 150.1 | KP23: 154.7 | KQ23: 159.2 | KR23: 149.8 | KS23: 154.8 | KT23: 160.3 | KU23: 150.7 | KV23: 155.8 | KW23: 160.9 | KX23: 153.2 | KY23: 157.5 | KZ23: 161.3 | LA23: 153.3 | LB23: 157.5 | LC23: 162 | LD23: 154.3 | LE23: 158.4 | LF23: 162.9 | LG23: 155.2 | LH23: 159.3 | LI23: 163.9 | LJ23: 156 | LK23: 160.2 | LL23: 164.9 | LM23: 156.8 | LN23: 161.1 | LO23: 165.7 | LP23: 157.4 | LQ23: 161.8 | LR23: 166.5 | LS23: 158.6 | LT23: 162.8 | LU23: 167.7 | LV23: 159.8 | LW23: 164 | LX23: 168.9 | LY23: 161.1 | LZ23: 165.2 | MA23: 170.3 | MB23: 162.1 | MC23: 166.4 | MD23: 171.3 | ME23: 163.1 | MF23: 167.4 | MG23: 172.3 | MH23: 164.2 | MI23: 168.5 | MJ23: 173.6 | MK23: 165 | ML23: 169.5 | MM23: 174.4 | MN23: 166 | MO23: 170.4 | MP23: 175.5 | MQ23: 166.9 | MR23: 171.4 | MS23: 176.4 | MT23: 167.3 | MU23: 172.1 | MV23: 177.2 | MW23: 168 | MX23: 172.9 | MY23: 178.6 | MZ23: 169.2 | NA23: 174.2 | NB23: 178.6 | NC23: 169.2 | ND23: 174.2 | NE23: 179.1 | NF23: 169.6 | NG23: 174.6 | NH23: 179.8 | NI23: 170.1 | NJ23: 175.2
A24: Health | B24: =VLOOKUP(A24, NOTES!C25:D50, 2,0) -> Goods, Services and Transport | C24: 104 | D24: 104.1 | E24: =SUMPRODUCT((Sheet3!$MA$1:$NJ$1="Rural+Urban")*(Sheet3!$A$4:$A$13=QUES_3!K25)*Sheet3!$MA$4:$NJ$13) -> 0 | F24: =E24/$E$31 -> 0 | G24: 104.7 | H24: 104.5 | I24: 104.7 | J24: 105.2 | K24: 104.9 | L24: 105.1 | M24: 105.7 | N24: 105.3 | O24: 105.7 | P24: 106.2 | Q24: 105.9 | R24: 106.3 | S24: 106.5 | T24: 106.4 | U24: 106.9 | V24: 107.1 | W24: 107 | X24: 107.5 | Y24: 107.6 | Z24: 107.5 | AA24: 108.3 | AB24: 107.9 | AC24: 108.1 | AD24: 108.9 | AE24: 108.2 | AF24: 108.6 | AG24: 109.7 | AH24: 108.6 | AI24: 109.3 | AJ24: 110.1 | AK24: 109 | AL24: 109.7 | AM24: 110.6 | AN24: 109.7 | AO24: 110.3 | AP24: 110.9 | AQ24: 110.4 | AR24: 110.7 | AS24: 111.4 | AT24: 110.8 | AU24: 111.2 | AV24: 111.8 | AW24: 111 | AX24: 111.5 | AY24: 112.1 | AZ24: 111.2 | BA24: 111.8 | BB24: 112.8 | BC24: 111.4 | BD24: 112.3 | BE24: 113.4 | BF24: 111.5 | BG24: 112.7 | BH24: 114 | BI24: 112.2 | BJ24: 113.3 | BK24: 114.5 | BL24: 112.3 | BM24: 113.7 | BN24: 115.3 | BO24: 112.6 | BP24: 114.3 | BQ24: 115.9 | BR24: 113 | BS24: 114.8 | BT24: 116.2 | BU24: 113.2 | BV24: 115.1 | BW24: 116.6 | BX24: 113.7 | BY24: 115.5 | BZ24: 117.7 | CA24: 114.1 | CB24: 116.3 | CC24: 118.2 | CD24: 114.3 | CE24: 116.7 | CF24: 118.6 | CG24: 114.6 | CH24: 117.1 | CI24: 119.4 | CJ24: 114.9 | CK24: 117.7 | CL24: 120.4 | CM24: 115.4 | CN24: 118.5 | CO24: 120.8 | CP24: 116 | CQ24: 119 | CR24: 121.1 | CS24: 116.6 | CT24: 119.4 | CU24: 121.4 | CV24: 117.1 | CW24: 119.8 | CX24: 122 | CY24: 117.7 | CZ24: 120.4 | DA24: 122.6 | DB24: 118.1 | DC24: 120.9 | DD24: 123.1 | DE24: 118.6 | DF24: 121.4 | DG24: 123.7 | DH24: 119.1 | DI24: 122 | DJ24: 124.3 | DK24: 119.5 | DL24: 122.5 | DM24: 124.8 | DN24: 119.7 | DO24: 122.9 | DP24: 125.2 | DQ24: 120 | DR24: 123.2 | DS24: 125.8 | DT24: 120.3 | DU24: 123.7 | DV24: 126.2 | DW24: 120.6 | DX24: 124.1 | DY24: 126.7 | DZ24: 120.9 | EA24: 124.5 | EB24: 127 | EC24: 121.2 | ED24: 124.8 | EE24: 127.8 | EF24: 121.4 | EG24: 125.4 | EH24: 128.7 | EI24: 121.8 | EJ24: 126.1 | EK24: 129.1 | EL24: 122.1 | EM24: 126.4 | EN24: 129.7 | EO24: 122.3 | EP24: 126.9 | EQ24: 129.9 | ER24: 122.6 | ES24: 127.1 | ET24: 130.1 | EU24: 122.9 | EV24: 127.4 | EW24: 130.6 | EX24: 123.1 | EY24: 127.8 | EZ24: 131 | FA24: 123.4 | FB24: 128.1 | FC24: 131.4 | FD24: 123.6 | FE24: 128.4 | FF24: 131.3 | FG24: 123.8 | FH24: 128.5 | FI24: 132.1 | FJ24: 125 | FK24: 129.4 | FL24: 133 | FM24: 125.7 | FN24: 130.2 | FO24: 133.4 | FP24: 126.1 | FQ24: 130.6 | FR24: 134.2 | FS24: 126.6 | FT24: 131.3 | FU24: 135.8 | FV24: 127.4 | FW24: 132.6 | FX24: 136.1 | FY24: 128.2 | FZ24: 133.1 | GA24: 136 | GB24: 129 | GC24: 133.3 | GD24: 136.2 | GE24: 129.8 | GF24: 133.8 | GG24: 136.7 | GH24: 130.5 | GI24: 134.3 | GJ24: 137.6 | GK24: 131.3 | GL24: 135.2 | GM24: 138.4 | GN24: 132 | GO24: 136 | GP24: 138.4 | GQ24: 132.6 | GR24: 136.2 | GS24: 139 | GT24: 133.6 | GU24: 137 | GV24: 139.4 | GW24: 134.9 | GX24: 137.7 | GY24: 140 | GZ24: 135.7 | HA24: 138.4 | HB24: 144.8 | HC24: 136.2 | HD24: 142.1 | HE24: 145.4 | HF24: 136.8 | HG24: 142.1 | HH24: 149.6 | HI24: 137.3 | HJ24: 144.9 | HK24: 149.6 | HL24: 137.8 | HM24: 145.1 | HN24: 149.9 | HO24: 138.5 | HP24: 145.6 | HQ24: 150.4 | HR24: 139.2 | HS24: 146.2 | HT24: 151.3 | HU24: 139.8 | HV24: 146.9 | HW24: 151.7 | HX24: 140.3 | HY24: 147.4 | HZ24: 152.2 | IA24: 140.8 | IB24: 147.9 | IC24: 152.7 | ID24: 141.5 | IE24: 148.5 | IF24: 153.4 | IG24: 141.9 | IH24: 149 | II24: 153.7 | IJ24: 142.4 | IK24: 149.4 | IL24: 154.3 | IM24: 142.8 | IN24: 149.9 | IO24: 154.8 | IP24: 143.2 | IQ24: 150.4 | IR24: 155.7 | IS24: 143.8 | IT24: 151.2 | IU24: 156.2 | IV24: 144.4 | IW24: 151.7 | IX24: 156.7 | IY24: 145 | IZ24: 152.3 | JA24: 154.3 | JB24: 144.8 | JC24: 150.7 | JD24: NA | JE24: NA | JF24: NA | JG24: 158.2 | JH24: 148.1 | JI24: 154.4 | JJ24: 158.2 | JK24: 148.1 | JL24: 154.4 | JM24: 158.8 | JN24: 148.7 | JO24: 155 | JP24: 159.1 | JQ24: 150 | JR24: 155.6 | JS24: 159.5 | JT24: 151 | JU24: 156.3 | JV24: 160.4 | JW24: 152 | JX24: 157.2 | JY24: 161.6 | JZ24: 152.9 | KA24: 158.3 | KB24: 162.5 | KC24: 154.1 | KD24: 159.3 | KE24: 164.3 | KF24: 156.3 | KG24: 161.3 | KH24: 164.6 | KI24: 156.9 | KJ24: 161.7 | KK24: 165.3 | KL24: 157.5 | KM24: 162.3 | KN24: 169.1 | KO24: 160.4 | KP24: 165.8 | KQ24: 169.7 | KR24: 160.8 | KS24: 166.3 | KT24: 170.4 | KU24: 161.5 | KV24: 167 | KW24: 171.1 | KX24: 162.8 | KY24: 168.4 | KZ24: 171.9 | LA24: 162.8 | LB24: 168.4 | LC24: 172.5 | LD24: 163.5 | LE24: 169.1 | LF24: 173.4 | LG24: 164.2 | LH24: 169.9 | LI24: 174 | LJ24: 165.1 | LK24: 170.6 | LL24: 174.7 | LM24: 166.1 | LN24: 171.4 | LO24: 175.3 | LP24: 167.2 | LQ24: 172.2 | LR24: 176 | LS24: 168.2 | LT24: 173 | LU24: 177 | LV24: 169 | LW24: 174 | LX24: 177.7 | LY24: 170.1 | LZ24: 174.8 | MA24: 178.2 | MB24: 170.9 | MC24: 175.4 | MD24: 178.8 | ME24: 171.7 | MF24: 176.1 | MG24: 179.4 | MH24: 172.6 | MI24: 176.8 | MJ24: 180.2 | MK24: 173.8 | ML24: 177.8 | MM24: 181.2 | MN24: 174.7 | MO24: 178.7 | MP24: 182.3 | MQ24: 175.8 | MR24: 179.8 | MS24: 183.5 | MT24: 177.2 | MU24: 181.1 | MV24: 184.7 | MW24: 178.5 | MX24: 182.3 | MY24: 186.6 | MZ24: 180.8 | NA24: 184.4 | NB24: 186.6 | NC24: 180.8 | ND24: 184.4 | NE24: 187.2 | NF24: 181.5 | NG24: 185 | NH24: 187.8 | NI24: 182.2 | NJ24: 185.7
A25: Transport and communication | B25: =VLOOKUP(A25, NOTES!C26:D51, 2,0) -> Social and Miscellaneous | C25: 103.3 | D25: 103.2 | E25: =SUMPRODUCT((Sheet3!$MA$1:$NJ$1="Rural+Urban")*(Sheet3!$A$4:$A$13=QUES_3!K26)*Sheet3!$MA$4:$NJ$13) -> 0 | F25: =E25/$E$31 -> 0 | G25: 104.4 | H25: 104.2 | I25: 104.6 | J25: 105.5 | K25: 105.1 | L25: 104.4 | M25: 105 | N25: 104.7 | O25: 104.1 | P25: 103.9 | Q25: 104 | R25: 105 | S25: 105.2 | T25: 105.1 | U25: 106.8 | V25: 107.3 | W25: 107.1 | X25: 107.8 | Y25: 108.1 | Z25: 108 | AA25: 109.3 | AB25: 110.4 | AC25: 109.9 | AD25: 109.3 | AE25: 109.7 | AF25: 109.5 | AG25: 109.6 | AH25: 109.5 | AI25: 109.5 | AJ25: 109.9 | AK25: 109.7 | AL25: 109.8 | AM25: 110.5 | AN25: 110.8 | AO25: 110.7 | AP25: 110.8 | AQ25: 111.3 | AR25: 111.1 | AS25: 111.2 | AT25: 111.6 | AU25: 111.4 | AV25: 111.2 | AW25: 111.2 | AX25: 111.2 | AY25: 111.4 | AZ25: 111.3 | BA25: 111.3 | BB25: 112.2 | BC25: 111.5 | BD25: 111.8 | BE25: 113.2 | BF25: 113 | BG25: 113.1 | BH25: 113.2 | BI25: 112.5 | BJ25: 112.8 | BK25: 112.8 | BL25: 111.2 | BM25: 112 | BN25: 112.6 | BO25: 111 | BP25: 111.8 | BQ25: 112 | BR25: 109.7 | BS25: 110.8 | BT25: 111.5 | BU25: 108.8 | BV25: 110.1 | BW25: 111 | BX25: 107.9 | BY25: 109.4 | BZ25: 110.9 | CA25: 106.8 | CB25: 108.7 | CC25: 111.6 | CD25: 108.4 | CE25: 109.9 | CF25: 111.9 | CG25: 108.4 | CH25: 110.1 | CI25: 113.3 | CJ25: 110.8 | CK25: 112 | CL25: 114.2 | CM25: 111.7 | CN25: 112.9 | CO25: 114.1 | CP25: 111.5 | CQ25: 112.7 | CR25: 113.6 | CS25: 109.9 | CT25: 111.7 | CU25: 113.8 | CV25: 109.1 | CW25: 111.3 | CX25: 113.8 | CY25: 109.3 | CZ25: 111.4 | DA25: 114 | DB25: 109.3 | DC25: 111.5 | DD25: 114 | DE25: 109.3 | DF25: 111.5 | DG25: 113.6 | DH25: 108.9 | DI25: 111.1 | DJ25: 113.9 | DK25: 109.1 | DL25: 111.4 | DM25: 113.6 | DN25: 108.5 | DO25: 110.9 | DP25: 114.4 | DQ25: 110 | DR25: 112.1 | DS25: 115.1 | DT25: 110.7 | DU25: 112.8 | DV25: 116.3 | DW25: 112.3 | DX25: 114.2 | DY25: 116.4 | DZ25: 111.7 | EA25: 113.9 | EB25: 116 | EC25: 110.4 | ED25: 113.1 | EE25: 117 | EF25: 111.8 | EG25: 114.3 | EH25: 117.8 | EI25: 112.8 | EJ25: 115.2 | EK25: 118.2 | EL25: 113.4 | EM25: 115.7 | EN25: 118.6 | EO25: 113.7 | EP25: 116 | EQ25: 119.1 | ER25: 115.2 | ES25: 117 | ET25: 119.5 | EU25: 115.5 | EV25: 117.4 | EW25: 119.8 | EX25: 115.6 | EY25: 117.6 | EZ25: 119.2 | FA25: 114.3 | FB25: 116.6 | FC25: 119.4 | FD25: 114.3 | FE25: 116.7 | FF25: 119.4 | FG25: 113.9 | FH25: 116.5 | FI25: 119.1 | FJ25: 113.2 | FK25: 116 | FL25: 120.3 | FM25: 114.6 | FN25: 117.3 | FO25: 121.2 | FP25: 115.7 | FQ25: 118.3 | FR25: 121 | FS25: 115 | FT25: 117.8 | FU25: 121.6 | FV25: 115.3 | FW25: 118.3 | FX25: 122 | FY25: 115.3 | FZ25: 118.5 | GA25: 122.7 | GB25: 116.3 | GC25: 119.3 | GD25: 123.3 | GE25: 117.4 | GF25: 120.2 | GG25: 124.6 | GH25: 117.8 | GI25: 121 | GJ25: 125.3 | GK25: 118.9 | GL25: 121.9 | GM25: 126.4 | GN25: 119.8 | GO25: 122.9 | GP25: 127.4 | GQ25: 120.4 | GR25: 123.7 | GS25: 127.5 | GT25: 120.1 | GU25: 123.6 | GV25: 128.3 | GW25: 120.7 | GX25: 124.3 | GY25: 129.9 | GZ25: 122.5 | HA25: 126 | HB25: 130.8 | HC25: 123.3 | HD25: 125.5 | HE25: 130.3 | HF25: 121.2 | HG25: 125.5 | HH25: 128.9 | HI25: 118.8 | HJ25: 123.6 | HK25: 128.6 | HL25: 118.6 | HM25: 123.3 | HN25: 129.2 | HO25: 119.2 | HP25: 123.9 | HQ25: 129.9 | HR25: 119.9 | HS25: 124.6 | HT25: 130.2 | HU25: 120.1 | HV25: 124.9 | HW25: 130.2 | HX25: 119.6 | HY25: 124.6 | HZ25: 131.2 | IA25: 120.6 | IB25: 125.6 | IC25: 131.4 | ID25: 120.8 | IE25: 125.8 | IF25: 131.6 | IG25: 121.2 | IH25: 126.1 | II25: 131.7 | IJ25: 121.5 | IK25: 126.3 | IL25: 132.1 | IM25: 121.7 | IN25: 126.6 | IO25: 135 | IP25: 125.2 | IQ25: 129.8 | IR25: 136.3 | IS25: 126.1 | IT25: 130.9 | IU25: 136 | IV25: 125.2 | IW25: 130.3 | IX25: 135.8 | IY25: 124.6 | IZ25: 129.9 | JA25: NA | JB25: NA | JC25: NA | JD25: NA | JE25: NA | JF25: NA | JG25: 141.4 | JH25: 129.3 | JI25: 135 | JJ25: 141.4 | JK25: 129.3 | JL25: 135 | JM25: 143.6 | JN25: 133.9 | JO25: 138.5 | JP25: 144.6 | JQ25: 135.1 | JR25: 139.6 | JS25: 146.4 | JT25: 135.4 | JU25: 140.6 | JV25: 146.1 | JW25: 135.2 | JX25: 140.4 | JY25: 146.4 | JZ25: 135.5 | KA25: 140.7 | KB25: 147.5 | KC25: 136.9 | KD25: 141.9 | KE25: 150.2 | KF25: 140.5 | KG25: 145.1 | KH25: 151.3 | KI25: 141.7 | KJ25: 146.2 | KK25: 151.7 | KL25: 142.1 | KM25: 146.6 | KN25: 153.2 | KO25: 145 | KP25: 148.9 | KQ25: 154.2 | KR25: 147.5 | KS25: 150.7 | KT25: 157.1 | KU25: 149.5 | KV25: 153.1 | KW25: 157.7 | KX25: 150.4 | KY25: 154 | KZ25: 157.8 | LA25: 150.5 | LB25: 154 | LC25: 159.5 | LD25: 152.2 | LE25: 155.7 | LF25: 158.9 | LG25: 151.2 | LH25: 154.8 | LI25: 160.1 | LJ25: 151.8 | LK25: 155.7 | LL25: 160.8 | LM25: 152.7 | LN25: 156.5 | LO25: 161.2 | LP25: 153.1 | LQ25: 156.9 | LR25: 162 | LS25: 154.2 | LT25: 157.9 | LU25: 166.2 | LV25: 159.3 | LW25: 162.6 | LX25: 167.1 | LY25: 159.4 | LZ25: 163 | MA25: 165.5 | MB25: 157.2 | MC25: 161.1 | MD25: 166.3 | ME25: 157.4 | MF25: 161.6 | MG25: 166.6 | MH25: 157.7 | MI25: 161.9 | MJ25: 166.9 | MK25: 158.2 | ML25: 162.3 | MM25: 167.4 | MN25: 158.8 | MO25: 162.9 | MP25: 167.5 | MQ25: 158.9 | MR25: 163 | MS25: 167.8 | MT25: 159.4 | MU25: 163.4 | MV25: 168.2 | MW25: 159.5 | MX25: 163.6 | MY25: 169 | MZ25: 159.8 | NA25: 164.2 | NB25: 169 | NC25: 159.8 | ND25: 164.2 | NE25: 169.4 | NF25: 160.1 | NG25: 164.5 | NH25: 169.7 | NI25: 160.4 | NJ25: 164.8
A26: Recreation and amusement | B26: =VLOOKUP(A26, NOTES!C27:D52, 2,0) -> Social and Miscellaneous | C26: 103.4 | D26: 102.9 | E26: =SUMPRODUCT((Sheet3!$MA$1:$NJ$1="Rural+Urban")*(Sheet3!$A$4:$A$13=QUES_3!K27)*Sheet3!$MA$4:$NJ$13) -> 2010.8 | F26: =E26/$E$31 -> 0.23322006 | G26: 103.3 | H26: 103.6 | I26: 104 | J26: 103.5 | K26: 103.7 | L26: 104.5 | M26: 104 | N26: 104.2 | O26: 105 | P26: 104.6 | Q26: 104.8 | R26: 105.6 | S26: 105.2 | T26: 105.4 | U26: 106.4 | V26: 105.9 | W26: 106.1 | X26: 106.8 | Y26: 106.5 | Z26: 106.6 | AA26: 107.7 | AB26: 107.4 | AC26: 107.5 | AD26: 108.3 | AE26: 108 | AF26: 108.1 | AG26: 108.7 | AH26: 108.5 | AI26: 108.6 | AJ26: 109.2 | AK26: 108.9 | AL26: 109 | AM26: 109.6 | AN26: 109.8 | AO26: 109.7 | AP26: 109.9 | AQ26: 110.3 | AR26: 110.1 | AS26: 110.2 | AT26: 110.9 | AU26: 110.6 | AV26: 110.5 | AW26: 111.2 | AX26: 110.9 | AY26: 110.9 | AZ26: 111.5 | BA26: 111.2 | BB26: 111.4 | BC26: 111.8 | BD26: 111.6 | BE26: 111.8 | BF26: 112.4 | BG26: 112.1 | BH26: 112.2 | BI26: 112.9 | BJ26: 112.6 | BK26: 112.6 | BL26: 113.4 | BM26: 113.1 | BN26: 113 | BO26: 113.6 | BP26: 113.3 | BQ26: 113.3 | BR26: 114 | BS26: 113.7 | BT26: 113.3 | BU26: 114.3 | BV26: 113.9 | BW26: 114 | BX26: 114.6 | BY26: 114.3 | BZ26: 114.8 | CA26: 114.9 | CB26: 114.9 | CC26: 115.5 | CD26: 115.4 | CE26: 115.4 | CF26: 116.2 | CG26: 115.6 | CH26: 115.9 | CI26: 116.7 | CJ26: 116 | CK26: 116.3 | CL26: 117.9 | CM26: 116.2 | CN26: 116.9 | CO26: 118 | CP26: 116.6 | CQ26: 117.2 | CR26: 118.5 | CS26: 117.2 | CT26: 117.8 | CU26: 119.6 | CV26: 117.3 | CW26: 118.3 | CX26: 120.1 | CY26: 117.7 | CZ26: 118.7 | DA26: 120.9 | DB26: 117.9 | DC26: 119.2 | DD26: 121.6 | DE26: 118.1 | DF26: 119.6 | DG26: 121.4 | DH26: 118.5 | DI26: 119.8 | DJ26: 122.3 | DK26: 118.8 | DL26: 120.3 | DM26: 122.5 | DN26: 119.1 | DO26: 120.6 | DP26: 123.2 | DQ26: 119.5 | DR26: 121.1 | DS26: 123.6 | DT26: 119.8 | DU26: 121.5 | DV26: 124.1 | DW26: 119.9 | DX26: 121.7 | DY26: 125.2 | DZ26: 120.3 | EA26: 122.4 | EB26: 125.5 | EC26: 120.6 | ED26: 122.7 | EE26: 125.7 | EF26: 120.8 | EG26: 122.9 | EH26: 126.5 | EI26: 121.2 | EJ26: 123.5 | EK26: 126.9 | EL26: 121.7 | EM26: 124 | EN26: 127.3 | EO26: 121.8 | EP26: 124.2 | EQ26: 127 | ER26: 122 | ES26: 124.2 | ET26: 127.7 | EU26: 122.2 | EV26: 124.6 | EW26: 128.3 | EX26: 122.4 | EY26: 125 | EZ26: 128.3 | FA26: 122.6 | FB26: 125.1 | FC26: 129.4 | FD26: 122.8 | FE26: 125.7 | FF26: 129.8 | FG26: 122.9 | FH26: 125.9 | FI26: 130.6 | FJ26: 123.5 | FK26: 126.6 | FL26: 131.5 | FM26: 124.1 | FN26: 127.3 | FO26: 132.3 | FP26: 124.5 | FQ26: 127.9 | FR26: 133 | FS26: 124.8 | FT26: 128.4 | FU26: 133.7 | FV26: 125.1 | FW26: 128.9 | FX26: 133.4 | FY26: 125.6 | FZ26: 129 | GA26: 134.3 | GB26: 126.2 | GC26: 129.7 | GD26: 134.3 | GE26: 126.5 | GF26: 129.9 | GG26: 135.1 | GH26: 126.8 | GI26: 130.4 | GJ26: 136 | GK26: 127.6 | GL26: 131.3 | GM26: 136.8 | GN26: 128 | GO26: 131.8 | GP26: 137.8 | GQ26: 128.5 | GR26: 132.6 | GS26: 138.4 | GT26: 129 | GU26: 133.1 | GV26: 138.6 | GW26: 129.8 | GX26: 133.6 | GY26: 140 | GZ26: 130.2 | HA26: 134.5 | HB26: 140.1 | HC26: 130.7 | HD26: 136.5 | HE26: 143.1 | HF26: 131.3 | HG26: 136.5 | HH26: 143.3 | HI26: 131.7 | HJ26: 136.8 | HK26: 142.9 | HL26: 131.9 | HM26: 136.7 | HN26: 143.4 | HO26: 132.2 | HP26: 137.1 | HQ26: 143.8 | HR26: 133 | HS26: 137.7 | HT26: 145.9 | HU26: 134 | HV26: 139.2 | HW26: 146.4 | HX26: 134.3 | HY26: 139.6 | HZ26: 147.5 | IA26: 135 | IB26: 140.5 | IC26: 148 | ID26: 135.4 | IE26: 140.9 | IF26: 148.3 | IG26: 135.9 | IH26: 141.3 | II26: 148.7 | IJ26: 136.2 | IK26: 141.7 | IL26: 149.1 | IM26: 136.7 | IN26: 142.1 | IO26: 149.5 | IP26: 136.8 | IQ26: 142.3 | IR26: 150.1 | IS26: 137.2 | IT26: 142.8 | IU26: 150.4 | IV26: 137.7 | IW26: 143.2 | IX26: 151.2 | IY26: 137.9 | IZ26: 143.7 | JA26: NA | JB26: NA | JC26: NA | JD26: NA | JE26: NA | JF26: NA | JG26: 153.2 | JH26: 144.5 | JI26: 148.3 | JJ26: 153.2 | JK26: 144.5 | JL26: 148.3 | JM26: 152.2 | JN26: 141.2 | JO26: 146 | JP26: 152.8 | JQ26: 141.8 | JR26: 146.6 | JS26: 152.4 | JT26: 142 | JU26: 146.5 | JV26: 153.6 | JW26: 144.4 | JX26: 148.4 | JY26: 153.9 | JZ26: 144.3 | KA26: 148.5 | KB26: 155.1 | KC26: 145.4 | KD26: 149.6 | KE26: 157 | KF26: 147.3 | KG26: 151.5 | KH26: 157.8 | KI26: 148.6 | KJ26: 152.6 | KK26: 158.6 | KL26: 149.1 | KM26: 153.2 | KN26: 160 | KO26: 152.6 | KP26: 155.8 | KQ26: 160.4 | KR26: 150.7 | KS26: 154.9 | KT26: 160.7 | KU26: 151.2 | KV26: 155.3 | KW26: 161.1 | KX26: 153.7 | KY26: 157.6 | KZ26: 162.7 | LA26: 153.9 | LB26: 157.7 | LC26: 163.2 | LD26: 155.1 | LE26: 158.6 | LF26: 163.8 | LG26: 156.7 | LH26: 159.8 | LI26: 164.5 | LJ26: 157.6 | LK26: 160.6 | LL26: 164.9 | LM26: 158.4 | LN26: 161.2 | LO26: 165.5 | LP26: 159.5 | LQ26: 162.1 | LR26: 166.6 | LS26: 160.8 | LT26: 163.3 | LU26: 167.2 | LV26: 162.2 | LW26: 164.4 | LX26: 167.6 | LY26: 163.2 | LZ26: 165.1 | MA26: 168 | MB26: 164.1 | MC26: 165.8 | MD26: 168.6 | ME26: 164.6 | MF26: 166.3 | MG26: 169.3 | MH26: 165.1 | MI26: 166.9 | MJ26: 170 | MK26: 165.8 | ML26: 167.6 | MM26: 170.6 | MN26: 166.3 | MO26: 168.2 | MP26: 170.8 | MQ26: 166.7 | MR26: 168.5 | MS26: 171.2 | MT26: 167.1 | MU26: 168.9 | MV26: 171.8 | MW26: 167.8 | MX26: 169.5 | MY26: 172.8 | MZ26: 168.4 | NA26: 170.3 | NB26: 172.8 | NC26: 168.4 | ND26: 170.3 | NE26: 173.2 | NF26: 168.8 | NG26: 170.7 | NH26: 173.8 | NI26: 169.2 | NJ26: 171.2
A27: Education | B27: =VLOOKUP(A27, NOTES!C28:D53, 2,0) -> Social and Miscellaneous | C27: 103.8 | D27: 103.5 | E27: =SUMPRODUCT((Sheet3!$MA$1:$NJ$1="Rural+Urban")*(Sheet3!$A$4:$A$13=QUES_3!K28)*Sheet3!$MA$4:$NJ$13) -> 2061.4 | F27: =E27/$E$31 -> 0.23908883 | G27: 103.7 | H27: 103.9 | I27: 104.3 | J27: 103.8 | K27: 104 | L27: 104.8 | M27: 105.2 | N27: 105 | O27: 105.5 | P27: 105.7 | Q27: 105.6 | R27: 106.5 | S27: 108.1 | T27: 107.4 | U27: 107.8 | V27: 110.1 | W27: 109.1 | X27: 108.7 | Y27: 110.8 | Z27: 109.9 | AA27: 109.8 | AB27: 111.2 | AC27: 110.6 | AD27: 110.2 | AE27: 111.3 | AF27: 110.8 | AG27: 111 | AH27: 111.3 | AI27: 111.2 | AJ27: 111.6 | AK27: 111.4 | AL27: 111.5 | AM27: 111.8 | AN27: 111.5 | AO27: 111.6 | AP27: 112 | AQ27: 111.6 | AR27: 111.8 | AS27: 112.4 | AT27: 111.8 | AU27: 112 | AV27: 113 | AW27: 112.5 | AX27: 112.7 | AY27: 113.1 | AZ27: 112.9 | BA27: 113 | BB27: 114.3 | BC27: 115.1 | BD27: 114.8 | BE27: 115.5 | BF27: 117.8 | BG27: 116.8 | BH27: 116.2 | BI27: 119.2 | BJ27: 118 | BK27: 116.6 | BL27: 120 | BM27: 118.6 | BN27: 116.9 | BO27: 120.2 | BP27: 118.8 | BQ27: 117.2 | BR27: 120.3 | BS27: 119 | BT27: 117.7 | BU27: 120.7 | BV27: 119.5 | BW27: 118.2 | BX27: 120.8 | BY27: 119.7 | BZ27: 118.7 | CA27: 120.4 | CB27: 119.7 | CC27: 119.4 | CD27: 120.6 | CE27: 120.1 | CF27: 119.9 | CG27: 121.7 | CH27: 121 | CI27: 120.5 | CJ27: 122 | CK27: 121.4 | CL27: 122 | CM27: 123.8 | CN27: 123.1 | CO27: 122.9 | CP27: 125.4 | CQ27: 124.4 | CR27: 123.6 | CS27: 126.2 | CT27: 125.1 | CU27: 124.5 | CV27: 126.5 | CW27: 125.7 | CX27: 125.1 | CY27: 126.5 | CZ27: 125.9 | DA27: 125.8 | DB27: 126.6 | DC27: 126.3 | DD27: 125.6 | DE27: 126.6 | DF27: 126.2 | DG27: 126.2 | DH27: 126.4 | DI27: 126.3 | DJ27: 127.1 | DK27: 126.3 | DL27: 126.6 | DM27: 127.5 | DN27: 126.4 | DO27: 126.9 | DP27: 127.9 | DQ27: 127.6 | DR27: 127.7 | DS27: 129.1 | DT27: 128 | DU27: 128.5 | DV27: 130.2 | DW27: 129.3 | DX27: 129.7 | DY27: 130.8 | DZ27: 130.8 | EA27: 130.8 | EB27: 131.9 | EC27: 131.5 | ED27: 131.7 | EE27: 132.2 | EF27: 131.6 | EG27: 131.8 | EH27: 133 | EI27: 131.9 | EJ27: 132.4 | EK27: 133.7 | EL27: 132.1 | EM27: 132.8 | EN27: 134.2 | EO27: 132.3 | EP27: 133.1 | EQ27: 134.6 | ER27: 132.4 | ES27: 133.3 | ET27: 134.9 | EU27: 132.4 | EV27: 133.4 | EW27: 135.2 | EX27: 132.8 | EY27: 133.8 | EZ27: 135.7 | FA27: 133.6 | FB27: 134.5 | FC27: 136.3 | FD27: 133.8 | FE27: 134.8 | FF27: 136.9 | FG27: 134.3 | FH27: 135.4 | FI27: 138.6 | FJ27: 135.5 | FK27: 136.8 | FL27: 140.2 | FM27: 135.7 | FN27: 137.6 | FO27: 139.6 | FP27: 135.9 | FQ27: 137.4 | FR27: 140.1 | FS27: 136.3 | FT27: 137.9 | FU27: 141.5 | FV27: 136.6 | FW27: 138.6 | FX27: 141.1 | FY27: 136.7 | FZ27: 138.5 | GA27: 141.6 | GB27: 137.1 | GC27: 139 | GD27: 141.5 | GE27: 137.2 | GF27: 139 | GG27: 142.7 | GH27: 137.8 | GI27: 139.8 | GJ27: 143.7 | GK27: 139.7 | GL27: 141.4 | GM27: 144.4 | GN27: 140.4 | GO27: 142.1 | GP27: 145.1 | GQ27: 141.2 | GR27: 142.8 | GS27: 145.8 | GT27: 144 | GU27: 144.7 | GV27: 146.9 | GW27: 145.3 | GX27: 146 | GY27: 147.6 | GZ27: 145.2 | HA27: 146.2 | HB27: 148 | HC27: 145.5 | HD27: 147.8 | HE27: 150.2 | HF27: 146.1 | HG27: 147.8 | HH27: 155.1 | HI27: 146.5 | HJ27: 150.1 | HK27: 155.2 | HL27: 146.6 | HM27: 150.2 | HN27: 155.5 | HO27: 146.6 | HP27: 150.3 | HQ27: 155.5 | HR27: 146.7 | HS27: 150.3 | HT27: 156.7 | HU27: 148 | HV27: 151.6 | HW27: 157.7 | HX27: 148.9 | HY27: 152.5 | HZ27: 159.1 | IA27: 150.4 | IB27: 154 | IC27: 159.7 | ID27: 151.5 | IE27: 154.9 | IF27: 160.2 | IG27: 151.6 | IH27: 155.2 | II27: 160.7 | IJ27: 151.7 | IK27: 155.4 | IL27: 160.8 | IM27: 151.8 | IN27: 155.5 | IO27: 161.1 | IP27: 151.9 | IQ27: 155.7 | IR27: 161.7 | IS27: 152.1 | IT27: 156.1 | IU27: 161.9 | IV27: 152.2 | IW27: 156.2 | IX27: 161.2 | IY27: 152.5 | IZ27: 156.1 | JA27: NA | JB27: NA | JC27: NA | JD27: NA | JE27: NA | JF27: NA | JG27: 161.8 | JH27: 152.5 | JI27: 156.4 | JJ27: 161.8 | JK27: 152.5 | JL27: 156.4 | JM27: 162.7 | JN27: 155.5 | JO27: 158.5 | JP27: 161.1 | JQ27: 154.9 | JR27: 157.5 | JS27: 162.5 | JT27: 155.7 | JU27: 158.5 | JV27: 161.6 | JW27: 156.4 | JX27: 158.6 | JY27: 162.9 | JZ27: 156.9 | KA27: 159.4 | KB27: 163.5 | KC27: 156.1 | KD27: 159.2 | KE27: 163.6 | KF27: 156.6 | KG27: 159.5 | KH27: 163.8 | KI27: 157.6 | KJ27: 160.2 | KK27: 164.1 | KL27: 157.6 | KM27: 160.3 | KN27: 167.6 | KO27: 156.6 | KP27: 161.2 | KQ27: 166.8 | KR27: 158.1 | KS27: 161.7 | KT27: 167.2 | KU27: 160.3 | KV27: 163.2 | KW27: 167.5 | KX27: 160.4 | KY27: 163.8 | KZ27: 168.5 | LA27: 160.3 | LB27: 163.7 | LC27: 169 | LD27: 160.3 | LE27: 163.9 | LF27: 169.3 | LG27: 160.8 | LH27: 164.3 | LI27: 169.7 | LJ27: 160.6 | LK27: 164.4 | LL27: 169.9 | LM27: 161 | LN27: 164.7 | LO27: 170.3 | LP27: 162 | LQ27: 165.4 | LR27: 170.6 | LS27: 162.7 | LT27: 166 | LU27: 170.9 | LV27: 164 | LW27: 166.9 | LX27: 171.8 | LY27: 165.2 | LZ27: 167.9 | MA27: 172.6 | MB27: 166.5 | MC27: 169 | MD27: 174.7 | ME27: 169.1 | MF27: 171.4 | MG27: 175.7 | MH27: 169.9 | MI27: 172.3 | MJ27: 176.2 | MK27: 170.9 | ML27: 173.1 | MM27: 176.5 | MN27: 171.2 | MO27: 173.4 | MP27: 176.9 | MQ27: 171.5 | MR27: 173.7 | MS27: 177.3 | MT27: 171.8 | MU27: 174.1 | MV27: 177.8 | MW27: 171.8 | MX27: 174.3 | MY27: 178.5 | MZ27: 172.5 | NA27: 175 | NB27: 178.5 | NC27: 172.5 | ND27: 175 | NE27: 179.4 | NF27: 174.2 | NG27: 176.4 | NH27: 180.3 | NI27: 174.8 | NJ27: 177.1
A28: Personal care and effects | B28: Goods, Services and Transport | C28: 104.7 | D28: 104.3 | F28: =E28/$E$31 -> 0 | G28: 104.3 | H28: 104.5 | I28: 104.3 | J28: 104.2 | K28: 104.3 | L28: 102.7 | M28: 103.2 | N28: 102.9 | O28: 102.1 | P28: 102.6 | Q28: 102.3 | R28: 102.5 | S28: 103.3 | T28: 102.8 | U28: 102.5 | V28: 103.2 | W28: 102.8 | X28: 105 | Y28: 106 | Z28: 105.4 | AA28: 106.7 | AB28: 106.9 | AC28: 106.8 | AD28: 107.5 | AE28: 107.3 | AF28: 107.4 | AG28: 108.2 | AH28: 107.9 | AI28: 108.1 | AJ28: 108.1 | AK28: 107.7 | AL28: 107.9 | AM28: 108.3 | AN28: 108 | AO28: 108.2 | AP28: 108.7 | AQ28: 108.7 | AR28: 108.7 | AS28: 108.9 | AT28: 109.2 | AU28: 109 | AV28: 108.9 | AW28: 109.1 | AX28: 109 | AY28: 108.9 | AZ28: 109.3 | BA28: 109.1 | BB28: 108 | BC28: 108.7 | BD28: 108.3 | BE28: 108.8 | BF28: 109.7 | BG28: 109.2 | BH28: 109.4 | BI28: 110.5 | BJ28: 109.9 | BK28: 109.1 | BL28: 110 | BM28: 109.5 | BN28: 109.3 | BO28: 110.1 | BP28: 109.6 | BQ28: 108.8 | BR28: 109.6 | BS28: 109.1 | BT28: 109.4 | BU28: 110.4 | BV28: 109.8 | BW28: 110.2 | BX28: 111.4 | BY28: 110.7 | BZ28: 110.8 | CA28: 111.7 | CB28: 111.2 | CC28: 110.8 | CD28: 111.3 | CE28: 111 | CF28: 111.6 | CG28: 111.8 | CH28: 111.7 | CI28: 112.3 | CJ28: 112.4 | CK28: 112.3 | CL28: 113 | CM28: 112.5 | CN28: 112.8 | CO28: 112.7 | CP28: 111.7 | CQ28: 112.3 | CR28: 112.5 | CS28: 112 | CT28: 112.3 | CU28: 113.7 | CV28: 112.9 | CW28: 113.4 | CX28: 114.2 | CY28: 113.5 | CZ28: 113.9 | DA28: 114.2 | DB28: 113.3 | DC28: 113.8 | DD28: 114.1 | DE28: 113.2 | DF28: 113.7 | DG28: 114.9 | DH28: 114 | DI28: 114.5 | DJ28: 116.8 | DK28: 116.2 | DL28: 116.6 | DM28: 117.4 | DN28: 117.1 | DO28: 117.3 | DP28: 118.4 | DQ28: 117.6 | DR28: 118.1 | DS28: 119.7 | DT28: 118.5 | DU28: 119.2 | DV28: 119.9 | DW28: 118.8 | DX28: 119.4 | DY28: 120.9 | DZ28: 120 | EA28: 120.5 | EB28: 122 | EC28: 120.9 | ED28: 121.5 | EE28: 122.8 | EF28: 121.2 | EG28: 122.1 | EH28: 123 | EI28: 120.8 | EJ28: 122.1 | EK28: 123.5 | EL28: 121.3 | EM28: 122.6 | EN28: 121.9 | EO28: 119.9 | EP28: 121.1 | EQ28: 122.3 | ER28: 120.9 | ES28: 121.7 | ET28: 123.2 | EU28: 121.7 | EV28: 122.6 | EW28: 123.3 | EX28: 121.7 | EY28: 122.6 | EZ28: 123.7 | FA28: 122.2 | FB28: 123.1 | FC28: 123.7 | FD28: 122 | FE28: 123 | FF28: 124.1 | FG28: 122.5 | FH28: 123.4 | FI28: 124.4 | FJ28: 122.4 | FK28: 123.6 | FL28: 125.4 | FM28: 123.3 | FN28: 124.5 | FO28: 126.7 | FP28: 124.4 | FQ28: 125.7 | FR28: 127.4 | FS28: 124.6 | FT28: 126.2 | FU28: 128.1 | FV28: 124.9 | FW28: 126.8 | FX28: 127.8 | FY28: 124.6 | FZ28: 126.5 | GA28: 128.6 | GB28: 125.5 | GC28: 127.3 | GD28: 128.8 | GE28: 126.2 | GF28: 127.7 | GG28: 129.3 | GH28: 126.7 | GI28: 128.2 | GJ28: 130.4 | GK28: 127.6 | GL28: 129.2 | GM28: 131.2 | GN28: 128.1 | GO28: 129.9 | GP28: 131.4 | GQ28: 128.2 | GR28: 130.1 | GS28: 131.4 | GT28: 128.2 | GU28: 130.1 | GV28: 131.3 | GW28: 128.3 | GX28: 130.1 | GY28: 132 | GZ28: 129.3 | HA28: 130.9 | HB28: 134.4 | HC28: 130.4 | HD28: 132 | HE28: 133.1 | HF28: 130.5 | HG28: 132 | HH28: 133.2 | HI28: 130.8 | HJ28: 132.2 | HK28: 133.5 | HL28: 131.7 | HM28: 132.8 | HN28: 134.9 | HO28: 133 | HP28: 134.1 | HQ28: 134 | HR28: 132.5 | HS28: 133.4 | HT28: 133.9 | HU28: 132.6 | HV28: 133.4 | HW28: 134.8 | HX28: 133.7 | HY28: 134.3 | HZ28: 136.1 | IA28: 135.1 | IB28: 135.7 | IC28: 138.8 | ID28: 137.8 | IE28: 138.4 | IF28: 140.2 | IG28: 139 | IH28: 139.7 | II28: 140.3 | IJ28: 139.5 | IK28: 140 | IL28: 140.6 | IM28: 139.8 | IN28: 140.3 | IO28: 140.6 | IP28: 140.2 | IQ28: 140.4 | IR28: 142.5 | IS28: 142.1 | IT28: 142.3 | IU28: 143.4 | IV28: 143.5 | IW28: 143.4 | IX28: 145.1 | IY28: 145.3 | IZ28: 145.2 | JA28: NA | JB28: NA | JC28: NA | JD28: NA | JE28: NA | JF28: NA | JG28: 151.2 | JH28: 152.2 | JI28: 151.6 | JJ28: 151.2 | JK28: 152.2 | JL28: 151.6 | JM28: 153.6 | JN28: 155.2 | JO28: 154.3 | JP28: 157.4 | JQ28: 159.8 | JR28: 158.4 | JS28: 156.2 | JT28: 158.1 | JU28: 157 | JV28: 156.2 | JW28: 157.9 | JX28: 156.9 | JY28: 156.6 | JZ28: 157.9 | KA28: 157.1 | KB28: 156.2 | KC28: 157.7 | KD28: 156.8 | KE28: 155.2 | KF28: 156.7 | KG28: 155.8 | KH28: 153.1 | KI28: 154.9 | KJ28: 153.8 | KK28: 154.6 | KL28: 156.6 | KM28: 155.4 | KN28: 159.3 | KO28: 157.5 | KP28: 158.6 | KQ28: 159.4 | KR28: 158 | KS28: 158.8 | KT28: 160.4 | KU28: 159.6 | KV28: 160.1 | KW28: 160.3 | KX28: 159.6 | KY28: 160 | KZ28: 160.2 | LA28: 159.6 | LB28: 160 | LC28: 161.1 | LD28: 160.3 | LE28: 160.8 | LF28: 162.4 | LG28: 161.8 | LH28: 162.2 | LI28: 162.8 | LJ28: 162.4 | LK28: 162.6 | LL28: 163.2 | LM28: 162.8 | LN28: 163 | LO28: 164.5 | LP28: 164.2 | LQ28: 164.4 | LR28: 167.4 | LS28: 166.8 | LT28: 167.2 | LU28: 169 | LV28: 168.4 | LW28: 168.8 | LX28: 168.5 | LY28: 168.2 | LZ28: 168.4 | MA28: 169.5 | MB28: 169.2 | MC28: 169.4 | MD28: 169.7 | ME28: 169.8 | MF28: 169.7 | MG28: 171.1 | MH28: 171.4 | MI28: 171.2 | MJ28: 170.8 | MK28: 171.1 | ML28: 170.9 | MM28: 172 | MN28: 172.3 | MO28: 172.1 | MP28: 173.4 | MQ28: 173.8 | MR28: 173.6 | MS28: 175.7 | MT28: 176 | MU28: 175.8 | MV28: 178.4 | MW28: 178.8 | MX28: 178.6 | MY28: 180.7 | MZ28: 181.4 | NA28: 181 | NB28: 180.7 | NC28: 181.5 | ND28: 181 | NE28: 183.8 | NF28: 184.4 | NG28: 184 | NH28: 184.9 | NI28: 185.6 | NJ28: 185.2
A29: Miscellaneous | B29: =VLOOKUP(A29, NOTES!C30:D55, 2,0) -> Social and Miscellaneous | C29: 104 | D29: 103.7 | E29: =SUMPRODUCT((Sheet3!$MA$1:$NJ$1="Rural+Urban")*(Sheet3!$A$4:$A$13=QUES_3!K30)*Sheet3!$MA$4:$NJ$13) -> 0 | F29: =E29/$E$31 -> 0 | G29: 104.3 | H29: 104.4 | I29: 104.6 | J29: 104.9 | K29: 104.7 | L29: 104.6 | M29: 105.1 | N29: 104.8 | O29: 104.8 | P29: 104.9 | Q29: 104.8 | R29: 105.5 | S29: 106.1 | T29: 105.8 | U29: 106.5 | V29: 107.3 | W29: 106.9 | X29: 107.5 | Y29: 108.3 | Z29: 107.9 | AA29: 108.7 | AB29: 109.4 | AC29: 109 | AD29: 109.1 | AE29: 109.4 | AF29: 109.2 | AG29: 109.8 | AH29: 109.6 | AI29: 109.7 | AJ29: 110.1 | AK29: 109.8 | AL29: 110 | AM29: 110.6 | AN29: 110.5 | AO29: 110.6 | AP29: 110.9 | AQ29: 111 | AR29: 110.9 | AS29: 111.3 | AT29: 111.4 | AU29: 111.3 | AV29: 111.5 | AW29: 111.4 | AX29: 111.5 | AY29: 111.8 | AZ29: 111.7 | BA29: 111.8 | BB29: 112.3 | BC29: 112.2 | BD29: 112.3 | BE29: 113.1 | BF29: 113.5 | BG29: 113.3 | BH29: 113.5 | BI29: 113.9 | BJ29: 113.7 | BK29: 113.7 | BL29: 113.6 | BM29: 113.7 | BN29: 114 | BO29: 113.7 | BP29: 113.9 | BQ29: 114.1 | BR29: 113.4 | BS29: 113.8 | BT29: 114.2 | BU29: 113.4 | BV29: 113.8 | BW29: 114.5 | BX29: 113.4 | BY29: 114 | BZ29: 115 | CA29: 113.2 | CB29: 114.1 | CC29: 115.5 | CD29: 113.8 | CE29: 114.7 | CF29: 116 | CG29: 114.2 | CH29: 115.1 | CI29: 116.9 | CJ29: 115.2 | CK29: 116.1 | CL29: 117.9 | CM29: 116 | CN29: 117 | CO29: 118.1 | CP29: 116.3 | CQ29: 117.2 | CR29: 118.2 | CS29: 116.2 | CT29: 117.2 | CU29: 118.8 | CV29: 116.2 | CW29: 117.5 | CX29: 119.2 | CY29: 116.5 | CZ29: 117.9 | DA29: 119.6 | DB29: 116.6 | DC29: 118.1 | DD29: 119.8 | DE29: 116.7 | DF29: 118.3 | DG29: 120.1 | DH29: 116.8 | DI29: 118.5 | DJ29: 120.9 | DK29: 117.2 | DL29: 119.1 | DM29: 121.1 | DN29: 117.3 | DO29: 119.3 | DP29: 121.7 | DQ29: 118.2 | DR29: 120 | DS29: 122.5 | DT29: 118.7 | DU29: 120.7 | DV29: 123.3 | DW29: 119.6 | DX29: 121.5 | DY29: 123.8 | DZ29: 119.9 | EA29: 121.9 | EB29: 124.2 | EC29: 119.9 | ED29: 122.1 | EE29: 124.9 | EF29: 120.5 | EG29: 122.8 | EH29: 125.7 | EI29: 120.9 | EJ29: 123.4 | EK29: 126.1 | EL29: 121.3 | EM29: 123.8 | EN29: 126.3 | EO29: 121.4 | EP29: 123.9 | EQ29: 126.6 | ER29: 122.1 | ES29: 124.4 | ET29: 127 | EU29: 122.4 | EV29: 124.8 | EW29: 127.4 | EX29: 122.6 | EY29: 125.1 | EZ29: 127.5 | FA29: 122.5 | FB29: 125.1 | FC29: 127.9 | FD29: 122.6 | FE29: 125.3 | FF29: 128.1 | FG29: 122.7 | FH29: 125.5 | FI29: 128.6 | FJ29: 123 | FK29: 125.9 | FL29: 129.7 | FM29: 123.8 | FN29: 126.8 | FO29: 130.3 | FP29: 124.5 | FQ29: 127.5 | FR29: 130.7 | FS29: 124.5 | FT29: 127.7 | FU29: 131.7 | FV29: 124.9 | FW29: 128.4 | FX29: 131.9 | FY29: 125.1 | FZ29: 128.6 | GA29: 132.3 | GB29: 125.8 | GC29: 129.1 | GD29: 132.5 | GE29: 126.5 | GF29: 129.6 | GG29: 133.3 | GH29: 127.1 | GI29: 130.3 | GJ29: 134.2 | GK29: 128.2 | GL29: 131.3 | GM29: 135.1 | GN29: 128.9 | GO29: 132.1 | GP29: 135.6 | GQ29: 129.5 | GR29: 132.6 | GS29: 136 | GT29: 130.2 | GU29: 133.2 | GV29: 136.6 | GW29: 131 | GX29: 133.9 | GY29: 137.4 | GZ29: 131.9 | HA29: 134.7 | HB29: 139.8 | HC29: 132.5 | HD29: 136.3 | HE29: 140.1 | HF29: 132.2 | HG29: 136.3 | HH29: 141.6 | HI29: 131.7 | HJ29: 136.8 | HK29: 141.7 | HL29: 131.8 | HM29: 136.9 | HN29: 142.2 | HO29: 132.4 | HP29: 137.4 | HQ29: 142.4 | HR29: 132.8 | HS29: 137.7 | HT29: 142.9 | HU29: 133.3 | HV29: 138.2 | HW29: 143.3 | HX29: 133.6 | HY29: 138.6 | HZ29: 144.2 | IA29: 134.5 | IB29: 139.5 | IC29: 144.9 | ID29: 135.3 | IE29: 140.2 | IF29: 145.4 | IG29: 135.7 | IH29: 140.7 | II29: 145.7 | IJ29: 136 | IK29: 141 | IL29: 146.1 | IM29: 136.3 | IN29: 141.3 | IO29: 147.1 | IP29: 137.7 | IQ29: 142.5 | IR29: 148.1 | IS29: 138.4 | IT29: 143.4 | IU29: 148.4 | IV29: 138.4 | IW29: 143.6 | IX29: 148.6 | IY29: 138.7 | IZ29: 143.8 | JA29: NA | JB29: NA | JC29: NA | JD29: NA | JE29: NA | JF29: NA | JG29: 151.7 | JH29: 142 | JI29: 147 | JJ29: 151.7 | JK29: 142 | JL29: 147 | JM29: 153 | JN29: 144.8 | JO29: 149 | JP29: 153.7 | JQ29: 146 | JR29: 150 | JS29: 154.3 | JT29: 146.2 | JU29: 150.4 | JV29: 154.5 | JW29: 146.6 | JX29: 150.7 | JY29: 155.2 | JZ29: 146.9 | KA29: 151.2 | KB29: 155.9 | KC29: 147.6 | KD29: 151.9 | KE29: 157.2 | KF29: 149.3 | KG29: 153.4 | KH29: 157.3 | KI29: 150 | KJ29: 153.8 | KK29: 158 | KL29: 150.5 | KM29: 154.4 | KN29: 161.1 | KO29: 152.3 | KP29: 156.8 | KQ29: 161.5 | KR29: 153.4 | KS29: 157.6 | KT29: 162.8 | KU29: 155 | KV29: 159 | KW29: 163.3 | KX29: 156 | KY29: 160 | KZ29: 163.8 | LA29: 156 | LB29: 160 | LC29: 164.7 | LD29: 157 | LE29: 161 | LF29: 165.2 | LG29: 157.3 | LH29: 161.4 | LI29: 166 | LJ29: 157.8 | LK29: 162 | LL29: 166.6 | LM29: 158.6 | LN29: 162.7 | LO29: 167.3 | LP29: 159.4 | LQ29: 163.5 | LR29: 168.3 | LS29: 160.6 | LT29: 164.6 | LU29: 170.2 | LV29: 163.1 | LW29: 166.8 | LX29: 170.9 | LY29: 163.8 | LZ29: 167.5 | MA29: 171 | MB29: 163.8 | MC29: 167.5 | MD29: 171.8 | ME29: 164.7 | MF29: 168.4 | MG29: 172.6 | MH29: 165.4 | MI29: 169.1 | MJ29: 173.1 | MK29: 166.1 | ML29: 169.7 | MM29: 173.9 | MN29: 166.8 | MO29: 170.5 | MP29: 174.6 | MQ29: 167.4 | MR29: 171.1 | MS29: 175.5 | MT29: 168.2 | MU29: 172 | MV29: 176.5 | MW29: 168.9 | MX29: 172.8 | MY29: 177.9 | MZ29: 170 | NA29: 174.1 | NB29: 177.9 | NC29: 170 | ND29: 174.1 | NE29: 178.9 | NF29: 170.9 | NG29: 175 | NH29: 179.5 | NI29: 171.6 | NJ29: 175.7
A30: General index | C30: 105.1 | D30: 104 | E30: =SUMPRODUCT((Sheet3!$MA$1:$NJ$1="Rural+Urban")*(Sheet3!$A$4:$A$13=QUES_3!K31)*Sheet3!$MA$4:$NJ$13) -> 2434.6 | F30: =E30/$E$31 -> 0.28237395 | G30: 104.7 | H30: 105.3 | I30: 106 | J30: 105 | K30: 105.5 | L30: 106.4 | M30: 105.7 | N30: 106.1 | O30: 107.2 | P30: 106.6 | Q30: 106.9 | R30: 108.9 | S30: 109.7 | T30: 109.3 | U30: 110.7 | V30: 111.4 | W30: 111 | X30: 112.1 | Y30: 112.7 | Z30: 112.4 | AA30: 114.2 | AB30: 113.2 | AC30: 113.7 | AD30: 115.5 | AE30: 114 | AF30: 114.8 | AG30: 117.4 | AH30: 115 | AI30: 116.3 | AJ30: 115.5 | AK30: 113.3 | AL30: 114.5 | AM30: 114.2 | AN30: 112.9 | AO30: 113.6 | AP30: 114 | AQ30: 113.1 | AR30: 113.6 | AS30: 114.6 | AT30: 113.7 | AU30: 114.2 | AV30: 115.4 | AW30: 114.7 | AX30: 115.1 | AY30: 116 | AZ30: 115.6 | BA30: 115.8 | BB30: 117 | BC30: 116.4 | BD30: 116.7 | BE30: 119.5 | BF30: 118.9 | BG30: 119.2 | BH30: 120.7 | BI30: 119.9 | BJ30: 120.3 | BK30: 120.9 | BL30: 119.2 | BM30: 120.1 | BN30: 121 | BO30: 119.1 | BP30: 120.1 | BQ30: 121.1 | BR30: 119 | BS30: 120.1 | BT30: 120.3 | BU30: 118.4 | BV30: 119.4 | BW30: 120.3 | BX30: 118.5 | BY30: 119.5 | BZ30: 120.6 | CA30: 118.7 | CB30: 119.7 | CC30: 121.1 | CD30: 119.1 | CE30: 120.2 | CF30: 121.5 | CG30: 119.7 | CH30: 120.7 | CI30: 122.4 | CJ30: 120.7 | CK30: 121.6 | CL30: 124.1 | CM30: 121.7 | CN30: 123 | CO30: 124.7 | CP30: 122.4 | CQ30: 123.6 | CR30: 126.1 | CS30: 123.2 | CT30: 124.8 | CU30: 127 | CV30: 123.5 | CW30: 125.4 | CX30: 127.7 | CY30: 124.2 | CZ30: 126.1 | DA30: 128.3 | DB30: 124.6 | DC30: 126.6 | DD30: 127.9 | DE30: 124 | DF30: 126.1 | DG30: 128.1 | DH30: 124.2 | DI30: 126.3 | DJ30: 127.9 | DK30: 123.8 | DL30: 126 | DM30: 128 | DN30: 123.8 | DO30: 126 | DP30: 129 | DQ30: 125.3 | DR30: 127.3 | DS30: 130.3 | DT30: 126.6 | DU30: 128.6 | DV30: 131.9 | DW30: 128.1 | DX30: 130.1 | DY30: 133 | DZ30: 129 | EA30: 131.1 | EB30: 133.5 | EC30: 128.4 | ED30: 131.1 | EE30: 133.4 | EF30: 128 | EG30: 130.9 | EH30: 133.8 | EI30: 128.6 | EJ30: 131.4 | EK30: 133.6 | EL30: 128.5 | EM30: 131.2 | EN30: 132.8 | EO30: 127.6 | EP30: 130.4 | EQ30: 132.4 | ER30: 127.8 | ES30: 130.3 | ET30: 132.6 | EU30: 128.2 | EV30: 130.6 | EW30: 132.8 | EX30: 128.7 | EY30: 130.9 | EZ30: 132.9 | FA30: 129.1 | FB30: 131.1 | FC30: 133.3 | FD30: 129.3 | FE30: 131.4 | FF30: 133.9 | FG30: 129.9 | FH30: 132 | FI30: 136.2 | FJ30: 131.8 | FK30: 134.2 | FL30: 137.8 | FM30: 132.7 | FN30: 135.4 | FO30: 137.6 | FP30: 132.4 | FQ30: 135.2 | FR30: 138.3 | FS30: 133.5 | FT30: 136.1 | FU30: 140 | FV30: 134.8 | FW30: 137.6 | FX30: 139.8 | FY30: 134.1 | FZ30: 137.2 | GA30: 139.3 | GB30: 134.1 | GC30: 136.9 | GD30: 138.5 | GE30: 134 | GF30: 136.4 | GG30: 138.7 | GH30: 134 | GI30: 136.5 | GJ30: 139.1 | GK30: 134.8 | GL30: 137.1 | GM30: 139.8 | GN30: 135.4 | GO30: 137.8 | GP30: 140.5 | GQ30: 136.2 | GR30: 138.5 | GS30: 141.8 | GT30: 137.5 | GU30: 139.8 | GV30: 142.5 | GW30: 138 | GX30: 140.4 | GY30: 142.1 | GZ30: 138.1 | HA30: 140.2 | HB30: 142.2 | HC30: 138.9 | HD30: 140.8 | HE30: 142.4 | HF30: 139 | HG30: 140.8 | HH30: 141.9 | HI30: 138 | HJ30: 140.1 | HK30: 141 | HL30: 138 | HM30: 139.6 | HN30: 141 | HO30: 138.6 | HP30: 139.9 | HQ30: 141.2 | HR30: 139.5 | HS30: 140.4 | HT30: 142.4 | HU30: 141.5 | HV30: 142 | HW30: 143.6 | HX30: 142.1 | HY30: 142.9 | HZ30: 144.9 | IA30: 143.3 | IB30: 144.2 | IC30: 145.7 | ID30: 144.2 | IE30: 145 | IF30: 146.7 | IG30: 144.7 | IH30: 145.8 | II30: 148.3 | IJ30: 146 | IK30: 147.2 | IL30: 149.9 | IM30: 147 | IN30: 148.6 | IO30: 152.3 | IP30: 148.3 | IQ30: 150.4 | IR30: 151.9 | IS30: 148.2 | IT30: 150.2 | IU30: 150.4 | IV30: 147.7 | IW30: 149.1 | IX30: 149.8 | IY30: 147.3 | IZ30: 148.6 | JA30: NA | JB30: NA | JC30: NA | JD30: NA | JE30: NA | JF30: NA | JG30: 152.7 | JH30: 150.8 | JI30: 151.8 | JJ30: 152.7 | JK30: 150.8 | JL30: 151.8 | JM30: 154.7 | JN30: 152.9 | JO30: 153.9 | JP30: 155.4 | JQ30: 154 | JR30: 154.7 | JS30: 157.5 | JT30: 155.2 | JU30: 156.4 | JV30: 159.8 | JW30: 156.7 | JX30: 158.4 | JY30: 160.7 | JZ30: 156.9 | KA30: 158.9 | KB30: 158.5 | KC30: 156 | KD30: 157.3 | KE30: 156.7 | KF30: 156.5 | KG30: 156.6 | KH30: 156.7 | KI30: 156.9 | KJ30: 156.8 | KK30: 157.6 | KL30: 158 | KM30: 157.8 | KN30: 161.1 | KO30: 159.5 | KP30: 160.4 | KQ30: 162.1 | KR30: 160.4 | KS30: 161.3 | KT30: 163.2 | KU30: 161.8 | KV30: 162.5 | KW30: 163.6 | KX30: 162.3 | KY30: 163.2 | KZ30: 164 | LA30: 162.3 | LB30: 163.2 | LC30: 166.3 | LD30: 164.6 | LE30: 165.5 | LF30: 167.6 | LG30: 165.6 | LH30: 166.7 | LI30: 167 | LJ30: 165.2 | LK30: 166.2 | LL30: 166.4 | LM30: 165 | LN30: 165.7 | LO30: 166.7 | LP30: 165.5 | LQ30: 166.1 | LR30: 168.7 | LS30: 166.5 | LT30: 167.7 | LU30: 170.8 | LV30: 169.2 | LW30: 170.1 | LX30: 172.5 | LY30: 170.8 | LZ30: 171.7 | MA30: 173.6 | MB30: 171.4 | MC30: 172.6 | MD30: 174.3 | ME30: 172.3 | MF30: 173.4 | MG30: 175.3 | MH30: 173.1 | MI30: 174.3 | MJ30: 176.4 | MK30: 174.1 | ML30: 175.3 | MM30: 177.9 | MN30: 175.3 | MO30: 176.7 | MP30: 177.8 | MQ30: 174.1 | MR30: 176.5 | MS30: 177.1 | MT30: 174.1 | MU30: 175.7 | MV30: 177.8 | MW30: 174.9 | MX30: 176.5 | MY30: 178 | MZ30: 176.3 | NA30: 177.2 | NB30: 178 | NC30: 176.3 | ND30: 177.2 | NE30: 178.8 | NF30: 177.4 | NG30: 178.1 | NH30: 179.8 | NI30: 178.2 | NJ30: 179.1
C31: TOTAL | E31: =SUM(E21:E30) -> 8621.9 | F31: =E31/$E$31 -> 1
NA32: =SUM(NA4:NA13) -> 1736.8
M38: 2017-18 | N38: 2018-19
M39: =(ES30-GC30)/ES30 -> -0.050652341 | N39: =(GC30-HM30)/GC30 -> -0.019722425
M41: =(135-130)/130 -> 0.038461538

Sheet NOTES
A1: NOTES
C4: Categories | D4: BUCKETS | J4: Categories | K4: Short Forms
C5: Cereals and products | D5: Food | J5: Cereals and products | K5: C & P
C6: Meat and fish | D6: Food | J6: Meat and fish | K6: M & F | N6: FORMULA USED
C7: Egg | D7: Food | J7: Egg | K7: Egg
C8: Milk and products | D8: Food | J8: Milk and products | K8: M & P | N8: QUES -1 | O8: "SUMIF(Sheet3!$B$4:$B$29,QUES_1!$C8,Sheet3!$C$4:$C$29)"
C9: Oils and fats | D9: Food | J9: Oils and fats | K9: O & F | N9: QUES -2 | O9: (CURRENT YEAR - PREVIOUS YEAR) / PREVIOUS YEAR
C10: Fruits | D10: Food | J10: Fruits | K10: Fruits | N10: QUES -3 | O10: (CURRENT MONTH - PREVIOUS MONTH) / PREVIOUS MONTH
C11: Vegetables | D11: Food | J11: Vegetables | K11: Vegetables | N11: QUES -4 | O11: (AVG CURRENT - AVG PRE) / AVG pre
C12: Pulses and products | D12: Food | J12: Pulses and products | K12: P & P | N12: QUES -5 | O12: CORRELATION
C13: Sugar and Confectionery | D13: Food | J13: Sugar and Confectionery | K13: S & G
C14: Spices | D14: Food | J14: Spices | K14: Spices
C15: Non-alcoholic beverages | D15: Beverages and Intoxicants | J15: Non-alcoholic beverages | K15: Non- AB
C16: Prepared meals, snacks, sweets etc. | D16: Beverages and Intoxicants | J16: Prepared meals, snacks, sweets etc. | K16: P, M & S,S
C17: Food and beverages | D17: Beverages and Intoxicants | J17: Food and beverages | K17: F & B
C18: Pan, tobacco and intoxicants | J18: Pan, tobacco and intoxicants | K18: P , T & I
C19: Clothing | D19: Clothing and Housing | J19: Clothing | K19: Clothing
C20: Footwear | D20: Clothing and Housing | J20: Footwear | K20: Footwear
C21: Clothing and footwear | D21: Clothing and Housing | J21: Clothing and footwear | K21: C & F
C22: Housing | D22: Clothing and Housing | J22: Housing | K22: Housing
C23: Fuel and light | D23: Clothing and Housing | J23: Fuel and light | K23: F & L
C24: Household goods and services | D24: Goods, Services and Transport | J24: Household goods and services | K24: H G & S
C25: Health | D25: Goods, Services and Transport | J25: Health | K25: Health
C26: Personal care and effects | D26: Goods, Services and Transport | J26: Transport and communication | K26: T & C
C27: Transport and communication | D27: Social and Miscellaneous | J27: Recreation and amusement | K27: R & A
C28: Recreation and amusement | D28: Social and Miscellaneous | J28: Education | K28: Education
C29: Education | D29: Social and Miscellaneous | J29: Personal care and effects | K29: P C & E
C30: Miscellaneous | D30: Social and Miscellaneous | J30: Miscellaneous | K30: MSC
C31: TOTAL
E32: Short Forms
C33: BUCKETS----------------------------> | D33: FOOD | E33: FOOD
D34: Beverages and Intoxicants | E34: B&I
D35: Clothing and Housing | E35: C&H
D36: Goods, Services and Transport | E36: G&S,T
D37: Social and Miscellaneous | E37: S&M

Sheet QUES_1
B2: QUES : | C2: Which broader category has the highest contribution towards towards CPI calculation in jan 2013
C5: DATE: 2013 JAN
C7: CATEGORIES | D7: RURAL | E7: URBAN | F7: RURAL+URBAN | G7: RURAl | H7: URBAN | I7: RURAL+URBAN
C8: FOOD | D8: =SUMIF(Sheet3!$B$4:$B$29,QUES_1!$C8,Sheet3!$C$4:$C$29) -> 1054.7 | E8: =SUMIF(Sheet3!$B$4:$B$29,QUES_1!$C8,Sheet3!$D$4:$D$29) -> 1057.5 | F8: =SUMIF(Sheet3!$B$4:$B$29,QUES_1!$C8,Sheet3!$E$4:$E$29) -> 1055.5 | G8: =D8/$D$13 -> 0.40117916 | H8: =E8/$E$13 -> 0.40291854 | I8: =F8/$F$13 -> 0.13220687
C9: B&I | D9: 422.1 | E9: 424.1 | F9: 422.9 | G9: =D9/$D$13 -> 0.16055534 | H9: =E9/$E$13 -> 0.16158653 | I9: =F9/$F$13 -> 0.052970427
C10: C&H | D10: 424.2 | E10: 416.5 | F10: 318 | G10: =D10/$D$13 -> 0.16135413 | H10: =E10/$E$13 -> 0.15869085 | I10: =F10/$F$13 -> 0.039831156
C11: G&S,T | D11: 313.5 | E11: 313.2 | F11: 2115.1 | G11: =D11/$D$13 -> 0.11924686 | H11: =E11/$E$13 -> 0.11933247 | I11: =F11/$F$13 -> 0.26492729
C12: S&M | D12: 414.5 | E12: 413.3 | F12: 4072.2 | G12: =D12/$D$13 -> 0.15766451 | H12: =E12/$E$13 -> 0.15747161 | I12: =F12/$F$13 -> 0.51006426
C13: Sum | D13: =SUBTOTAL(109,QUES_1!$D$8:$D$12) -> 2629 | E13: =SUBTOTAL(109,QUES_1!$E$8:$E$12) -> 2624.6 | F13: =SUBTOTAL(109,QUES_1!$F$8:$F$12) -> 7983.7 | G13: =D13/$D$13 -> 1 | H13: =E13/$E$13 -> 1 | I13: =F13/$F$13 -> 1
C19: INSIGHTS
C20: > By our analysis we found that the food category has the highest contribution towards CPI calculation
C21: in all Rural and Urban area.
C23: > GOODS, Services and Trasport has lowest contribution towards CPI calculation in Rural and Urban area.
C25: > Urban and Rural consumption patterns are identical in all categories except when aggregated R+U
C26: , where B&I drops sharply
C28: > Goods, Services & Transport (31%) and Social & misc (38%) are key drivers in the combined Rural+Urban segment.
C30: > Beverages & Intoxicants contribute only 2% to overall Rural+Urban spending, despite being 16% in individual segments.

Sheet QUES_2
B2: QUES: | C2: Create a graph depicting the growth rate Y-o-Y and identify the year with highlight the
C3: reason why the year has the highest inflation | X3: Possible Reasons for High Inflation in 2019
C5: Y-O-Y | D5: growth per year | X5: 1. Food Price Surge
C6: 2017 | D6: 0.05295472 | X6: Vegetable prices (especially onions) spiked sharply in 2019 due to supply disruptions, delayed monsoons, and crop damage.
C7: 2018 | D7: 0.023374726 | X7: According to RBI and MoSPI reports, food inflation rose from near 0% to over 10% by late 2019.
C8: 2019 | D8: 0.077363897
C9: 2020 | D9: 0.05792277 | X9: 2. Crude Oil Prices
C10: 2021 | D10: 0.056579784
C11: 2022 | D11: 0.06035003 | X11: Global crude oil prices were relatively high and volatile in 2019.
C12: 2023 | D12: 0.014730878 | X12: India, being a major oil importer, saw pass-through effects on fuel and transportation costs, which in turn affected overall prices.
C14: INSIGHTS | X14: 3. Weak Rupee
C16: 1-> Inflation peaked in 2019 at 7.74%, the highest during the 2017–2023 period. | X16: The INR depreciated against the USD during parts of 2019, making imports (including oil and raw materials) more expensive.
C18: 3-> After a dip in 2018 to 2.34%, inflation surged dramatically the following year. | X18: 4. Low Base Effect
C20: 4-> From 2020 to 2022, inflation remained relatively stable between 5.66% and 6.04%. | X20: 2018 had unusually low inflation (2.34%), so even a moderate rise in prices in 2019 looked large in YoY terms.
C22: 4-> Inflation more than tripled from 2018 (2.34%) to 2019 (7.74%), indicating a sudden economic pressure spike | X22: 5. Supply-Side Constraints
X24: Issues like floods in some states, delayed harvests, and poor logistics contributed to supply bottlenecks, especially in perishable categories.
C25: NOTES: | D25: For 2023, we only have data of 3 months, from January to March, that is why its inflation rate is low.

Sheet QUES_3
L2: 2020 JUNE TO 2023 MAY
B3: QUES: | X3: Absolute change in inflation | Z3: MONTHS | AA3: Rural+Uraban | AB3: Rural | AC3: Urban
Z4: June | AA4: 0.011188811 | AB4: 0.010220865 | AC4: 0.012347097
K5: MONTHS | L5: Rural+Urban | M5: Inflation rate | O5: MONTHS | P5: Rural | Q5: Inflation rate | S5: MONTHS | T5: Urban | U5: Inflation Rate | X5: Rural + Urban: | Z5: July | AA5: 0.0014407561 | AB5: 0.0015118037 | AC5: 0.0010778307
